Workbook

Sheet Dashboard Mensual
B1: =CONCATENATE("BIOWELLNESS — Dashboard de Gestión · ",Parámetros!C5) -> BIOWELLNESS — Dashboard de Gestión · Agosto 2026
B2: Resumen del mes para Andrés y socios · se actualiza solo
B4: INGRESOS WELLNESS (ARS) | D4: INGRESOS (USD) | F4: RESULTADO TOTAL (ARS) | H4: MARGEN | J4: MRR MEMBRESÍAS (USD) | L4: OCUPACIÓN PROM.
B5: =SUMIFS('Caja Diaria'!$F$4:$F$403,'Caja Diaria'!$B$4:$B$403,"Ingreso") -> 5836500 | D5: =SUMIFS('Caja Diaria'!$F$4:$F$403,'Caja Diaria'!$B$4:$B$403,"Ingreso")/Parámetros!$C$8 -> 3891 | F5: =C20 -> -6187250 | H5: =C21 -> -1.137197 | J5: ='Membresías & Combos'!$E$16 -> 13214 | L5: =IF(SUMPRODUCT(Parámetros!$E$15:$E$27)=0,0,SUMPRODUCT(COUNTIF(Sesiones!$B$4:$B$903,Parámetros!$B$15:$B$27))/SUMPRODUCT(Parámetros!$E$15:$E$27)) -> 0.0014814815
B8: Estado de Resultados del mes (para socios) | H8: Mix de ingresos por línea
B9: Concepto | C9: ARS | D9: USD | H9: Línea | I9: ARS | J9: % del total
B10: Membresías | C10: =SUMIFS('Caja Diaria'!$F$4:$F$403,'Caja Diaria'!$B$4:$B$403,"Ingreso",'Caja Diaria'!$C$4:$C$403,"Membresías") -> 2628000 | D10: =C10/Parámetros!$C$8 -> 1752 | H10: Membresías | I10: =SUMIFS('Caja Diaria'!$F$4:$F$403,'Caja Diaria'!$B$4:$B$403,"Ingreso",'Caja Diaria'!$C$4:$C$403,"Membresías") -> 2628000 | J10: =IF($I$15=0,0,I10/$I$15) -> 0.45026985
B11: Sueltas & Combos | C11: =SUMIFS('Caja Diaria'!$F$4:$F$403,'Caja Diaria'!$B$4:$B$403,"Ingreso",'Caja Diaria'!$C$4:$C$403,"Sueltas & Combos") -> 606000 | D11: =C11/Parámetros!$C$8 -> 404 | H11: Sueltas & Combos | I11: =SUMIFS('Caja Diaria'!$F$4:$F$403,'Caja Diaria'!$B$4:$B$403,"Ingreso",'Caja Diaria'!$C$4:$C$403,"Sueltas & Combos") -> 606000 | J11: =IF($I$15=0,0,I11/$I$15) -> 0.10382935
B12: Paquetes | C12: =SUMIFS('Caja Diaria'!$F$4:$F$403,'Caja Diaria'!$B$4:$B$403,"Ingreso",'Caja Diaria'!$C$4:$C$403,"Paquetes") -> 2227500 | D12: =C12/Parámetros!$C$8 -> 1485 | H12: Paquetes | I12: =SUMIFS('Caja Diaria'!$F$4:$F$403,'Caja Diaria'!$B$4:$B$403,"Ingreso",'Caja Diaria'!$C$4:$C$403,"Paquetes") -> 2227500 | J12: =IF($I$15=0,0,I12/$I$15) -> 0.38164996
B13: IV + Terapias Biológicas | C13: =SUMIFS('Caja Diaria'!$F$4:$F$403,'Caja Diaria'!$B$4:$B$403,"Ingreso",'Caja Diaria'!$C$4:$C$403,"IV + Terapias Biológicas") -> 375000 | D13: =C13/Parámetros!$C$8 -> 250 | H13: IV + Terapias Biológicas | I13: =SUMIFS('Caja Diaria'!$F$4:$F$403,'Caja Diaria'!$B$4:$B$403,"Ingreso",'Caja Diaria'!$C$4:$C$403,"IV + Terapias Biológicas") -> 375000 | J13: =IF($I$15=0,0,I13/$I$15) -> 0.064250835
B14: Otros | C14: =SUMIFS('Caja Diaria'!$F$4:$F$403,'Caja Diaria'!$B$4:$B$403,"Ingreso",'Caja Diaria'!$C$4:$C$403,"Otros") -> 0 | D14: =C14/Parámetros!$C$8 -> 0 | H14: Otros | I14: =SUMIFS('Caja Diaria'!$F$4:$F$403,'Caja Diaria'!$B$4:$B$403,"Ingreso",'Caja Diaria'!$C$4:$C$403,"Otros") -> 0 | J14: =IF($I$15=0,0,I14/$I$15) -> 0
B15: INGRESOS WELLNESS (cobrado) | C15: =SUMIFS('Caja Diaria'!$F$4:$F$403,'Caja Diaria'!$B$4:$B$403,"Ingreso") -> 5836500 | D15: =C15/Parámetros!$C$8 -> 3891 | H15: TOTAL | I15: =SUM(I10:I14) -> 5836500 | J15: =SUM(J10:J14) -> 1
B16: (–) Gastos operativos del mes | C16: =-'Gastos del Mes'!$C$21 -> -12398750 | D16: =C16/Parámetros!$C$8 -> -8265.8333
B17: (–) Egresos de caja chica | C17: =-SUMIFS('Caja Diaria'!$F$4:$F$403,'Caja Diaria'!$B$4:$B$403,"Egreso") -> -75000 | D17: =C17/Parámetros!$C$8 -> -50
B18: RESULTADO WELLNESS (EBITDA) | C18: =SUMIFS('Caja Diaria'!$F$4:$F$403,'Caja Diaria'!$B$4:$B$403,"Ingreso")-'Gastos del Mes'!$C$21-SUMIFS('Caja Diaria'!$F$4:$F$403,'Caja Diaria'!$B$4:$B$403,"Egreso") -> -6637250 | D18: =C18/Parámetros!$C$8 -> -4424.8333
B19: (+) Bar — resultado neto (manual) | C19: 450000 | D19: =C19/Parámetros!$C$8 -> 300
B20: RESULTADO TOTAL DEL NEGOCIO | C20: =C18+C19 -> -6187250 | D20: =C20/Parámetros!$C$8 -> -4124.8333
B21: Margen operativo (wellness) | C21: =IF(C15=0,0,C18/C15) -> -1.137197
B26: Utilización por recurso (mes)
B27: Recurso | C27: Sesiones | D27: % utilización
B28: HBOT Monoplaza | C28: =COUNTIF(Sesiones!$B$4:$B$903,B28) -> 2 | D28: =IF(Parámetros!$E$15=0,0,C28/Parámetros!$E$15) -> 0.0066666667
B29: HBOT Biplaza | C29: =COUNTIF(Sesiones!$B$4:$B$903,B29) -> 0 | D29: =IF(Parámetros!$E$16=0,0,C29/Parámetros!$E$16) -> 0
B30: HBOT Multiplaza | C30: =COUNTIF(Sesiones!$B$4:$B$903,B30) -> 1 | D30: =IF(Parámetros!$E$17=0,0,C30/Parámetros!$E$17) -> 0.0033333333
B31: IHHT 1 | C31: =COUNTIF(Sesiones!$B$4:$B$903,B31) -> 1 | D31: =IF(Parámetros!$E$18=0,0,C31/Parámetros!$E$18) -> 0.0016666667
B32: IHHT 2 | C32: =COUNTIF(Sesiones!$B$4:$B$903,B32) -> 1 | D32: =IF(Parámetros!$E$19=0,0,C32/Parámetros!$E$19) -> 0.0016666667
B33: Recovery Pro Gab 1 | C33: =COUNTIF(Sesiones!$B$4:$B$903,B33) -> 1 | D33: =IF(Parámetros!$E$20=0,0,C33/Parámetros!$E$20) -> 0.0033333333
B34: Recovery Pro Gab 2 | C34: =COUNTIF(Sesiones!$B$4:$B$903,B34) -> 0 | D34: =IF(Parámetros!$E$21=0,0,C34/Parámetros!$E$21) -> 0
B35: Red Light | C35: =COUNTIF(Sesiones!$B$4:$B$903,B35) -> 1 | D35: =IF(Parámetros!$E$22=0,0,C35/Parámetros!$E$22) -> 0.0016666667
B36: Compresión (IPC06) | C36: =COUNTIF(Sesiones!$B$4:$B$903,B36) -> 0 | D36: =IF(Parámetros!$E$23=0,0,C36/Parámetros!$E$23) -> 0
B37: Crio (COT03) | C37: =COUNTIF(Sesiones!$B$4:$B$903,B37) -> 0 | D37: =IF(Parámetros!$E$24=0,0,C37/Parámetros!$E$24) -> 0
B38: Camilla masajes | C38: =COUNTIF(Sesiones!$B$4:$B$903,B38) -> 0 | D38: =IF(Parámetros!$E$25=0,0,C38/Parámetros!$E$25) -> 0
B39: Consultorio médico | C39: =COUNTIF(Sesiones!$B$4:$B$903,B39) -> 0 | D39: =IF(Parámetros!$E$26=0,0,C39/Parámetros!$E$26) -> 0
B40: Sala TB / IV | C40: =COUNTIF(Sesiones!$B$4:$B$903,B40) -> 1 | D40: =IF(Parámetros!$E$27=0,0,C40/Parámetros!$E$27) -> 0.0033333333
B42: Distribución del resultado por socio | G42: Referencia: reparto bruto del resultado total. No descuenta reservas/CAPEX. Validar con Andrés.
B43: Socio | C43: % | D43: Parte (ARS)
B44: Andrés Aizenberg | C44: 0.53 | D44: =C44*$C20 -> -3279242.5
B45: Diego | C45: 0.24 | D45: =C45*$C20 -> -1484940
B46: Daniel Tognetti | C46: 0.09 | D46: =C46*$C20 -> -556852.5
B47: Evangelina Varela | C47: 0.06 | D47: =C47*$C20 -> -371235
B48: Julián Massetti | C48: 0.05 | D48: =C48*$C20 -> -309362.5
B49: Fernando Aldazabal | C49: 0.02 | D49: =C49*$C20 -> -123745
B50: Diego Sívori | C50: 0.01 | D50: =C50*$C20 -> -61872.5
B51: TOTAL | C51: =SUM(C44:C50) -> 1 | D51: =SUM(D44:D50) -> -6187250
B53: Comparativo vs. mes anterior
B54: Ingresos mes anterior (ARS) → | C54: 0
B55: Variación de ingresos | C55: =IF(C54=0,0,(SUMIFS('Caja Diaria'!$F$4:$F$403,'Caja Diaria'!$B$4:$B$403,"Ingreso")-C54)/C54) -> 0
B57: Análisis automático del mes
B58: =IF(C20>0,CONCATENATE("✔ El mes cerró POSITIVO: resultado total de ",TEXT(C20,"#,##0")," ARS (",TEXT(C21,"0.0%")," de margen)."),CONCATENATE("✖ El mes cerró NEGATIVO: ",TEXT(C20,"#,##0")," ARS. Revisar gastos e ingresos.")) -> ✖ El mes cerró NEGATIVO: -6,187,250 ARS. Revisar gastos e ingresos.
B59: =IF(C54=0,"• Cargá el mes anterior para ver la tendencia.",IF((SUMIFS('Caja Diaria'!$F$4:$F$403,'Caja Diaria'!$B$4:$B$403,"Ingreso")-C54)/C54>=0,CONCATENATE("• Ingresos SUBIERON ",TEXT((SUMIFS('Caja Diaria'!$F$4:$F$403,'Caja Diaria'!$B$4:$B$403,"Ingreso")-C54)/C54,"0.0%")," vs. el mes pasado."),CONCATENATE("• Ingresos BAJARON ",TEXT(ABS((SUMIFS('Caja Diaria'!$F$4:$F$403,'Caja Diaria'!$B$4:$B$403,"Ingreso")-C54)/C54),"0.0%")," vs. el mes pasado."))) -> • Cargá el mes anterior para ver la tendencia.
B60: =CONCATENATE("• MRR de membresías: ",TEXT('Membresías & Combos'!$E$16,"#,##0")," USD/mes con ",TEXT('Membresías & Combos'!$C$16,"0")," socios activos.") -> • MRR de membresías: 13,214 USD/mes con 10 socios activos.
B61: =CONCATENATE("• Recurso MÁS usado: ",INDEX(B28:B40,MATCH(MAX(D28:D40),D28:D40,0))," (",TEXT(MAX(D28:D40),"0.0%"),"). Menos usado: ",INDEX(B28:B40,MATCH(MIN(D28:D40),D28:D40,0))," (",TEXT(MIN(D28:D40),"0.0%"),").") -> • Recurso MÁS usado: HBOT Monoplaza (0.7%). Menos usado: HBOT Biplaza (0.0%).
B62: =IF(C21<0.2,"⚠ Margen por debajo del 20% objetivo: revisar pricing o costos.","✔ Margen saludable (≥20%).") -> ⚠ Margen por debajo del 20% objetivo: revisar pricing o costos.
B65: Formas de pago del mes | G65: Detalle diario y anual: ver pestaña 'Formas de Pago'.
B66: Método | C66: Monto ARS | D66: % del total
B67: Efectivo | C67: ='Formas de Pago'!C6 -> 543000 | D67: ='Formas de Pago'!E6 -> 0.093035209
B68: Tarjeta débito | C68: ='Formas de Pago'!C7 -> 0 | D68: ='Formas de Pago'!E7 -> 0
B69: Tarjeta crédito | C69: ='Formas de Pago'!C8 -> 2665500 | D69: ='Formas de Pago'!E8 -> 0.45669494
B70: Transferencia | C70: ='Formas de Pago'!C9 -> 0 | D70: ='Formas de Pago'!E9 -> 0
B71: MercadoPago | C71: ='Formas de Pago'!C10 -> 2628000 | D71: ='Formas de Pago'!E10 -> 0.45026985
B72: TOTAL | C72: =SUM(C67:C71) -> 5836500 | D72: =SUM(D67:D71) -> 1
B73: =CONCATENATE("• Forma de pago principal: ",INDEX(B67:B71,MATCH(MAX(D67:D71),D67:D71,0))," (",TEXT(MAX(D67:D71),"0.0%")," de la facturación).") -> • Forma de pago principal: Tarjeta crédito (45.7% de la facturación).

Sheet Parámetros
B1: BIOWELLNESS — Tablero de Gestión Mensual | J1: LISTAS (no tocar)
B2: Parámetros · editá solo las celdas en AZUL / fondo amarillo | J2: Membresías | K2: Efectivo | L2: Insumos menores | M2: Ingreso | N2: HBOT Monoplaza
J3: Sueltas & Combos | K3: Tarjeta débito | L3: Limpieza | M3: Egreso | N3: HBOT Biplaza
B4: General | J4: Paquetes | K4: Tarjeta crédito | L4: Viáticos | N4: HBOT Multiplaza
B5: Mes | C5: Agosto 2026 | J5: IV + Terapias Biológicas | K5: Transferencia | L5: Mantenimiento menor | N5: IHHT 1
B6: Año | C6: 2026 | J6: Otros | K6: MercadoPago | L6: Varios | N6: IHHT 2
B7: Mes (número) | C7: 8 | D7: 1=Ene ... 12=Dic | N7: Recovery Pro Gab 1
B8: Tipo de cambio (ARS por USD) | C8: 1500 | D8: Editable cada mes | N8: Recovery Pro Gab 2
B9: Días operativos del mes | C9: 25 | N9: Red Light
B10: Horas operativas por día | C10: 12 | D10: Ej. 9:00-21:00 | N10: Compresión (IPC06)
B11: Saldo inicial caja chica (ARS) | C11: 0 | D11: Efectivo físico al arrancar el mes | N11: Crio (COT03)
N12: Camilla masajes
B13: Recursos físicos y capacidad | D13: (Slots/día y capacidad se calculan solos) | N13: Consultorio médico
B14: Recurso | C14: Duración (min) | D14: Slots / día | E14: Capacidad mensual | N14: Sala TB / IV
B15: HBOT Monoplaza | C15: 60 | D15: =INT(($C$10*60)/C15) -> 12 | E15: =D15*$C$9 -> 300
B16: HBOT Biplaza | C16: 60 | D16: =INT(($C$10*60)/C16) -> 12 | E16: =D16*$C$9 -> 300
B17: HBOT Multiplaza | C17: 60 | D17: =INT(($C$10*60)/C17) -> 12 | E17: =D17*$C$9 -> 300
B18: IHHT 1 | C18: 30 | D18: =INT(($C$10*60)/C18) -> 24 | E18: =D18*$C$9 -> 600
B19: IHHT 2 | C19: 30 | D19: =INT(($C$10*60)/C19) -> 24 | E19: =D19*$C$9 -> 600
B20: Recovery Pro Gab 1 | C20: 60 | D20: =INT(($C$10*60)/C20) -> 12 | E20: =D20*$C$9 -> 300
B21: Recovery Pro Gab 2 | C21: 60 | D21: =INT(($C$10*60)/C21) -> 12 | E21: =D21*$C$9 -> 300
B22: Red Light | C22: 30 | D22: =INT(($C$10*60)/C22) -> 24 | E22: =D22*$C$9 -> 600
B23: Compresión (IPC06) | C23: 30 | D23: =INT(($C$10*60)/C23) -> 24 | E23: =D23*$C$9 -> 600
B24: Crio (COT03) | C24: 30 | D24: =INT(($C$10*60)/C24) -> 24 | E24: =D24*$C$9 -> 600
B25: Camilla masajes | C25: 60 | D25: =INT(($C$10*60)/C25) -> 12 | E25: =D25*$C$9 -> 300
B26: Consultorio médico | C26: 60 | D26: =INT(($C$10*60)/C26) -> 12 | E26: =D26*$C$9 -> 300
B27: Sala TB / IV | C27: 60 | D27: =INT(($C$10*60)/C27) -> 12 | E27: =D27*$C$9 -> 300
B28: Nota: Recovery Pro Gab 1 y 2 comparten 2 tumbonas Red Light (Regla R-07). Ajustá Slots/día si hace falta.

Sheet Caja Diaria
A1: Caja Diaria — ingresos cobrados y egresos de caja chica
A2: Una fila por movimiento de plata. El Bar NO va acá (es unidad aparte). USD se calcula solo.
A3: Fecha | B3: Tipo | C3: Línea / Categoría | D3: Detalle | E3: Método de pago | F3: Monto ARS | G3: Monto USD
A4: 46237 | B4: Ingreso | C4: Membresías | D4: PRIME Standard - J. Perez | E4: MercadoPago | F4: 2628000 | G4: =IF(F4="","",F4/Parámetros!$C$8) -> 1752
A5: 46237 | B5: Ingreso | C5: Sueltas & Combos | D5: BIO RECOVERY - M. Gomez | E5: Tarjeta crédito | F5: 438000 | G5: =IF(F5="","",F5/Parámetros!$C$8) -> 292
A6: 46237 | B6: Ingreso | C6: IV + Terapias Biológicas | D6: IV NAD+ - L. Ruiz | E6: Efectivo | F6: 375000 | G6: =IF(F6="","",F6/Parámetros!$C$8) -> 250
A7: 46237 | B7: Egreso | C7: Insumos menores | D7: Cánulas y guantes | E7: Efectivo | F7: 45000 | G7: =IF(F7="","",F7/Parámetros!$C$8) -> 30
A8: 46238 | B8: Ingreso | C8: Paquetes | D8: Paquete 10 HBOT - A. Diaz | E8: Tarjeta crédito | F8: 2227500 | G8: =IF(F8="","",F8/Parámetros!$C$8) -> 1485
A9: 46238 | B9: Ingreso | C9: Sueltas & Combos | D9: BIO ENERGY - S. Mora | E9: Efectivo | F9: 168000 | G9: =IF(F9="","",F9/Parámetros!$C$8) -> 112
A10: 46238 | B10: Egreso | C10: Limpieza | D10: Artículos de limpieza | E10: Efectivo | F10: 30000 | G10: =IF(F10="","",F10/Parámetros!$C$8) -> 20
G11: =IF(F11="","",F11/Parámetros!$C$8)
G12: =IF(F12="","",F12/Parámetros!$C$8)
G13: =IF(F13="","",F13/Parámetros!$C$8)
G14: =IF(F14="","",F14/Parámetros!$C$8)
G15: =IF(F15="","",F15/Parámetros!$C$8)
G16: =IF(F16="","",F16/Parámetros!$C$8)
G17: =IF(F17="","",F17/Parámetros!$C$8)
G18: =IF(F18="","",F18/Parámetros!$C$8)
G19: =IF(F19="","",F19/Parámetros!$C$8)
G20: =IF(F20="","",F20/Parámetros!$C$8)
G21: =IF(F21="","",F21/Parámetros!$C$8)
G22: =IF(F22="","",F22/Parámetros!$C$8)
... G403: =IF(F403="","",F403/Parámetros!$C$8)

Sheet Sesiones
A1: Sesiones realizadas — uso de recursos (ocupación)
A2: Una fila por sesión realizada (la pague socio o no). Mide ocupación, no plata.
A3: Fecha | B3: Recurso | C3: Servicio / Combo | D3: Ocupantes | E3: ¿Socio? | F3: Paciente
A4: 46237 | B4: HBOT Monoplaza | C4: BIO RECOVERY | D4: 1 | E4: No | F4: M. Gomez
A5: 46237 | B5: Recovery Pro Gab 1 | C5: BIO RECOVERY | D5: 1 | E5: No | F5: M. Gomez
A6: 46237 | B6: Sala TB / IV | C6: IV NAD+ | D6: 1 | E6: No | F6: L. Ruiz
A7: 46237 | B7: HBOT Monoplaza | C7: FOCUS Standard | D7: 1 | E7: Sí | F7: J. Perez
A8: 46237 | B8: IHHT 1 | C8: FOCUS Standard | D8: 1 | E8: Sí | F8: J. Perez
A9: 46238 | B9: HBOT Multiplaza | C9: Suelta | D9: 3 | E9: No | F9: Grupo corp.
A10: 46238 | B10: Red Light | C10: BIO ENERGY | D10: 1 | E10: No | F10: S. Mora
A11: 46238 | B11: IHHT 2 | C11: BIO ENERGY | D11: 1 | E11: No | F11: S. Mora

Sheet Resumen Diario
A1: Resumen Diario — cierre de caja y % de utilización por recurso
A2: Se llena solo. 'Saldo acum. mes' = lo que generó el negocio en el mes hasta ese día. 'Saldo efectivo caja' = efectivo físico real (entra cash, sale caja chica).
A3: Día | B3: Ingresos ARS | C3: Egresos ARS | D3: Saldo del día | E3: Saldo acum. mes | F3: Saldo efectivo caja | G3: Ingresos USD | H3: HBOT Monoplaza | I3: HBOT Biplaza | J3: HBOT Multiplaza | K3: IHHT 1 | L3: IHHT 2 | M3: Recovery Pro Gab 1 | N3: Recovery Pro Gab 2 | O3: Red Light | P3: Compresión (IPC06) | Q3: Crio (COT03) | R3: Camilla masajes | S3: Consultorio médico | T3: Sala TB / IV
A4: =DATE(Parámetros!$C$6,Parámetros!$C$7,1) -> 46235 | B4: =SUMIFS('Caja Diaria'!$F$4:$F$403,'Caja Diaria'!$B$4:$B$403,"Ingreso",'Caja Diaria'!$A$4:$A$403,$A4) -> 0 | C4: =SUMIFS('Caja Diaria'!$F$4:$F$403,'Caja Diaria'!$B$4:$B$403,"Egreso",'Caja Diaria'!$A$4:$A$403,$A4) -> 0 | D4: =B4-C4 -> 0 | E4: =D4 -> 0 | F4: =Parámetros!$C$11+SUMIFS('Caja Diaria'!$F$4:$F$403,'Caja Diaria'!$B$4:$B$403,"Ingreso",'Caja Diaria'!$E$4:$E$403,"Efectivo",'Caja Diaria'!$A$4:$A$403,$A4)-SUMIFS('Caja Diaria'!$F$4:$F$403,'Caja Diaria'!$B$4:$B$403,"Egreso",'Caja Diaria'!$E$4:$E$403,"Efectivo",'Caja Diaria'!$A$4:$A$403,$A4) -> 0 | G4: =B4/Parámetros!$C$8 -> 0 | H4: =IF(Parámetros!$D$15=0,0,COUNTIFS(Sesiones!$A$4:$A$903,$A4,Sesiones!$B$4:$B$903,Parámetros!$B$15)/Parámetros!$D$15) -> 0 | I4: =IF(Parámetros!$D$16=0,0,COUNTIFS(Sesiones!$A$4:$A$903,$A4,Sesiones!$B$4:$B$903,Parámetros!$B$16)/Parámetros!$D$16) -> 0 | J4: =IF(Parámetros!$D$17=0,0,COUNTIFS(Sesiones!$A$4:$A$903,$A4,Sesiones!$B$4:$B$903,Parámetros!$B$17)/Parámetros!$D$17) -> 0 | K4: =IF(Parámetros!$D$18=0,0,COUNTIFS(Sesiones!$A$4:$A$903,$A4,Sesiones!$B$4:$B$903,Parámetros!$B$18)/Parámetros!$D$18) -> 0 | L4: =IF(Parámetros!$D$19=0,0,COUNTIFS(Sesiones!$A$4:$A$903,$A4,Sesiones!$B$4:$B$903,Parámetros!$B$19)/Parámetros!$D$19) -> 0 | M4: =IF(Parámetros!$D$20=0,0,COUNTIFS(Sesiones!$A$4:$A$903,$A4,Sesiones!$B$4:$B$903,Parámetros!$B$20)/Parámetros!$D$20) -> 0 | N4: =IF(Parámetros!$D$21=0,0,COUNTIFS(Sesiones!$A$4:$A$903,$A4,Sesiones!$B$4:$B$903,Parámetros!$B$21)/Parámetros!$D$21) -> 0 | O4: =IF(Parámetros!$D$22=0,0,COUNTIFS(Sesiones!$A$4:$A$903,$A4,Sesiones!$B$4:$B$903,Parámetros!$B$22)/Parámetros!$D$22) -> 0 | P4: =IF(Parámetros!$D$23=0,0,COUNTIFS(Sesiones!$A$4:$A$903,$A4,Sesiones!$B$4:$B$903,Parámetros!$B$23)/Parámetros!$D$23) -> 0 | Q4: =IF(Parámetros!$D$24=0,0,COUNTIFS(Sesiones!$A$4:$A$903,$A4,Sesiones!$B$4:$B$903,Parámetros!$B$24)/Parámetros!$D$24) -> 0 | R4: =IF(Parámetros!$D$25=0,0,COUNTIFS(Sesiones!$A$4:$A$903,$A4,Sesiones!$B$4:$B$903,Parámetros!$B$25)/Parámetros!$D$25) -> 0 | S4: =IF(Parámetros!$D$26=0,0,COUNTIFS(Sesiones!$A$4:$A$903,$A4,Sesiones!$B$4:$B$903,Parámetros!$B$26)/Parámetros!$D$26) -> 0 | T4: =IF(Parámetros!$D$27=0,0,COUNTIFS(Sesiones!$A$4:$A$903,$A4,Sesiones!$B$4:$B$903,Parámetros!$B$27)/Parámetros!$D$27) -> 0
A5: =DATE(Parámetros!$C$6,Parámetros!$C$7,2) -> 46236 | B5: =SUMIFS('Caja Diaria'!$F$4:$F$403,'Caja Diaria'!$B$4:$B$403,"Ingreso",'Caja Diaria'!$A$4:$A$403,$A5) -> 0 | C5: =SUMIFS('Caja Diaria'!$F$4:$F$403,'Caja Diaria'!$B$4:$B$403,"Egreso",'Caja Diaria'!$A$4:$A$403,$A5) -> 0 | D5: =B5-C5 -> 0 | E5: =E4+D5 -> 0 | F5: =F4+SUMIFS('Caja Diaria'!$F$4:$F$403,'Caja Diaria'!$B$4:$B$403,"Ingreso",'Caja Diaria'!$E$4:$E$403,"Efectivo",'Caja Diaria'!$A$4:$A$403,$A5)-SUMIFS('Caja Diaria'!$F$4:$F$403,'Caja Diaria'!$B$4:$B$403,"Egreso",'Caja Diaria'!$E$4:$E$403,"Efectivo",'Caja Diaria'!$A$4:$A$403,$A5) -> 0 | G5: =B5/Parámetros!$C$8 -> 0 | H5: =IF(Parámetros!$D$15=0,0,COUNTIFS(Sesiones!$A$4:$A$903,$A5,Sesiones!$B$4:$B$903,Parámetros!$B$15)/Parámetros!$D$15) -> 0 | I5: =IF(Parámetros!$D$16=0,0,COUNTIFS(Sesiones!$A$4:$A$903,$A5,Sesiones!$B$4:$B$903,Parámetros!$B$16)/Parámetros!$D$16) -> 0 | J5: =IF(Parámetros!$D$17=0,0,COUNTIFS(Sesiones!$A$4:$A$903,$A5,Sesiones!$B$4:$B$903,Parámetros!$B$17)/Parámetros!$D$17) -> 0 | K5: =IF(Parámetros!$D$18=0,0,COUNTIFS(Sesiones!$A$4:$A$903,$A5,Sesiones!$B$4:$B$903,Parámetros!$B$18)/Parámetros!$D$18) -> 0 | L5: =IF(Parámetros!$D$19=0,0,COUNTIFS(Sesiones!$A$4:$A$903,$A5,Sesiones!$B$4:$B$903,Parámetros!$B$19)/Parámetros!$D$19) -> 0 | M5: =IF(Parámetros!$D$20=0,0,COUNTIFS(Sesiones!$A$4:$A$903,$A5,Sesiones!$B$4:$B$903,Parámetros!$B$20)/Parámetros!$D$20) -> 0 | N5: =IF(Parámetros!$D$21=0,0,COUNTIFS(Sesiones!$A$4:$A$903,$A5,Sesiones!$B$4:$B$903,Parámetros!$B$21)/Parámetros!$D$21) -> 0 | O5: =IF(Parámetros!$D$22=0,0,COUNTIFS(Sesiones!$A$4:$A$903,$A5,Sesiones!$B$4:$B$903,Parámetros!$B$22)/Parámetros!$D$22) -> 0 | P5: =IF(Parámetros!$D$23=0,0,COUNTIFS(Sesiones!$A$4:$A$903,$A5,Sesiones!$B$4:$B$903,Parámetros!$B$23)/Parámetros!$D$23) -> 0 | Q5: =IF(Parámetros!$D$24=0,0,COUNTIFS(Sesiones!$A$4:$A$903,$A5,Sesiones!$B$4:$B$903,Parámetros!$B$24)/Parámetros!$D$24) -> 0 | R5: =IF(Parámetros!$D$25=0,0,COUNTIFS(Sesiones!$A$4:$A$903,$A5,Sesiones!$B$4:$B$903,Parámetros!$B$25)/Parámetros!$D$25) -> 0 | S5: =IF(Parámetros!$D$26=0,0,COUNTIFS(Sesiones!$A$4:$A$903,$A5,Sesiones!$B$4:$B$903,Parámetros!$B$26)/Parámetros!$D$26) -> 0 | T5: =IF(Parámetros!$D$27=0,0,COUNTIFS(Sesiones!$A$4:$A$903,$A5,Sesiones!$B$4:$B$903,Parámetros!$B$27)/Parámetros!$D$27) -> 0
A6: =DATE(Parámetros!$C$6,Parámetros!$C$7,3) -> 46237 | B6: =SUMIFS('Caja Diaria'!$F$4:$F$403,'Caja Diaria'!$B$4:$B$403,"Ingreso",'Caja Diaria'!$A$4:$A$403,$A6) -> 3441000 | C6: =SUMIFS('Caja Diaria'!$F$4:$F$403,'Caja Diaria'!$B$4:$B$403,"Egreso",'Caja Diaria'!$A$4:$A$403,$A6) -> 45000 | D6: =B6-C6 -> 3396000 | E6: =E5+D6 -> 3396000 | F6: =F5+SUMIFS('Caja Diaria'!$F$4:$F$403,'Caja Diaria'!$B$4:$B$403,"Ingreso",'Caja Diaria'!$E$4:$E$403,"Efectivo",'Caja Diaria'!$A$4:$A$403,$A6)-SUMIFS('Caja Diaria'!$F$4:$F$403,'Caja Diaria'!$B$4:$B$403,"Egreso",'Caja Diaria'!$E$4:$E$403,"Efectivo",'Caja Diaria'!$A$4:$A$403,$A6) -> 330000 | G6: =B6/Parámetros!$C$8 -> 2294 | H6: =IF(Parámetros!$D$15=0,0,COUNTIFS(Sesiones!$A$4:$A$903,$A6,Sesiones!$B$4:$B$903,Parámetros!$B$15)/Parámetros!$D$15) -> 0.16666667 | I6: =IF(Parámetros!$D$16=0,0,COUNTIFS(Sesiones!$A$4:$A$903,$A6,Sesiones!$B$4:$B$903,Parámetros!$B$16)/Parámetros!$D$16) -> 0 | J6: =IF(Parámetros!$D$17=0,0,COUNTIFS(Sesiones!$A$4:$A$903,$A6,Sesiones!$B$4:$B$903,Parámetros!$B$17)/Parámetros!$D$17) -> 0 | K6: =IF(Parámetros!$D$18=0,0,COUNTIFS(Sesiones!$A$4:$A$903,$A6,Sesiones!$B$4:$B$903,Parámetros!$B$18)/Parámetros!$D$18) -> 0.041666667 | L6: =IF(Parámetros!$D$19=0,0,COUNTIFS(Sesiones!$A$4:$A$903,$A6,Sesiones!$B$4:$B$903,Parámetros!$B$19)/Parámetros!$D$19) -> 0 | M6: =IF(Parámetros!$D$20=0,0,COUNTIFS(Sesiones!$A$4:$A$903,$A6,Sesiones!$B$4:$B$903,Parámetros!$B$20)/Parámetros!$D$20) -> 0.083333333 | N6: =IF(Parámetros!$D$21=0,0,COUNTIFS(Sesiones!$A$4:$A$903,$A6,Sesiones!$B$4:$B$903,Parámetros!$B$21)/Parámetros!$D$21) -> 0 | O6: =IF(Parámetros!$D$22=0,0,COUNTIFS(Sesiones!$A$4:$A$903,$A6,Sesiones!$B$4:$B$903,Parámetros!$B$22)/Parámetros!$D$22) -> 0 | P6: =IF(Parámetros!$D$23=0,0,COUNTIFS(Sesiones!$A$4:$A$903,$A6,Sesiones!$B$4:$B$903,Parámetros!$B$23)/Parámetros!$D$23) -> 0 | Q6: =IF(Parámetros!$D$24=0,0,COUNTIFS(Sesiones!$A$4:$A$903,$A6,Sesiones!$B$4:$B$903,Parámetros!$B$24)/Parámetros!$D$24) -> 0 | R6: =IF(Parámetros!$D$25=0,0,COUNTIFS(Sesiones!$A$4:$A$903,$A6,Sesiones!$B$4:$B$903,Parámetros!$B$25)/Parámetros!$D$25) -> 0 | S6: =IF(Parámetros!$D$26=0,0,COUNTIFS(Sesiones!$A$4:$A$903,$A6,Sesiones!$B$4:$B$903,Parámetros!$B$26)/Parámetros!$D$26) -> 0 | T6: =IF(Parámetros!$D$27=0,0,COUNTIFS(Sesiones!$A$4:$A$903,$A6,Sesiones!$B$4:$B$903,Parámetros!$B$27)/Parámetros!$D$27) -> 0.083333333
A7: =DATE(Parámetros!$C$6,Parámetros!$C$7,4) -> 46238 | B7: =SUMIFS('Caja Diaria'!$F$4:$F$403,'Caja Diaria'!$B$4:$B$403,"Ingreso",'Caja Diaria'!$A$4:$A$403,$A7) -> 2395500 | C7: =SUMIFS('Caja Diaria'!$F$4:$F$403,'Caja Diaria'!$B$4:$B$403,"Egreso",'Caja Diaria'!$A$4:$A$403,$A7) -> 30000 | D7: =B7-C7 -> 2365500 | E7: =E6+D7 -> 5761500 | F7: =F6+SUMIFS('Caja Diaria'!$F$4:$F$403,'Caja Diaria'!$B$4:$B$403,"Ingreso",'Caja Diaria'!$E$4:$E$403,"Efectivo",'Caja Diaria'!$A$4:$A$403,$A7)-SUMIFS('Caja Diaria'!$F$4:$F$403,'Caja Diaria'!$B$4:$B$403,"Egreso",'Caja Diaria'!$E$4:$E$403,"Efectivo",'Caja Diaria'!$A$4:$A$403,$A7) -> 468000 | G7: =B7/Parámetros!$C$8 -> 1597 | H7: =IF(Parámetros!$D$15=0,0,COUNTIFS(Sesiones!$A$4:$A$903,$A7,Sesiones!$B$4:$B$903,Parámetros!$B$15)/Parámetros!$D$15) -> 0 | I7: =IF(Parámetros!$D$16=0,0,COUNTIFS(Sesiones!$A$4:$A$903,$A7,Sesiones!$B$4:$B$903,Parámetros!$B$16)/Parámetros!$D$16) -> 0 | J7: =IF(Parámetros!$D$17=0,0,COUNTIFS(Sesiones!$A$4:$A$903,$A7,Sesiones!$B$4:$B$903,Parámetros!$B$17)/Parámetros!$D$17) -> 0.083333333 | K7: =IF(Parámetros!$D$18=0,0,COUNTIFS(Sesiones!$A$4:$A$903,$A7,Sesiones!$B$4:$B$903,Parámetros!$B$18)/Parámetros!$D$18) -> 0 | L7: =IF(Parámetros!$D$19=0,0,COUNTIFS(Sesiones!$A$4:$A$903,$A7,Sesiones!$B$4:$B$903,Parámetros!$B$19)/Parámetros!$D$19) -> 0.041666667 | M7: =IF(Parámetros!$D$20=0,0,COUNTIFS(Sesiones!$A$4:$A$903,$A7,Sesiones!$B$4:$B$903,Parámetros!$B$20)/Parámetros!$D$20) -> 0 | N7: =IF(Parámetros!$D$21=0,0,COUNTIFS(Sesiones!$A$4:$A$903,$A7,Sesiones!$B$4:$B$903,Parámetros!$B$21)/Parámetros!$D$21) -> 0 | O7: =IF(Parámetros!$D$22=0,0,COUNTIFS(Sesiones!$A$4:$A$903,$A7,Sesiones!$B$4:$B$903,Parámetros!$B$22)/Parámetros!$D$22) -> 0.041666667 | P7: =IF(Parámetros!$D$23=0,0,COUNTIFS(Sesiones!$A$4:$A$903,$A7,Sesiones!$B$4:$B$903,Parámetros!$B$23)/Parámetros!$D$23) -> 0 | Q7: =IF(Parámetros!$D$24=0,0,COUNTIFS(Sesiones!$A$4:$A$903,$A7,Sesiones!$B$4:$B$903,Parámetros!$B$24)/Parámetros!$D$24) -> 0 | R7: =IF(Parámetros!$D$25=0,0,COUNTIFS(Sesiones!$A$4:$A$903,$A7,Sesiones!$B$4:$B$903,Parámetros!$B$25)/Parámetros!$D$25) -> 0 | S7: =IF(Parámetros!$D$26=0,0,COUNTIFS(Sesiones!$A$4:$A$903,$A7,Sesiones!$B$4:$B$903,Parámetros!$B$26)/Parámetros!$D$26) -> 0 | T7: =IF(Parámetros!$D$27=0,0,COUNTIFS(Sesiones!$A$4:$A$903,$A7,Sesiones!$B$4:$B$903,Parámetros!$B$27)/Parámetros!$D$27) -> 0
A8: =DATE(Parámetros!$C$6,Parámetros!$C$7,5) -> 46239 | B8: =SUMIFS('Caja Diaria'!$F$4:$F$403,'Caja Diaria'!$B$4:$B$403,"Ingreso",'Caja Diaria'!$A$4:$A$403,$A8) -> 0 | C8: =SUMIFS('Caja Diaria'!$F$4:$F$403,'Caja Diaria'!$B$4:$B$403,"Egreso",'Caja Diaria'!$A$4:$A$403,$A8) -> 0 | D8: =B8-C8 -> 0 | E8: =E7+D8 -> 5761500 | F8: =F7+SUMIFS('Caja Diaria'!$F$4:$F$403,'Caja Diaria'!$B$4:$B$403,"Ingreso",'Caja Diaria'!$E$4:$E$403,"Efectivo",'Caja Diaria'!$A$4:$A$403,$A8)-SUMIFS('Caja Diaria'!$F$4:$F$403,'Caja Diaria'!$B$4:$B$403,"Egreso",'Caja Diaria'!$E$4:$E$403,"Efectivo",'Caja Diaria'!$A$4:$A$403,$A8) -> 468000 | G8: =B8/Parámetros!$C$8 -> 0 | H8: =IF(Parámetros!$D$15=0,0,COUNTIFS(Sesiones!$A$4:$A$903,$A8,Sesiones!$B$4:$B$903,Parámetros!$B$15)/Parámetros!$D$15) -> 0 | I8: =IF(Parámetros!$D$16=0,0,COUNTIFS(Sesiones!$A$4:$A$903,$A8,Sesiones!$B$4:$B$903,Parámetros!$B$16)/Parámetros!$D$16) -> 0 | J8: =IF(Parámetros!$D$17=0,0,COUNTIFS(Sesiones!$A$4:$A$903,$A8,Sesiones!$B$4:$B$903,Parámetros!$B$17)/Parámetros!$D$17) -> 0 | K8: =IF(Parámetros!$D$18=0,0,COUNTIFS(Sesiones!$A$4:$A$903,$A8,Sesiones!$B$4:$B$903,Parámetros!$B$18)/Parámetros!$D$18) -> 0 | L8: =IF(Parámetros!$D$19=0,0,COUNTIFS(Sesiones!$A$4:$A$903,$A8,Sesiones!$B$4:$B$903,Parámetros!$B$19)/Parámetros!$D$19) -> 0 | M8: =IF(Parámetros!$D$20=0,0,COUNTIFS(Sesiones!$A$4:$A$903,$A8,Sesiones!$B$4:$B$903,Parámetros!$B$20)/Parámetros!$D$20) -> 0 | N8: =IF(Parámetros!$D$21=0,0,COUNTIFS(Sesiones!$A$4:$A$903,$A8,Sesiones!$B$4:$B$903,Parámetros!$B$21)/Parámetros!$D$21) -> 0 | O8: =IF(Parámetros!$D$22=0,0,COUNTIFS(Sesiones!$A$4:$A$903,$A8,Sesiones!$B$4:$B$903,Parámetros!$B$22)/Parámetros!$D$22) -> 0 | P8: =IF(Parámetros!$D$23=0,0,COUNTIFS(Sesiones!$A$4:$A$903,$A8,Sesiones!$B$4:$B$903,Parámetros!$B$23)/Parámetros!$D$23) -> 0 | Q8: =IF(Parámetros!$D$24=0,0,COUNTIFS(Sesiones!$A$4:$A$903,$A8,Sesiones!$B$4:$B$903,Parámetros!$B$24)/Parámetros!$D$24) -> 0 | R8: =IF(Parámetros!$D$25=0,0,COUNTIFS(Sesiones!$A$4:$A$903,$A8,Sesiones!$B$4:$B$903,Parámetros!$B$25)/Parámetros!$D$25) -> 0 | S8: =IF(Parámetros!$D$26=0,0,COUNTIFS(Sesiones!$A$4:$A$903,$A8,Sesiones!$B$4:$B$903,Parámetros!$B$26)/Parámetros!$D$26) -> 0 | T8: =IF(Parámetros!$D$27=0,0,COUNTIFS(Sesiones!$A$4:$A$903,$A8,Sesiones!$B$4:$B$903,Parámetros!$B$27)/Parámetros!$D$27) -> 0
A9: =DATE(Parámetros!$C$6,Parámetros!$C$7,6) -> 46240 | B9: =SUMIFS('Caja Diaria'!$F$4:$F$403,'Caja Diaria'!$B$4:$B$403,"Ingreso",'Caja Diaria'!$A$4:$A$403,$A9) -> 0 | C9: =SUMIFS('Caja Diaria'!$F$4:$F$403,'Caja Diaria'!$B$4:$B$403,"Egreso",'Caja Diaria'!$A$4:$A$403,$A9) -> 0 | D9: =B9-C9 -> 0 | E9: =E8+D9 -> 5761500 | F9: =F8+SUMIFS('Caja Diaria'!$F$4:$F$403,'Caja Diaria'!$B$4:$B$403,"Ingreso",'Caja Diaria'!$E$4:$E$403,"Efectivo",'Caja Diaria'!$A$4:$A$403,$A9)-SUMIFS('Caja Diaria'!$F$4:$F$403,'Caja Diaria'!$B$4:$B$403,"Egreso",'Caja Diaria'!$E$4:$E$403,"Efectivo",'Caja Diaria'!$A$4:$A$403,$A9) -> 468000 | G9: =B9/Parámetros!$C$8 -> 0 | H9: =IF(Parámetros!$D$15=0,0,COUNTIFS(Sesiones!$A$4:$A$903,$A9,Sesiones!$B$4:$B$903,Parámetros!$B$15)/Parámetros!$D$15) -> 0 | I9: =IF(Parámetros!$D$16=0,0,COUNTIFS(Sesiones!$A$4:$A$903,$A9,Sesiones!$B$4:$B$903,Parámetros!$B$16)/Parámetros!$D$16) -> 0 | J9: =IF(Parámetros!$D$17=0,0,COUNTIFS(Sesiones!$A$4:$A$903,$A9,Sesiones!$B$4:$B$903,Parámetros!$B$17)/Parámetros!$D$17) -> 0 | K9: =IF(Parámetros!$D$18=0,0,COUNTIFS(Sesiones!$A$4:$A$903,$A9,Sesiones!$B$4:$B$903,Parámetros!$B$18)/Parámetros!$D$18) -> 0 | L9: =IF(Parámetros!$D$19=0,0,COUNTIFS(Sesiones!$A$4:$A$903,$A9,Sesiones!$B$4:$B$903,Parámetros!$B$19)/Parámetros!$D$19) -> 0 | M9: =IF(Parámetros!$D$20=0,0,COUNTIFS(Sesiones!$A$4:$A$903,$A9,Sesiones!$B$4:$B$903,Parámetros!$B$20)/Parámetros!$D$20) -> 0 | N9: =IF(Parámetros!$D$21=0,0,COUNTIFS(Sesiones!$A$4:$A$903,$A9,Sesiones!$B$4:$B$903,Parámetros!$B$21)/Parámetros!$D$21) -> 0 | O9: =IF(Parámetros!$D$22=0,0,COUNTIFS(Sesiones!$A$4:$A$903,$A9,Sesiones!$B$4:$B$903,Parámetros!$B$22)/Parámetros!$D$22) -> 0 | P9: =IF(Parámetros!$D$23=0,0,COUNTIFS(Sesiones!$A$4:$A$903,$A9,Sesiones!$B$4:$B$903,Parámetros!$B$23)/Parámetros!$D$23) -> 0 | Q9: =IF(Parámetros!$D$24=0,0,COUNTIFS(Sesiones!$A$4:$A$903,$A9,Sesiones!$B$4:$B$903,Parámetros!$B$24)/Parámetros!$D$24) -> 0 | R9: =IF(Parámetros!$D$25=0,0,COUNTIFS(Sesiones!$A$4:$A$903,$A9,Sesiones!$B$4:$B$903,Parámetros!$B$25)/Parámetros!$D$25) -> 0 | S9: =IF(Parámetros!$D$26=0,0,COUNTIFS(Sesiones!$A$4:$A$903,$A9,Sesiones!$B$4:$B$903,Parámetros!$B$26)/Parámetros!$D$26) -> 0 | T9: =IF(Parámetros!$D$27=0,0,COUNTIFS(Sesiones!$A$4:$A$903,$A9,Sesiones!$B$4:$B$903,Parámetros!$B$27)/Parámetros!$D$27) -> 0
A10: =DATE(Parámetros!$C$6,Parámetros!$C$7,7) -> 46241 | B10: =SUMIFS('Caja Diaria'!$F$4:$F$403,'Caja Diaria'!$B$4:$B$403,"Ingreso",'Caja Diaria'!$A$4:$A$403,$A10) -> 0 | C10: =SUMIFS('Caja Diaria'!$F$4:$F$403,'Caja Diaria'!$B$4:$B$403,"Egreso",'Caja Diaria'!$A$4:$A$403,$A10) -> 0 | D10: =B10-C10 -> 0 | E10: =E9+D10 -> 5761500 | F10: =F9+SUMIFS('Caja Diaria'!$F$4:$F$403,'Caja Diaria'!$B$4:$B$403,"Ingreso",'Caja Diaria'!$E$4:$E$403,"Efectivo",'Caja Diaria'!$A$4:$A$403,$A10)-SUMIFS('Caja Diaria'!$F$4:$F$403,'Caja Diaria'!$B$4:$B$403,"Egreso",'Caja Diaria'!$E$4:$E$403,"Efectivo",'Caja Diaria'!$A$4:$A$403,$A10) -> 468000 | G10: =B10/Parámetros!$C$8 -> 0 | H10: =IF(Parámetros!$D$15=0,0,COUNTIFS(Sesiones!$A$4:$A$903,$A10,Sesiones!$B$4:$B$903,Parámetros!$B$15)/Parámetros!$D$15) -> 0 | I10: =IF(Parámetros!$D$16=0,0,COUNTIFS(Sesiones!$A$4:$A$903,$A10,Sesiones!$B$4:$B$903,Parámetros!$B$16)/Parámetros!$D$16) -> 0 | J10: =IF(Parámetros!$D$17=0,0,COUNTIFS(Sesiones!$A$4:$A$903,$A10,Sesiones!$B$4:$B$903,Parámetros!$B$17)/Parámetros!$D$17) -> 0 | K10: =IF(Parámetros!$D$18=0,0,COUNTIFS(Sesiones!$A$4:$A$903,$A10,Sesiones!$B$4:$B$903,Parámetros!$B$18)/Parámetros!$D$18) -> 0 | L10: =IF(Parámetros!$D$19=0,0,COUNTIFS(Sesiones!$A$4:$A$903,$A10,Sesiones!$B$4:$B$903,Parámetros!$B$19)/Parámetros!$D$19) -> 0 | M10: =IF(Parámetros!$D$20=0,0,COUNTIFS(Sesiones!$A$4:$A$903,$A10,Sesiones!$B$4:$B$903,Parámetros!$B$20)/Parámetros!$D$20) -> 0 | N10: =IF(Parámetros!$D$21=0,0,COUNTIFS(Sesiones!$A$4:$A$903,$A10,Sesiones!$B$4:$B$903,Parámetros!$B$21)/Parámetros!$D$21) -> 0 | O10: =IF(Parámetros!$D$22=0,0,COUNTIFS(Sesiones!$A$4:$A$903,$A10,Sesiones!$B$4:$B$903,Parámetros!$B$22)/Parámetros!$D$22) -> 0 | P10: =IF(Parámetros!$D$23=0,0,COUNTIFS(Sesiones!$A$4:$A$903,$A10,Sesiones!$B$4:$B$903,Parámetros!$B$23)/Parámetros!$D$23) -> 0 | Q10: =IF(Parámetros!$D$24=0,0,COUNTIFS(Sesiones!$A$4:$A$903,$A10,Sesiones!$B$4:$B$903,Parámetros!$B$24)/Parámetros!$D$24) -> 0 | R10: =IF(Parámetros!$D$25=0,0,COUNTIFS(Sesiones!$A$4:$A$903,$A10,Sesiones!$B$4:$B$903,Parámetros!$B$25)/Parámetros!$D$25) -> 0 | S10: =IF(Parámetros!$D$26=0,0,COUNTIFS(Sesiones!$A$4:$A$903,$A10,Sesiones!$B$4:$B$903,Parámetros!$B$26)/Parámetros!$D$26) -> 0 | T10: =IF(Parámetros!$D$27=0,0,COUNTIFS(Sesiones!$A$4:$A$903,$A10,Sesiones!$B$4:$B$903,Parámetros!$B$27)/Parámetros!$D$27) -> 0
A11: =DATE(Parámetros!$C$6,Parámetros!$C$7,8) -> 46242 | B11: =SUMIFS('Caja Diaria'!$F$4:$F$403,'Caja Diaria'!$B$4:$B$403,"Ingreso",'Caja Diaria'!$A$4:$A$403,$A11) -> 0 | C11: =SUMIFS('Caja Diaria'!$F$4:$F$403,'Caja Diaria'!$B$4:$B$403,"Egreso",'Caja Diaria'!$A$4:$A$403,$A11) -> 0 | D11: =B11-C11 -> 0 | E11: =E10+D11 -> 5761500 | F11: =F10+SUMIFS('Caja Diaria'!$F$4:$F$403,'Caja Diaria'!$B$4:$B$403,"Ingreso",'Caja Diaria'!$E$4:$E$403,"Efectivo",'Caja Diaria'!$A$4:$A$403,$A11)-SUMIFS('Caja Diaria'!$F$4:$F$403,'Caja Diaria'!$B$4:$B$403,"Egreso",'Caja Diaria'!$E$4:$E$403,"Efectivo",'Caja Diaria'!$A$4:$A$403,$A11) -> 468000 | G11: =B11/Parámetros!$C$8 -> 0 | H11: =IF(Parámetros!$D$15=0,0,COUNTIFS(Sesiones!$A$4:$A$903,$A11,Sesiones!$B$4:$B$903,Parámetros!$B$15)/Parámetros!$D$15) -> 0 | I11: =IF(Parámetros!$D$16=0,0,COUNTIFS(Sesiones!$A$4:$A$903,$A11,Sesiones!$B$4:$B$903,Parámetros!$B$16)/Parámetros!$D$16) -> 0 | J11: =IF(Parámetros!$D$17=0,0,COUNTIFS(Sesiones!$A$4:$A$903,$A11,Sesiones!$B$4:$B$903,Parámetros!$B$17)/Parámetros!$D$17) -> 0 | K11: =IF(Parámetros!$D$18=0,0,COUNTIFS(Sesiones!$A$4:$A$903,$A11,Sesiones!$B$4:$B$903,Parámetros!$B$18)/Parámetros!$D$18) -> 0 | L11: =IF(Parámetros!$D$19=0,0,COUNTIFS(Sesiones!$A$4:$A$903,$A11,Sesiones!$B$4:$B$903,Parámetros!$B$19)/Parámetros!$D$19) -> 0 | M11: =IF(Parámetros!$D$20=0,0,COUNTIFS(Sesiones!$A$4:$A$903,$A11,Sesiones!$B$4:$B$903,Parámetros!$B$20)/Parámetros!$D$20) -> 0 | N11: =IF(Parámetros!$D$21=0,0,COUNTIFS(Sesiones!$A$4:$A$903,$A11,Sesiones!$B$4:$B$903,Parámetros!$B$21)/Parámetros!$D$21) -> 0 | O11: =IF(Parámetros!$D$22=0,0,COUNTIFS(Sesiones!$A$4:$A$903,$A11,Sesiones!$B$4:$B$903,Parámetros!$B$22)/Parámetros!$D$22) -> 0 | P11: =IF(Parámetros!$D$23=0,0,COUNTIFS(Sesiones!$A$4:$A$903,$A11,Sesiones!$B$4:$B$903,Parámetros!$B$23)/Parámetros!$D$23) -> 0 | Q11: =IF(Parámetros!$D$24=0,0,COUNTIFS(Sesiones!$A$4:$A$903,$A11,Sesiones!$B$4:$B$903,Parámetros!$B$24)/Parámetros!$D$24) -> 0 | R11: =IF(Parámetros!$D$25=0,0,COUNTIFS(Sesiones!$A$4:$A$903,$A11,Sesiones!$B$4:$B$903,Parámetros!$B$25)/Parámetros!$D$25) -> 0 | S11: =IF(Parámetros!$D$26=0,0,COUNTIFS(Sesiones!$A$4:$A$903,$A11,Sesiones!$B$4:$B$903,Parámetros!$B$26)/Parámetros!$D$26) -> 0 | T11: =IF(Parámetros!$D$27=0,0,COUNTIFS(Sesiones!$A$4:$A$903,$A11,Sesiones!$B$4:$B$903,Parámetros!$B$27)/Parámetros!$D$27) -> 0
A12: =DATE(Parámetros!$C$6,Parámetros!$C$7,9) -> 46243 | B12: =SUMIFS('Caja Diaria'!$F$4:$F$403,'Caja Diaria'!$B$4:$B$403,"Ingreso",'Caja Diaria'!$A$4:$A$403,$A12) -> 0 | C12: =SUMIFS('Caja Diaria'!$F$4:$F$403,'Caja Diaria'!$B$4:$B$403,"Egreso",'Caja Diaria'!$A$4:$A$403,$A12) -> 0 | D12: =B12-C12 -> 0 | E12: =E11+D12 -> 5761500 | F12: =F11+SUMIFS('Caja Diaria'!$F$4:$F$403,'Caja Diaria'!$B$4:$B$403,"Ingreso",'Caja Diaria'!$E$4:$E$403,"Efectivo",'Caja Diaria'!$A$4:$A$403,$A12)-SUMIFS('Caja Diaria'!$F$4:$F$403,'Caja Diaria'!$B$4:$B$403,"Egreso",'Caja Diaria'!$E$4:$E$403,"Efectivo",'Caja Diaria'!$A$4:$A$403,$A12) -> 468000 | G12: =B12/Parámetros!$C$8 -> 0 | H12: =IF(Parámetros!$D$15=0,0,COUNTIFS(Sesiones!$A$4:$A$903,$A12,Sesiones!$B$4:$B$903,Parámetros!$B$15)/Parámetros!$D$15) -> 0 | I12: =IF(Parámetros!$D$16=0,0,COUNTIFS(Sesiones!$A$4:$A$903,$A12,Sesiones!$B$4:$B$903,Parámetros!$B$16)/Parámetros!$D$16) -> 0 | J12: =IF(Parámetros!$D$17=0,0,COUNTIFS(Sesiones!$A$4:$A$903,$A12,Sesiones!$B$4:$B$903,Parámetros!$B$17)/Parámetros!$D$17) -> 0 | K12: =IF(Parámetros!$D$18=0,0,COUNTIFS(Sesiones!$A$4:$A$903,$A12,Sesiones!$B$4:$B$903,Parámetros!$B$18)/Parámetros!$D$18) -> 0 | L12: =IF(Parámetros!$D$19=0,0,COUNTIFS(Sesiones!$A$4:$A$903,$A12,Sesiones!$B$4:$B$903,Parámetros!$B$19)/Parámetros!$D$19) -> 0 | M12: =IF(Parámetros!$D$20=0,0,COUNTIFS(Sesiones!$A$4:$A$903,$A12,Sesiones!$B$4:$B$903,Parámetros!$B$20)/Parámetros!$D$20) -> 0 | N12: =IF(Parámetros!$D$21=0,0,COUNTIFS(Sesiones!$A$4:$A$903,$A12,Sesiones!$B$4:$B$903,Parámetros!$B$21)/Parámetros!$D$21) -> 0 | O12: =IF(Parámetros!$D$22=0,0,COUNTIFS(Sesiones!$A$4:$A$903,$A12,Sesiones!$B$4:$B$903,Parámetros!$B$22)/Parámetros!$D$22) -> 0 | P12: =IF(Parámetros!$D$23=0,0,COUNTIFS(Sesiones!$A$4:$A$903,$A12,Sesiones!$B$4:$B$903,Parámetros!$B$23)/Parámetros!$D$23) -> 0 | Q12: =IF(Parámetros!$D$24=0,0,COUNTIFS(Sesiones!$A$4:$A$903,$A12,Sesiones!$B$4:$B$903,Parámetros!$B$24)/Parámetros!$D$24) -> 0 | R12: =IF(Parámetros!$D$25=0,0,COUNTIFS(Sesiones!$A$4:$A$903,$A12,Sesiones!$B$4:$B$903,Parámetros!$B$25)/Parámetros!$D$25) -> 0 | S12: =IF(Parámetros!$D$26=0,0,COUNTIFS(Sesiones!$A$4:$A$903,$A12,Sesiones!$B$4:$B$903,Parámetros!$B$26)/Parámetros!$D$26) -> 0 | T12: =IF(Parámetros!$D$27=0,0,COUNTIFS(Sesiones!$A$4:$A$903,$A12,Sesiones!$B$4:$B$903,Parámetros!$B$27)/Parámetros!$D$27) -> 0
A13: =DATE(Parámetros!$C$6,Parámetros!$C$7,10) -> 46244 | B13: =SUMIFS('Caja Diaria'!$F$4:$F$403,'Caja Diaria'!$B$4:$B$403,"Ingreso",'Caja Diaria'!$A$4:$A$403,$A13) -> 0 | C13: =SUMIFS('Caja Diaria'!$F$4:$F$403,'Caja Diaria'!$B$4:$B$403,"Egreso",'Caja Diaria'!$A$4:$A$403,$A13) -> 0 | D13: =B13-C13 -> 0 | E13: =E12+D13 -> 5761500 | F13: =F12+SUMIFS('Caja Diaria'!$F$4:$F$403,'Caja Diaria'!$B$4:$B$403,"Ingreso",'Caja Diaria'!$E$4:$E$403,"Efectivo",'Caja Diaria'!$A$4:$A$403,$A13)-SUMIFS('Caja Diaria'!$F$4:$F$403,'Caja Diaria'!$B$4:$B$403,"Egreso",'Caja Diaria'!$E$4:$E$403,"Efectivo",'Caja Diaria'!$A$4:$A$403,$A13) -> 468000 | G13: =B13/Parámetros!$C$8 -> 0 | H13: =IF(Parámetros!$D$15=0,0,COUNTIFS(Sesiones!$A$4:$A$903,$A13,Sesiones!$B$4:$B$903,Parámetros!$B$15)/Parámetros!$D$15) -> 0 | I13: =IF(Parámetros!$D$16=0,0,COUNTIFS(Sesiones!$A$4:$A$903,$A13,Sesiones!$B$4:$B$903,Parámetros!$B$16)/Parámetros!$D$16) -> 0 | J13: =IF(Parámetros!$D$17=0,0,COUNTIFS(Sesiones!$A$4:$A$903,$A13,Sesiones!$B$4:$B$903,Parámetros!$B$17)/Parámetros!$D$17) -> 0 | K13: =IF(Parámetros!$D$18=0,0,COUNTIFS(Sesiones!$A$4:$A$903,$A13,Sesiones!$B$4:$B$903,Parámetros!$B$18)/Parámetros!$D$18) -> 0 | L13: =IF(Parámetros!$D$19=0,0,COUNTIFS(Sesiones!$A$4:$A$903,$A13,Sesiones!$B$4:$B$903,Parámetros!$B$19)/Parámetros!$D$19) -> 0 | M13: =IF(Parámetros!$D$20=0,0,COUNTIFS(Sesiones!$A$4:$A$903,$A13,Sesiones!$B$4:$B$903,Parámetros!$B$20)/Parámetros!$D$20) -> 0 | N13: =IF(Parámetros!$D$21=0,0,COUNTIFS(Sesiones!$A$4:$A$903,$A13,Sesiones!$B$4:$B$903,Parámetros!$B$21)/Parámetros!$D$21) -> 0 | O13: =IF(Parámetros!$D$22=0,0,COUNTIFS(Sesiones!$A$4:$A$903,$A13,Sesiones!$B$4:$B$903,Parámetros!$B$22)/Parámetros!$D$22) -> 0 | P13: =IF(Parámetros!$D$23=0,0,COUNTIFS(Sesiones!$A$4:$A$903,$A13,Sesiones!$B$4:$B$903,Parámetros!$B$23)/Parámetros!$D$23) -> 0 | Q13: =IF(Parámetros!$D$24=0,0,COUNTIFS(Sesiones!$A$4:$A$903,$A13,Sesiones!$B$4:$B$903,Parámetros!$B$24)/Parámetros!$D$24) -> 0 | R13: =IF(Parámetros!$D$25=0,0,COUNTIFS(Sesiones!$A$4:$A$903,$A13,Sesiones!$B$4:$B$903,Parámetros!$B$25)/Parámetros!$D$25) -> 0 | S13: =IF(Parámetros!$D$26=0,0,COUNTIFS(Sesiones!$A$4:$A$903,$A13,Sesiones!$B$4:$B$903,Parámetros!$B$26)/Parámetros!$D$26) -> 0 | T13: =IF(Parámetros!$D$27=0,0,COUNTIFS(Sesiones!$A$4:$A$903,$A13,Sesiones!$B$4:$B$903,Parámetros!$B$27)/Parámetros!$D$27) -> 0
A14: =DATE(Parámetros!$C$6,Parámetros!$C$7,11) -> 46245 | B14: =SUMIFS('Caja Diaria'!$F$4:$F$403,'Caja Diaria'!$B$4:$B$403,"Ingreso",'Caja Diaria'!$A$4:$A$403,$A14) -> 0 | C14: =SUMIFS('Caja Diaria'!$F$4:$F$403,'Caja Diaria'!$B$4:$B$403,"Egreso",'Caja Diaria'!$A$4:$A$403,$A14) -> 0 | D14: =B14-C14 -> 0 | E14: =E13+D14 -> 5761500 | F14: =F13+SUMIFS('Caja Diaria'!$F$4:$F$403,'Caja Diaria'!$B$4:$B$403,"Ingreso",'Caja Diaria'!$E$4:$E$403,"Efectivo",'Caja Diaria'!$A$4:$A$403,$A14)-SUMIFS('Caja Diaria'!$F$4:$F$403,'Caja Diaria'!$B$4:$B$403,"Egreso",'Caja Diaria'!$E$4:$E$403,"Efectivo",'Caja Diaria'!$A$4:$A$403,$A14) -> 468000 | G14: =B14/Parámetros!$C$8 -> 0 | H14: =IF(Parámetros!$D$15=0,0,COUNTIFS(Sesiones!$A$4:$A$903,$A14,Sesiones!$B$4:$B$903,Parámetros!$B$15)/Parámetros!$D$15) -> 0 | I14: =IF(Parámetros!$D$16=0,0,COUNTIFS(Sesiones!$A$4:$A$903,$A14,Sesiones!$B$4:$B$903,Parámetros!$B$16)/Parámetros!$D$16) -> 0 | J14: =IF(Parámetros!$D$17=0,0,COUNTIFS(Sesiones!$A$4:$A$903,$A14,Sesiones!$B$4:$B$903,Parámetros!$B$17)/Parámetros!$D$17) -> 0 | K14: =IF(Parámetros!$D$18=0,0,COUNTIFS(Sesiones!$A$4:$A$903,$A14,Sesiones!$B$4:$B$903,Parámetros!$B$18)/Parámetros!$D$18) -> 0 | L14: =IF(Parámetros!$D$19=0,0,COUNTIFS(Sesiones!$A$4:$A$903,$A14,Sesiones!$B$4:$B$903,Parámetros!$B$19)/Parámetros!$D$19) -> 0 | M14: =IF(Parámetros!$D$20=0,0,COUNTIFS(Sesiones!$A$4:$A$903,$A14,Sesiones!$B$4:$B$903,Parámetros!$B$20)/Parámetros!$D$20) -> 0 | N14: =IF(Parámetros!$D$21=0,0,COUNTIFS(Sesiones!$A$4:$A$903,$A14,Sesiones!$B$4:$B$903,Parámetros!$B$21)/Parámetros!$D$21) -> 0 | O14: =IF(Parámetros!$D$22=0,0,COUNTIFS(Sesiones!$A$4:$A$903,$A14,Sesiones!$B$4:$B$903,Parámetros!$B$22)/Parámetros!$D$22) -> 0 | P14: =IF(Parámetros!$D$23=0,0,COUNTIFS(Sesiones!$A$4:$A$903,$A14,Sesiones!$B$4:$B$903,Parámetros!$B$23)/Parámetros!$D$23) -> 0 | Q14: =IF(Parámetros!$D$24=0,0,COUNTIFS(Sesiones!$A$4:$A$903,$A14,Sesiones!$B$4:$B$903,Parámetros!$B$24)/Parámetros!$D$24) -> 0 | R14: =IF(Parámetros!$D$25=0,0,COUNTIFS(Sesiones!$A$4:$A$903,$A14,Sesiones!$B$4:$B$903,Parámetros!$B$25)/Parámetros!$D$25) -> 0 | S14: =IF(Parámetros!$D$26=0,0,COUNTIFS(Sesiones!$A$4:$A$903,$A14,Sesiones!$B$4:$B$903,Parámetros!$B$26)/Parámetros!$D$26) -> 0 | T14: =IF(Parámetros!$D$27=0,0,COUNTIFS(Sesiones!$A$4:$A$903,$A14,Sesiones!$B$4:$B$903,Parámetros!$B$27)/Parámetros!$D$27) -> 0
A15: =DATE(Parámetros!$C$6,Parámetros!$C$7,12) -> 46246 | B15: =SUMIFS('Caja Diaria'!$F$4:$F$403,'Caja Diaria'!$B$4:$B$403,"Ingreso",'Caja Diaria'!$A$4:$A$403,$A15) -> 0 | C15: =SUMIFS('Caja Diaria'!$F$4:$F$403,'Caja Diaria'!$B$4:$B$403,"Egreso",'Caja Diaria'!$A$4:$A$403,$A15) -> 0 | D15: =B15-C15 -> 0 | E15: =E14+D15 -> 5761500 | F15: =F14+SUMIFS('Caja Diaria'!$F$4:$F$403,'Caja Diaria'!$B$4:$B$403,"Ingreso",'Caja Diaria'!$E$4:$E$403,"Efectivo",'Caja Diaria'!$A$4:$A$403,$A15)-SUMIFS('Caja Diaria'!$F$4:$F$403,'Caja Diaria'!$B$4:$B$403,"Egreso",'Caja Diaria'!$E$4:$E$403,"Efectivo",'Caja Diaria'!$A$4:$A$403,$A15) -> 468000 | G15: =B15/Parámetros!$C$8 -> 0 | H15: =IF(Parámetros!$D$15=0,0,COUNTIFS(Sesiones!$A$4:$A$903,$A15,Sesiones!$B$4:$B$903,Parámetros!$B$15)/Parámetros!$D$15) -> 0 | I15: =IF(Parámetros!$D$16=0,0,COUNTIFS(Sesiones!$A$4:$A$903,$A15,Sesiones!$B$4:$B$903,Parámetros!$B$16)/Parámetros!$D$16) -> 0 | J15: =IF(Parámetros!$D$17=0,0,COUNTIFS(Sesiones!$A$4:$A$903,$A15,Sesiones!$B$4:$B$903,Parámetros!$B$17)/Parámetros!$D$17) -> 0 | K15: =IF(Parámetros!$D$18=0,0,COUNTIFS(Sesiones!$A$4:$A$903,$A15,Sesiones!$B$4:$B$903,Parámetros!$B$18)/Parámetros!$D$18) -> 0 | L15: =IF(Parámetros!$D$19=0,0,COUNTIFS(Sesiones!$A$4:$A$903,$A15,Sesiones!$B$4:$B$903,Parámetros!$B$19)/Parámetros!$D$19) -> 0 | M15: =IF(Parámetros!$D$20=0,0,COUNTIFS(Sesiones!$A$4:$A$903,$A15,Sesiones!$B$4:$B$903,Parámetros!$B$20)/Parámetros!$D$20) -> 0 | N15: =IF(Parámetros!$D$21=0,0,COUNTIFS(Sesiones!$A$4:$A$903,$A15,Sesiones!$B$4:$B$903,Parámetros!$B$21)/Parámetros!$D$21) -> 0 | O15: =IF(Parámetros!$D$22=0,0,COUNTIFS(Sesiones!$A$4:$A$903,$A15,Sesiones!$B$4:$B$903,Parámetros!$B$22)/Parámetros!$D$22) -> 0 | P15: =IF(Parámetros!$D$23=0,0,COUNTIFS(Sesiones!$A$4:$A$903,$A15,Sesiones!$B$4:$B$903,Parámetros!$B$23)/Parámetros!$D$23) -> 0 | Q15: =IF(Parámetros!$D$24=0,0,COUNTIFS(Sesiones!$A$4:$A$903,$A15,Sesiones!$B$4:$B$903,Parámetros!$B$24)/Parámetros!$D$24) -> 0 | R15: =IF(Parámetros!$D$25=0,0,COUNTIFS(Sesiones!$A$4:$A$903,$A15,Sesiones!$B$4:$B$903,Parámetros!$B$25)/Parámetros!$D$25) -> 0 | S15: =IF(Parámetros!$D$26=0,0,COUNTIFS(Sesiones!$A$4:$A$903,$A15,Sesiones!$B$4:$B$903,Parámetros!$B$26)/Parámetros!$D$26) -> 0 | T15: =IF(Parámetros!$D$27=0,0,COUNTIFS(Sesiones!$A$4:$A$903,$A15,Sesiones!$B$4:$B$903,Parámetros!$B$27)/Parámetros!$D$27) -> 0
A16: =DATE(Parámetros!$C$6,Parámetros!$C$7,13) -> 46247 | B16: =SUMIFS('Caja Diaria'!$F$4:$F$403,'Caja Diaria'!$B$4:$B$403,"Ingreso",'Caja Diaria'!$A$4:$A$403,$A16) -> 0 | C16: =SUMIFS('Caja Diaria'!$F$4:$F$403,'Caja Diaria'!$B$4:$B$403,"Egreso",'Caja Diaria'!$A$4:$A$403,$A16) -> 0 | D16: =B16-C16 -> 0 | E16: =E15+D16 -> 5761500 | F16: =F15+SUMIFS('Caja Diaria'!$F$4:$F$403,'Caja Diaria'!$B$4:$B$403,"Ingreso",'Caja Diaria'!$E$4:$E$403,"Efectivo",'Caja Diaria'!$A$4:$A$403,$A16)-SUMIFS('Caja Diaria'!$F$4:$F$403,'Caja Diaria'!$B$4:$B$403,"Egreso",'Caja Diaria'!$E$4:$E$403,"Efectivo",'Caja Diaria'!$A$4:$A$403,$A16) -> 468000 | G16: =B16/Parámetros!$C$8 -> 0 | H16: =IF(Parámetros!$D$15=0,0,COUNTIFS(Sesiones!$A$4:$A$903,$A16,Sesiones!$B$4:$B$903,Parámetros!$B$15)/Parámetros!$D$15) -> 0 | I16: =IF(Parámetros!$D$16=0,0,COUNTIFS(Sesiones!$A$4:$A$903,$A16,Sesiones!$B$4:$B$903,Parámetros!$B$16)/Parámetros!$D$16) -> 0 | J16: =IF(Parámetros!$D$17=0,0,COUNTIFS(Sesiones!$A$4:$A$903,$A16,Sesiones!$B$4:$B$903,Parámetros!$B$17)/Parámetros!$D$17) -> 0 | K16: =IF(Parámetros!$D$18=0,0,COUNTIFS(Sesiones!$A$4:$A$903,$A16,Sesiones!$B$4:$B$903,Parámetros!$B$18)/Parámetros!$D$18) -> 0 | L16: =IF(Parámetros!$D$19=0,0,COUNTIFS(Sesiones!$A$4:$A$903,$A16,Sesiones!$B$4:$B$903,Parámetros!$B$19)/Parámetros!$D$19) -> 0 | M16: =IF(Parámetros!$D$20=0,0,COUNTIFS(Sesiones!$A$4:$A$903,$A16,Sesiones!$B$4:$B$903,Parámetros!$B$20)/Parámetros!$D$20) -> 0 | N16: =IF(Parámetros!$D$21=0,0,COUNTIFS(Sesiones!$A$4:$A$903,$A16,Sesiones!$B$4:$B$903,Parámetros!$B$21)/Parámetros!$D$21) -> 0 | O16: =IF(Parámetros!$D$22=0,0,COUNTIFS(Sesiones!$A$4:$A$903,$A16,Sesiones!$B$4:$B$903,Parámetros!$B$22)/Parámetros!$D$22) -> 0 | P16: =IF(Parámetros!$D$23=0,0,COUNTIFS(Sesiones!$A$4:$A$903,$A16,Sesiones!$B$4:$B$903,Parámetros!$B$23)/Parámetros!$D$23) -> 0 | Q16: =IF(Parámetros!$D$24=0,0,COUNTIFS(Sesiones!$A$4:$A$903,$A16,Sesiones!$B$4:$B$903,Parámetros!$B$24)/Parámetros!$D$24) -> 0 | R16: =IF(Parámetros!$D$25=0,0,COUNTIFS(Sesiones!$A$4:$A$903,$A16,Sesiones!$B$4:$B$903,Parámetros!$B$25)/Parámetros!$D$25) -> 0 | S16: =IF(Parámetros!$D$26=0,0,COUNTIFS(Sesiones!$A$4:$A$903,$A16,Sesiones!$B$4:$B$903,Parámetros!$B$26)/Parámetros!$D$26) -> 0 | T16: =IF(Parámetros!$D$27=0,0,COUNTIFS(Sesiones!$A$4:$A$903,$A16,Sesiones!$B$4:$B$903,Parámetros!$B$27)/Parámetros!$D$27) -> 0
A17: =DATE(Parámetros!$C$6,Parámetros!$C$7,14) -> 46248 | B17: =SUMIFS('Caja Diaria'!$F$4:$F$403,'Caja Diaria'!$B$4:$B$403,"Ingreso",'Caja Diaria'!$A$4:$A$403,$A17) -> 0 | C17: =SUMIFS('Caja Diaria'!$F$4:$F$403,'Caja Diaria'!$B$4:$B$403,"Egreso",'Caja Diaria'!$A$4:$A$403,$A17) -> 0 | D17: =B17-C17 -> 0 | E17: =E16+D17 -> 5761500 | F17: =F16+SUMIFS('Caja Diaria'!$F$4:$F$403,'Caja Diaria'!$B$4:$B$403,"Ingreso",'Caja Diaria'!$E$4:$E$403,"Efectivo",'Caja Diaria'!$A$4:$A$403,$A17)-SUMIFS('Caja Diaria'!$F$4:$F$403,'Caja Diaria'!$B$4:$B$403,"Egreso",'Caja Diaria'!$E$4:$E$403,"Efectivo",'Caja Diaria'!$A$4:$A$403,$A17) -> 468000 | G17: =B17/Parámetros!$C$8 -> 0 | H17: =IF(Parámetros!$D$15=0,0,COUNTIFS(Sesiones!$A$4:$A$903,$A17,Sesiones!$B$4:$B$903,Parámetros!$B$15)/Parámetros!$D$15) -> 0 | I17: =IF(Parámetros!$D$16=0,0,COUNTIFS(Sesiones!$A$4:$A$903,$A17,Sesiones!$B$4:$B$903,Parámetros!$B$16)/Parámetros!$D$16) -> 0 | J17: =IF(Parámetros!$D$17=0,0,COUNTIFS(Sesiones!$A$4:$A$903,$A17,Sesiones!$B$4:$B$903,Parámetros!$B$17)/Parámetros!$D$17) -> 0 | K17: =IF(Parámetros!$D$18=0,0,COUNTIFS(Sesiones!$A$4:$A$903,$A17,Sesiones!$B$4:$B$903,Parámetros!$B$18)/Parámetros!$D$18) -> 0 | L17: =IF(Parámetros!$D$19=0,0,COUNTIFS(Sesiones!$A$4:$A$903,$A17,Sesiones!$B$4:$B$903,Parámetros!$B$19)/Parámetros!$D$19) -> 0 | M17: =IF(Parámetros!$D$20=0,0,COUNTIFS(Sesiones!$A$4:$A$903,$A17,Sesiones!$B$4:$B$903,Parámetros!$B$20)/Parámetros!$D$20) -> 0 | N17: =IF(Parámetros!$D$21=0,0,COUNTIFS(Sesiones!$A$4:$A$903,$A17,Sesiones!$B$4:$B$903,Parámetros!$B$21)/Parámetros!$D$21) -> 0 | O17: =IF(Parámetros!$D$22=0,0,COUNTIFS(Sesiones!$A$4:$A$903,$A17,Sesiones!$B$4:$B$903,Parámetros!$B$22)/Parámetros!$D$22) -> 0 | P17: =IF(Parámetros!$D$23=0,0,COUNTIFS(Sesiones!$A$4:$A$903,$A17,Sesiones!$B$4:$B$903,Parámetros!$B$23)/Parámetros!$D$23) -> 0 | Q17: =IF(Parámetros!$D$24=0,0,COUNTIFS(Sesiones!$A$4:$A$903,$A17,Sesiones!$B$4:$B$903,Parámetros!$B$24)/Parámetros!$D$24) -> 0 | R17: =IF(Parámetros!$D$25=0,0,COUNTIFS(Sesiones!$A$4:$A$903,$A17,Sesiones!$B$4:$B$903,Parámetros!$B$25)/Parámetros!$D$25) -> 0 | S17: =IF(Parámetros!$D$26=0,0,COUNTIFS(Sesiones!$A$4:$A$903,$A17,Sesiones!$B$4:$B$903,Parámetros!$B$26)/Parámetros!$D$26) -> 0 | T17: =IF(Parámetros!$D$27=0,0,COUNTIFS(Sesiones!$A$4:$A$903,$A17,Sesiones!$B$4:$B$903,Parámetros!$B$27)/Parámetros!$D$27) -> 0
A18: =DATE(Parámetros!$C$6,Parámetros!$C$7,15) -> 46249 | B18: =SUMIFS('Caja Diaria'!$F$4:$F$403,'Caja Diaria'!$B$4:$B$403,"Ingreso",'Caja Diaria'!$A$4:$A$403,$A18) -> 0 | C18: =SUMIFS('Caja Diaria'!$F$4:$F$403,'Caja Diaria'!$B$4:$B$403,"Egreso",'Caja Diaria'!$A$4:$A$403,$A18) -> 0 | D18: =B18-C18 -> 0 | E18: =E17+D18 -> 5761500 | F18: =F17+SUMIFS('Caja Diaria'!$F$4:$F$403,'Caja Diaria'!$B$4:$B$403,"Ingreso",'Caja Diaria'!$E$4:$E$403,"Efectivo",'Caja Diaria'!$A$4:$A$403,$A18)-SUMIFS('Caja Diaria'!$F$4:$F$403,'Caja Diaria'!$B$4:$B$403,"Egreso",'Caja Diaria'!$E$4:$E$403,"Efectivo",'Caja Diaria'!$A$4:$A$403,$A18) -> 468000 | G18: =B18/Parámetros!$C$8 -> 0 | H18: =IF(Parámetros!$D$15=0,0,COUNTIFS(Sesiones!$A$4:$A$903,$A18,Sesiones!$B$4:$B$903,Parámetros!$B$15)/Parámetros!$D$15) -> 0 | I18: =IF(Parámetros!$D$16=0,0,COUNTIFS(Sesiones!$A$4:$A$903,$A18,Sesiones!$B$4:$B$903,Parámetros!$B$16)/Parámetros!$D$16) -> 0 | J18: =IF(Parámetros!$D$17=0,0,COUNTIFS(Sesiones!$A$4:$A$903,$A18,Sesiones!$B$4:$B$903,Parámetros!$B$17)/Parámetros!$D$17) -> 0 | K18: =IF(Parámetros!$D$18=0,0,COUNTIFS(Sesiones!$A$4:$A$903,$A18,Sesiones!$B$4:$B$903,Parámetros!$B$18)/Parámetros!$D$18) -> 0 | L18: =IF(Parámetros!$D$19=0,0,COUNTIFS(Sesiones!$A$4:$A$903,$A18,Sesiones!$B$4:$B$903,Parámetros!$B$19)/Parámetros!$D$19) -> 0 | M18: =IF(Parámetros!$D$20=0,0,COUNTIFS(Sesiones!$A$4:$A$903,$A18,Sesiones!$B$4:$B$903,Parámetros!$B$20)/Parámetros!$D$20) -> 0 | N18: =IF(Parámetros!$D$21=0,0,COUNTIFS(Sesiones!$A$4:$A$903,$A18,Sesiones!$B$4:$B$903,Parámetros!$B$21)/Parámetros!$D$21) -> 0 | O18: =IF(Parámetros!$D$22=0,0,COUNTIFS(Sesiones!$A$4:$A$903,$A18,Sesiones!$B$4:$B$903,Parámetros!$B$22)/Parámetros!$D$22) -> 0 | P18: =IF(Parámetros!$D$23=0,0,COUNTIFS(Sesiones!$A$4:$A$903,$A18,Sesiones!$B$4:$B$903,Parámetros!$B$23)/Parámetros!$D$23) -> 0 | Q18: =IF(Parámetros!$D$24=0,0,COUNTIFS(Sesiones!$A$4:$A$903,$A18,Sesiones!$B$4:$B$903,Parámetros!$B$24)/Parámetros!$D$24) -> 0 | R18: =IF(Parámetros!$D$25=0,0,COUNTIFS(Sesiones!$A$4:$A$903,$A18,Sesiones!$B$4:$B$903,Parámetros!$B$25)/Parámetros!$D$25) -> 0 | S18: =IF(Parámetros!$D$26=0,0,COUNTIFS(Sesiones!$A$4:$A$903,$A18,Sesiones!$B$4:$B$903,Parámetros!$B$26)/Parámetros!$D$26) -> 0 | T18: =IF(Parámetros!$D$27=0,0,COUNTIFS(Sesiones!$A$4:$A$903,$A18,Sesiones!$B$4:$B$903,Parámetros!$B$27)/Parámetros!$D$27) -> 0
A19: =DATE(Parámetros!$C$6,Parámetros!$C$7,16) -> 46250 | B19: =SUMIFS('Caja Diaria'!$F$4:$F$403,'Caja Diaria'!$B$4:$B$403,"Ingreso",'Caja Diaria'!$A$4:$A$403,$A19) -> 0 | C19: =SUMIFS('Caja Diaria'!$F$4:$F$403,'Caja Diaria'!$B$4:$B$403,"Egreso",'Caja Diaria'!$A$4:$A$403,$A19) -> 0 | D19: =B19-C19 -> 0 | E19: =E18+D19 -> 5761500 | F19: =F18+SUMIFS('Caja Diaria'!$F$4:$F$403,'Caja Diaria'!$B$4:$B$403,"Ingreso",'Caja Diaria'!$E$4:$E$403,"Efectivo",'Caja Diaria'!$A$4:$A$403,$A19)-SUMIFS('Caja Diaria'!$F$4:$F$403,'Caja Diaria'!$B$4:$B$403,"Egreso",'Caja Diaria'!$E$4:$E$403,"Efectivo",'Caja Diaria'!$A$4:$A$403,$A19) -> 468000 | G19: =B19/Parámetros!$C$8 -> 0 | H19: =IF(Parámetros!$D$15=0,0,COUNTIFS(Sesiones!$A$4:$A$903,$A19,Sesiones!$B$4:$B$903,Parámetros!$B$15)/Parámetros!$D$15) -> 0 | I19: =IF(Parámetros!$D$16=0,0,COUNTIFS(Sesiones!$A$4:$A$903,$A19,Sesiones!$B$4:$B$903,Parámetros!$B$16)/Parámetros!$D$16) -> 0 | J19: =IF(Parámetros!$D$17=0,0,COUNTIFS(Sesiones!$A$4:$A$903,$A19,Sesiones!$B$4:$B$903,Parámetros!$B$17)/Parámetros!$D$17) -> 0 | K19: =IF(Parámetros!$D$18=0,0,COUNTIFS(Sesiones!$A$4:$A$903,$A19,Sesiones!$B$4:$B$903,Parámetros!$B$18)/Parámetros!$D$18) -> 0 | L19: =IF(Parámetros!$D$19=0,0,COUNTIFS(Sesiones!$A$4:$A$903,$A19,Sesiones!$B$4:$B$903,Parámetros!$B$19)/Parámetros!$D$19) -> 0 | M19: =IF(Parámetros!$D$20=0,0,COUNTIFS(Sesiones!$A$4:$A$903,$A19,Sesiones!$B$4:$B$903,Parámetros!$B$20)/Parámetros!$D$20) -> 0 | N19: =IF(Parámetros!$D$21=0,0,COUNTIFS(Sesiones!$A$4:$A$903,$A19,Sesiones!$B$4:$B$903,Parámetros!$B$21)/Parámetros!$D$21) -> 0 | O19: =IF(Parámetros!$D$22=0,0,COUNTIFS(Sesiones!$A$4:$A$903,$A19,Sesiones!$B$4:$B$903,Parámetros!$B$22)/Parámetros!$D$22) -> 0 | P19: =IF(Parámetros!$D$23=0,0,COUNTIFS(Sesiones!$A$4:$A$903,$A19,Sesiones!$B$4:$B$903,Parámetros!$B$23)/Parámetros!$D$23) -> 0 | Q19: =IF(Parámetros!$D$24=0,0,COUNTIFS(Sesiones!$A$4:$A$903,$A19,Sesiones!$B$4:$B$903,Parámetros!$B$24)/Parámetros!$D$24) -> 0 | R19: =IF(Parámetros!$D$25=0,0,COUNTIFS(Sesiones!$A$4:$A$903,$A19,Sesiones!$B$4:$B$903,Parámetros!$B$25)/Parámetros!$D$25) -> 0 | S19: =IF(Parámetros!$D$26=0,0,COUNTIFS(Sesiones!$A$4:$A$903,$A19,Sesiones!$B$4:$B$903,Parámetros!$B$26)/Parámetros!$D$26) -> 0 | T19: =IF(Parámetros!$D$27=0,0,COUNTIFS(Sesiones!$A$4:$A$903,$A19,Sesiones!$B$4:$B$903,Parámetros!$B$27)/Parámetros!$D$27) -> 0
A20: =DATE(Parámetros!$C$6,Parámetros!$C$7,17) -> 46251 | B20: =SUMIFS('Caja Diaria'!$F$4:$F$403,'Caja Diaria'!$B$4:$B$403,"Ingreso",'Caja Diaria'!$A$4:$A$403,$A20) -> 0 | C20: =SUMIFS('Caja Diaria'!$F$4:$F$403,'Caja Diaria'!$B$4:$B$403,"Egreso",'Caja Diaria'!$A$4:$A$403,$A20) -> 0 | D20: =B20-C20 -> 0 | E20: =E19+D20 -> 5761500 | F20: =F19+SUMIFS('Caja Diaria'!$F$4:$F$403,'Caja Diaria'!$B$4:$B$403,"Ingreso",'Caja Diaria'!$E$4:$E$403,"Efectivo",'Caja Diaria'!$A$4:$A$403,$A20)-SUMIFS('Caja Diaria'!$F$4:$F$403,'Caja Diaria'!$B$4:$B$403,"Egreso",'Caja Diaria'!$E$4:$E$403,"Efectivo",'Caja Diaria'!$A$4:$A$403,$A20) -> 468000 | G20: =B20/Parámetros!$C$8 -> 0 | H20: =IF(Parámetros!$D$15=0,0,COUNTIFS(Sesiones!$A$4:$A$903,$A20,Sesiones!$B$4:$B$903,Parámetros!$B$15)/Parámetros!$D$15) -> 0 | I20: =IF(Parámetros!$D$16=0,0,COUNTIFS(Sesiones!$A$4:$A$903,$A20,Sesiones!$B$4:$B$903,Parámetros!$B$16)/Parámetros!$D$16) -> 0 | J20: =IF(Parámetros!$D$17=0,0,COUNTIFS(Sesiones!$A$4:$A$903,$A20,Sesiones!$B$4:$B$903,Parámetros!$B$17)/Parámetros!$D$17) -> 0 | K20: =IF(Parámetros!$D$18=0,0,COUNTIFS(Sesiones!$A$4:$A$903,$A20,Sesiones!$B$4:$B$903,Parámetros!$B$18)/Parámetros!$D$18) -> 0 | L20: =IF(Parámetros!$D$19=0,0,COUNTIFS(Sesiones!$A$4:$A$903,$A20,Sesiones!$B$4:$B$903,Parámetros!$B$19)/Parámetros!$D$19) -> 0 | M20: =IF(Parámetros!$D$20=0,0,COUNTIFS(Sesiones!$A$4:$A$903,$A20,Sesiones!$B$4:$B$903,Parámetros!$B$20)/Parámetros!$D$20) -> 0 | N20: =IF(Parámetros!$D$21=0,0,COUNTIFS(Sesiones!$A$4:$A$903,$A20,Sesiones!$B$4:$B$903,Parámetros!$B$21)/Parámetros!$D$21) -> 0 | O20: =IF(Parámetros!$D$22=0,0,COUNTIFS(Sesiones!$A$4:$A$903,$A20,Sesiones!$B$4:$B$903,Parámetros!$B$22)/Parámetros!$D$22) -> 0 | P20: =IF(Parámetros!$D$23=0,0,COUNTIFS(Sesiones!$A$4:$A$903,$A20,Sesiones!$B$4:$B$903,Parámetros!$B$23)/Parámetros!$D$23) -> 0 | Q20: =IF(Parámetros!$D$24=0,0,COUNTIFS(Sesiones!$A$4:$A$903,$A20,Sesiones!$B$4:$B$903,Parámetros!$B$24)/Parámetros!$D$24) -> 0 | R20: =IF(Parámetros!$D$25=0,0,COUNTIFS(Sesiones!$A$4:$A$903,$A20,Sesiones!$B$4:$B$903,Parámetros!$B$25)/Parámetros!$D$25) -> 0 | S20: =IF(Parámetros!$D$26=0,0,COUNTIFS(Sesiones!$A$4:$A$903,$A20,Sesiones!$B$4:$B$903,Parámetros!$B$26)/Parámetros!$D$26) -> 0 | T20: =IF(Parámetros!$D$27=0,0,COUNTIFS(Sesiones!$A$4:$A$903,$A20,Sesiones!$B$4:$B$903,Parámetros!$B$27)/Parámetros!$D$27) -> 0
A21: =DATE(Parámetros!$C$6,Parámetros!$C$7,18) -> 46252 | B21: =SUMIFS('Caja Diaria'!$F$4:$F$403,'Caja Diaria'!$B$4:$B$403,"Ingreso",'Caja Diaria'!$A$4:$A$403,$A21) -> 0 | C21: =SUMIFS('Caja Diaria'!$F$4:$F$403,'Caja Diaria'!$B$4:$B$403,"Egreso",'Caja Diaria'!$A$4:$A$403,$A21) -> 0 | D21: =B21-C21 -> 0 | E21: =E20+D21 -> 5761500 | F21: =F20+SUMIFS('Caja Diaria'!$F$4:$F$403,'Caja Diaria'!$B$4:$B$403,"Ingreso",'Caja Diaria'!$E$4:$E$403,"Efectivo",'Caja Diaria'!$A$4:$A$403,$A21)-SUMIFS('Caja Diaria'!$F$4:$F$403,'Caja Diaria'!$B$4:$B$403,"Egreso",'Caja Diaria'!$E$4:$E$403,"Efectivo",'Caja Diaria'!$A$4:$A$403,$A21) -> 468000 | G21: =B21/Parámetros!$C$8 -> 0 | H21: =IF(Parámetros!$D$15=0,0,COUNTIFS(Sesiones!$A$4:$A$903,$A21,Sesiones!$B$4:$B$903,Parámetros!$B$15)/Parámetros!$D$15) -> 0 | I21: =IF(Parámetros!$D$16=0,0,COUNTIFS(Sesiones!$A$4:$A$903,$A21,Sesiones!$B$4:$B$903,Parámetros!$B$16)/Parámetros!$D$16) -> 0 | J21: =IF(Parámetros!$D$17=0,0,COUNTIFS(Sesiones!$A$4:$A$903,$A21,Sesiones!$B$4:$B$903,Parámetros!$B$17)/Parámetros!$D$17) -> 0 | K21: =IF(Parámetros!$D$18=0,0,COUNTIFS(Sesiones!$A$4:$A$903,$A21,Sesiones!$B$4:$B$903,Parámetros!$B$18)/Parámetros!$D$18) -> 0 | L21: =IF(Parámetros!$D$19=0,0,COUNTIFS(Sesiones!$A$4:$A$903,$A21,Sesiones!$B$4:$B$903,Parámetros!$B$19)/Parámetros!$D$19) -> 0 | M21: =IF(Parámetros!$D$20=0,0,COUNTIFS(Sesiones!$A$4:$A$903,$A21,Sesiones!$B$4:$B$903,Parámetros!$B$20)/Parámetros!$D$20) -> 0 | N21: =IF(Parámetros!$D$21=0,0,COUNTIFS(Sesiones!$A$4:$A$903,$A21,Sesiones!$B$4:$B$903,Parámetros!$B$21)/Parámetros!$D$21) -> 0 | O21: =IF(Parámetros!$D$22=0,0,COUNTIFS(Sesiones!$A$4:$A$903,$A21,Sesiones!$B$4:$B$903,Parámetros!$B$22)/Parámetros!$D$22) -> 0 | P21: =IF(Parámetros!$D$23=0,0,COUNTIFS(Sesiones!$A$4:$A$903,$A21,Sesiones!$B$4:$B$903,Parámetros!$B$23)/Parámetros!$D$23) -> 0 | Q21: =IF(Parámetros!$D$24=0,0,COUNTIFS(Sesiones!$A$4:$A$903,$A21,Sesiones!$B$4:$B$903,Parámetros!$B$24)/Parámetros!$D$24) -> 0 | R21: =IF(Parámetros!$D$25=0,0,COUNTIFS(Sesiones!$A$4:$A$903,$A21,Sesiones!$B$4:$B$903,Parámetros!$B$25)/Parámetros!$D$25) -> 0 | S21: =IF(Parámetros!$D$26=0,0,COUNTIFS(Sesiones!$A$4:$A$903,$A21,Sesiones!$B$4:$B$903,Parámetros!$B$26)/Parámetros!$D$26) -> 0 | T21: =IF(Parámetros!$D$27=0,0,COUNTIFS(Sesiones!$A$4:$A$903,$A21,Sesiones!$B$4:$B$903,Parámetros!$B$27)/Parámetros!$D$27) -> 0
A22: =DATE(Parámetros!$C$6,Parámetros!$C$7,19) -> 46253 | B22: =SUMIFS('Caja Diaria'!$F$4:$F$403,'Caja Diaria'!$B$4:$B$403,"Ingreso",'Caja Diaria'!$A$4:$A$403,$A22) -> 0 | C22: =SUMIFS('Caja Diaria'!$F$4:$F$403,'Caja Diaria'!$B$4:$B$403,"Egreso",'Caja Diaria'!$A$4:$A$403,$A22) -> 0 | D22: =B22-C22 -> 0 | E22: =E21+D22 -> 5761500 | F22: =F21+SUMIFS('Caja Diaria'!$F$4:$F$403,'Caja Diaria'!$B$4:$B$403,"Ingreso",'Caja Diaria'!$E$4:$E$403,"Efectivo",'Caja Diaria'!$A$4:$A$403,$A22)-SUMIFS('Caja Diaria'!$F$4:$F$403,'Caja Diaria'!$B$4:$B$403,"Egreso",'Caja Diaria'!$E$4:$E$403,"Efectivo",'Caja Diaria'!$A$4:$A$403,$A22) -> 468000 | G22: =B22/Parámetros!$C$8 -> 0 | H22: =IF(Parámetros!$D$15=0,0,COUNTIFS(Sesiones!$A$4:$A$903,$A22,Sesiones!$B$4:$B$903,Parámetros!$B$15)/Parámetros!$D$15) -> 0 | I22: =IF(Parámetros!$D$16=0,0,COUNTIFS(Sesiones!$A$4:$A$903,$A22,Sesiones!$B$4:$B$903,Parámetros!$B$16)/Parámetros!$D$16) -> 0 | J22: =IF(Parámetros!$D$17=0,0,COUNTIFS(Sesiones!$A$4:$A$903,$A22,Sesiones!$B$4:$B$903,Parámetros!$B$17)/Parámetros!$D$17) -> 0 | K22: =IF(Parámetros!$D$18=0,0,COUNTIFS(Sesiones!$A$4:$A$903,$A22,Sesiones!$B$4:$B$903,Parámetros!$B$18)/Parámetros!$D$18) -> 0 | L22: =IF(Parámetros!$D$19=0,0,COUNTIFS(Sesiones!$A$4:$A$903,$A22,Sesiones!$B$4:$B$903,Parámetros!$B$19)/Parámetros!$D$19) -> 0 | M22: =IF(Parámetros!$D$20=0,0,COUNTIFS(Sesiones!$A$4:$A$903,$A22,Sesiones!$B$4:$B$903,Parámetros!$B$20)/Parámetros!$D$20) -> 0 | N22: =IF(Parámetros!$D$21=0,0,COUNTIFS(Sesiones!$A$4:$A$903,$A22,Sesiones!$B$4:$B$903,Parámetros!$B$21)/Parámetros!$D$21) -> 0 | O22: =IF(Parámetros!$D$22=0,0,COUNTIFS(Sesiones!$A$4:$A$903,$A22,Sesiones!$B$4:$B$903,Parámetros!$B$22)/Parámetros!$D$22) -> 0 | P22: =IF(Parámetros!$D$23=0,0,COUNTIFS(Sesiones!$A$4:$A$903,$A22,Sesiones!$B$4:$B$903,Parámetros!$B$23)/Parámetros!$D$23) -> 0 | Q22: =IF(Parámetros!$D$24=0,0,COUNTIFS(Sesiones!$A$4:$A$903,$A22,Sesiones!$B$4:$B$903,Parámetros!$B$24)/Parámetros!$D$24) -> 0 | R22: =IF(Parámetros!$D$25=0,0,COUNTIFS(Sesiones!$A$4:$A$903,$A22,Sesiones!$B$4:$B$903,Parámetros!$B$25)/Parámetros!$D$25) -> 0 | S22: =IF(Parámetros!$D$26=0,0,COUNTIFS(Sesiones!$A$4:$A$903,$A22,Sesiones!$B$4:$B$903,Parámetros!$B$26)/Parámetros!$D$26) -> 0 | T22: =IF(Parámetros!$D$27=0,0,COUNTIFS(Sesiones!$A$4:$A$903,$A22,Sesiones!$B$4:$B$903,Parámetros!$B$27)/Parámetros!$D$27) -> 0
A23: =DATE(Parámetros!$C$6,Parámetros!$C$7,20) -> 46254 | B23: =SUMIFS('Caja Diaria'!$F$4:$F$403,'Caja Diaria'!$B$4:$B$403,"Ingreso",'Caja Diaria'!$A$4:$A$403,$A23) -> 0 | C23: =SUMIFS('Caja Diaria'!$F$4:$F$403,'Caja Diaria'!$B$4:$B$403,"Egreso",'Caja Diaria'!$A$4:$A$403,$A23) -> 0 | D23: =B23-C23 -> 0 | E23: =E22+D23 -> 5761500 | F23: =F22+SUMIFS('Caja Diaria'!$F$4:$F$403,'Caja Diaria'!$B$4:$B$403,"Ingreso",'Caja Diaria'!$E$4:$E$403,"Efectivo",'Caja Diaria'!$A$4:$A$403,$A23)-SUMIFS('Caja Diaria'!$F$4:$F$403,'Caja Diaria'!$B$4:$B$403,"Egreso",'Caja Diaria'!$E$4:$E$403,"Efectivo",'Caja Diaria'!$A$4:$A$403,$A23) -> 468000 | G23: =B23/Parámetros!$C$8 -> 0 | H23: =IF(Parámetros!$D$15=0,0,COUNTIFS(Sesiones!$A$4:$A$903,$A23,Sesiones!$B$4:$B$903,Parámetros!$B$15)/Parámetros!$D$15) -> 0 | I23: =IF(Parámetros!$D$16=0,0,COUNTIFS(Sesiones!$A$4:$A$903,$A23,Sesiones!$B$4:$B$903,Parámetros!$B$16)/Parámetros!$D$16) -> 0 | J23: =IF(Parámetros!$D$17=0,0,COUNTIFS(Sesiones!$A$4:$A$903,$A23,Sesiones!$B$4:$B$903,Parámetros!$B$17)/Parámetros!$D$17) -> 0 | K23: =IF(Parámetros!$D$18=0,0,COUNTIFS(Sesiones!$A$4:$A$903,$A23,Sesiones!$B$4:$B$903,Parámetros!$B$18)/Parámetros!$D$18) -> 0 | L23: =IF(Parámetros!$D$19=0,0,COUNTIFS(Sesiones!$A$4:$A$903,$A23,Sesiones!$B$4:$B$903,Parámetros!$B$19)/Parámetros!$D$19) -> 0 | M23: =IF(Parámetros!$D$20=0,0,COUNTIFS(Sesiones!$A$4:$A$903,$A23,Sesiones!$B$4:$B$903,Parámetros!$B$20)/Parámetros!$D$20) -> 0 | N23: =IF(Parámetros!$D$21=0,0,COUNTIFS(Sesiones!$A$4:$A$903,$A23,Sesiones!$B$4:$B$903,Parámetros!$B$21)/Parámetros!$D$21) -> 0 | O23: =IF(Parámetros!$D$22=0,0,COUNTIFS(Sesiones!$A$4:$A$903,$A23,Sesiones!$B$4:$B$903,Parámetros!$B$22)/Parámetros!$D$22) -> 0 | P23: =IF(Parámetros!$D$23=0,0,COUNTIFS(Sesiones!$A$4:$A$903,$A23,Sesiones!$B$4:$B$903,Parámetros!$B$23)/Parámetros!$D$23) -> 0 | Q23: =IF(Parámetros!$D$24=0,0,COUNTIFS(Sesiones!$A$4:$A$903,$A23,Sesiones!$B$4:$B$903,Parámetros!$B$24)/Parámetros!$D$24) -> 0 | R23: =IF(Parámetros!$D$25=0,0,COUNTIFS(Sesiones!$A$4:$A$903,$A23,Sesiones!$B$4:$B$903,Parámetros!$B$25)/Parámetros!$D$25) -> 0 | S23: =IF(Parámetros!$D$26=0,0,COUNTIFS(Sesiones!$A$4:$A$903,$A23,Sesiones!$B$4:$B$903,Parámetros!$B$26)/Parámetros!$D$26) -> 0 | T23: =IF(Parámetros!$D$27=0,0,COUNTIFS(Sesiones!$A$4:$A$903,$A23,Sesiones!$B$4:$B$903,Parámetros!$B$27)/Parámetros!$D$27) -> 0
A24: =DATE(Parámetros!$C$6,Parámetros!$C$7,21) -> 46255 | B24: =SUMIFS('Caja Diaria'!$F$4:$F$403,'Caja Diaria'!$B$4:$B$403,"Ingreso",'Caja Diaria'!$A$4:$A$403,$A24) -> 0 | C24: =SUMIFS('Caja Diaria'!$F$4:$F$403,'Caja Diaria'!$B$4:$B$403,"Egreso",'Caja Diaria'!$A$4:$A$403,$A24) -> 0 | D24: =B24-C24 -> 0 | E24: =E23+D24 -> 5761500 | F24: =F23+SUMIFS('Caja Diaria'!$F$4:$F$403,'Caja Diaria'!$B$4:$B$403,"Ingreso",'Caja Diaria'!$E$4:$E$403,"Efectivo",'Caja Diaria'!$A$4:$A$403,$A24)-SUMIFS('Caja Diaria'!$F$4:$F$403,'Caja Diaria'!$B$4:$B$403,"Egreso",'Caja Diaria'!$E$4:$E$403,"Efectivo",'Caja Diaria'!$A$4:$A$403,$A24) -> 468000 | G24: =B24/Parámetros!$C$8 -> 0 | H24: =IF(Parámetros!$D$15=0,0,COUNTIFS(Sesiones!$A$4:$A$903,$A24,Sesiones!$B$4:$B$903,Parámetros!$B$15)/Parámetros!$D$15) -> 0 | I24: =IF(Parámetros!$D$16=0,0,COUNTIFS(Sesiones!$A$4:$A$903,$A24,Sesiones!$B$4:$B$903,Parámetros!$B$16)/Parámetros!$D$16) -> 0 | J24: =IF(Parámetros!$D$17=0,0,COUNTIFS(Sesiones!$A$4:$A$903,$A24,Sesiones!$B$4:$B$903,Parámetros!$B$17)/Parámetros!$D$17) -> 0 | K24: =IF(Parámetros!$D$18=0,0,COUNTIFS(Sesiones!$A$4:$A$903,$A24,Sesiones!$B$4:$B$903,Parámetros!$B$18)/Parámetros!$D$18) -> 0 | L24: =IF(Parámetros!$D$19=0,0,COUNTIFS(Sesiones!$A$4:$A$903,$A24,Sesiones!$B$4:$B$903,Parámetros!$B$19)/Parámetros!$D$19) -> 0 | M24: =IF(Parámetros!$D$20=0,0,COUNTIFS(Sesiones!$A$4:$A$903,$A24,Sesiones!$B$4:$B$903,Parámetros!$B$20)/Parámetros!$D$20) -> 0 | N24: =IF(Parámetros!$D$21=0,0,COUNTIFS(Sesiones!$A$4:$A$903,$A24,Sesiones!$B$4:$B$903,Parámetros!$B$21)/Parámetros!$D$21) -> 0 | O24: =IF(Parámetros!$D$22=0,0,COUNTIFS(Sesiones!$A$4:$A$903,$A24,Sesiones!$B$4:$B$903,Parámetros!$B$22)/Parámetros!$D$22) -> 0 | P24: =IF(Parámetros!$D$23=0,0,COUNTIFS(Sesiones!$A$4:$A$903,$A24,Sesiones!$B$4:$B$903,Parámetros!$B$23)/Parámetros!$D$23) -> 0 | Q24: =IF(Parámetros!$D$24=0,0,COUNTIFS(Sesiones!$A$4:$A$903,$A24,Sesiones!$B$4:$B$903,Parámetros!$B$24)/Parámetros!$D$24) -> 0 | R24: =IF(Parámetros!$D$25=0,0,COUNTIFS(Sesiones!$A$4:$A$903,$A24,Sesiones!$B$4:$B$903,Parámetros!$B$25)/Parámetros!$D$25) -> 0 | S24: =IF(Parámetros!$D$26=0,0,COUNTIFS(Sesiones!$A$4:$A$903,$A24,Sesiones!$B$4:$B$903,Parámetros!$B$26)/Parámetros!$D$26) -> 0 | T24: =IF(Parámetros!$D$27=0,0,COUNTIFS(Sesiones!$A$4:$A$903,$A24,Sesiones!$B$4:$B$903,Parámetros!$B$27)/Parámetros!$D$27) -> 0
A25: =DATE(Parámetros!$C$6,Parámetros!$C$7,22) -> 46256 | B25: =SUMIFS('Caja Diaria'!$F$4:$F$403,'Caja Diaria'!$B$4:$B$403,"Ingreso",'Caja Diaria'!$A$4:$A$403,$A25) -> 0 | C25: =SUMIFS('Caja Diaria'!$F$4:$F$403,'Caja Diaria'!$B$4:$B$403,"Egreso",'Caja Diaria'!$A$4:$A$403,$A25) -> 0 | D25: =B25-C25 -> 0 | E25: =E24+D25 -> 5761500 | F25: =F24+SUMIFS('Caja Diaria'!$F$4:$F$403,'Caja Diaria'!$B$4:$B$403,"Ingreso",'Caja Diaria'!$E$4:$E$403,"Efectivo",'Caja Diaria'!$A$4:$A$403,$A25)-SUMIFS('Caja Diaria'!$F$4:$F$403,'Caja Diaria'!$B$4:$B$403,"Egreso",'Caja Diaria'!$E$4:$E$403,"Efectivo",'Caja Diaria'!$A$4:$A$403,$A25) -> 468000 | G25: =B25/Parámetros!$C$8 -> 0 | H25: =IF(Parámetros!$D$15=0,0,COUNTIFS(Sesiones!$A$4:$A$903,$A25,Sesiones!$B$4:$B$903,Parámetros!$B$15)/Parámetros!$D$15) -> 0 | I25: =IF(Parámetros!$D$16=0,0,COUNTIFS(Sesiones!$A$4:$A$903,$A25,Sesiones!$B$4:$B$903,Parámetros!$B$16)/Parámetros!$D$16) -> 0 | J25: =IF(Parámetros!$D$17=0,0,COUNTIFS(Sesiones!$A$4:$A$903,$A25,Sesiones!$B$4:$B$903,Parámetros!$B$17)/Parámetros!$D$17) -> 0 | K25: =IF(Parámetros!$D$18=0,0,COUNTIFS(Sesiones!$A$4:$A$903,$A25,Sesiones!$B$4:$B$903,Parámetros!$B$18)/Parámetros!$D$18) -> 0 | L25: =IF(Parámetros!$D$19=0,0,COUNTIFS(Sesiones!$A$4:$A$903,$A25,Sesiones!$B$4:$B$903,Parámetros!$B$19)/Parámetros!$D$19) -> 0 | M25: =IF(Parámetros!$D$20=0,0,COUNTIFS(Sesiones!$A$4:$A$903,$A25,Sesiones!$B$4:$B$903,Parámetros!$B$20)/Parámetros!$D$20) -> 0 | N25: =IF(Parámetros!$D$21=0,0,COUNTIFS(Sesiones!$A$4:$A$903,$A25,Sesiones!$B$4:$B$903,Parámetros!$B$21)/Parámetros!$D$21) -> 0 | O25: =IF(Parámetros!$D$22=0,0,COUNTIFS(Sesiones!$A$4:$A$903,$A25,Sesiones!$B$4:$B$903,Parámetros!$B$22)/Parámetros!$D$22) -> 0 | P25: =IF(Parámetros!$D$23=0,0,COUNTIFS(Sesiones!$A$4:$A$903,$A25,Sesiones!$B$4:$B$903,Parámetros!$B$23)/Parámetros!$D$23) -> 0 | Q25: =IF(Parámetros!$D$24=0,0,COUNTIFS(Sesiones!$A$4:$A$903,$A25,Sesiones!$B$4:$B$903,Parámetros!$B$24)/Parámetros!$D$24) -> 0 | R25: =IF(Parámetros!$D$25=0,0,COUNTIFS(Sesiones!$A$4:$A$903,$A25,Sesiones!$B$4:$B$903,Parámetros!$B$25)/Parámetros!$D$25) -> 0 | S25: =IF(Parámetros!$D$26=0,0,COUNTIFS(Sesiones!$A$4:$A$903,$A25,Sesiones!$B$4:$B$903,Parámetros!$B$26)/Parámetros!$D$26) -> 0 | T25: =IF(Parámetros!$D$27=0,0,COUNTIFS(Sesiones!$A$4:$A$903,$A25,Sesiones!$B$4:$B$903,Parámetros!$B$27)/Parámetros!$D$27) -> 0
A26: =DATE(Parámetros!$C$6,Parámetros!$C$7,23) -> 46257 | B26: =SUMIFS('Caja Diaria'!$F$4:$F$403,'Caja Diaria'!$B$4:$B$403,"Ingreso",'Caja Diaria'!$A$4:$A$403,$A26) -> 0 | C26: =SUMIFS('Caja Diaria'!$F$4:$F$403,'Caja Diaria'!$B$4:$B$403,"Egreso",'Caja Diaria'!$A$4:$A$403,$A26) -> 0 | D26: =B26-C26 -> 0 | E26: =E25+D26 -> 5761500 | F26: =F25+SUMIFS('Caja Diaria'!$F$4:$F$403,'Caja Diaria'!$B$4:$B$403,"Ingreso",'Caja Diaria'!$E$4:$E$403,"Efectivo",'Caja Diaria'!$A$4:$A$403,$A26)-SUMIFS('Caja Diaria'!$F$4:$F$403,'Caja Diaria'!$B$4:$B$403,"Egreso",'Caja Diaria'!$E$4:$E$403,"Efectivo",'Caja Diaria'!$A$4:$A$403,$A26) -> 468000 | G26: =B26/Parámetros!$C$8 -> 0 | H26: =IF(Parámetros!$D$15=0,0,COUNTIFS(Sesiones!$A$4:$A$903,$A26,Sesiones!$B$4:$B$903,Parámetros!$B$15)/Parámetros!$D$15) -> 0 | I26: =IF(Parámetros!$D$16=0,0,COUNTIFS(Sesiones!$A$4:$A$903,$A26,Sesiones!$B$4:$B$903,Parámetros!$B$16)/Parámetros!$D$16) -> 0 | J26: =IF(Parámetros!$D$17=0,0,COUNTIFS(Sesiones!$A$4:$A$903,$A26,Sesiones!$B$4:$B$903,Parámetros!$B$17)/Parámetros!$D$17) -> 0 | K26: =IF(Parámetros!$D$18=0,0,COUNTIFS(Sesiones!$A$4:$A$903,$A26,Sesiones!$B$4:$B$903,Parámetros!$B$18)/Parámetros!$D$18) -> 0 | L26: =IF(Parámetros!$D$19=0,0,COUNTIFS(Sesiones!$A$4:$A$903,$A26,Sesiones!$B$4:$B$903,Parámetros!$B$19)/Parámetros!$D$19) -> 0 | M26: =IF(Parámetros!$D$20=0,0,COUNTIFS(Sesiones!$A$4:$A$903,$A26,Sesiones!$B$4:$B$903,Parámetros!$B$20)/Parámetros!$D$20) -> 0 | N26: =IF(Parámetros!$D$21=0,0,COUNTIFS(Sesiones!$A$4:$A$903,$A26,Sesiones!$B$4:$B$903,Parámetros!$B$21)/Parámetros!$D$21) -> 0 | O26: =IF(Parámetros!$D$22=0,0,COUNTIFS(Sesiones!$A$4:$A$903,$A26,Sesiones!$B$4:$B$903,Parámetros!$B$22)/Parámetros!$D$22) -> 0 | P26: =IF(Parámetros!$D$23=0,0,COUNTIFS(Sesiones!$A$4:$A$903,$A26,Sesiones!$B$4:$B$903,Parámetros!$B$23)/Parámetros!$D$23) -> 0 | Q26: =IF(Parámetros!$D$24=0,0,COUNTIFS(Sesiones!$A$4:$A$903,$A26,Sesiones!$B$4:$B$903,Parámetros!$B$24)/Parámetros!$D$24) -> 0 | R26: =IF(Parámetros!$D$25=0,0,COUNTIFS(Sesiones!$A$4:$A$903,$A26,Sesiones!$B$4:$B$903,Parámetros!$B$25)/Parámetros!$D$25) -> 0 | S26: =IF(Parámetros!$D$26=0,0,COUNTIFS(Sesiones!$A$4:$A$903,$A26,Sesiones!$B$4:$B$903,Parámetros!$B$26)/Parámetros!$D$26) -> 0 | T26: =IF(Parámetros!$D$27=0,0,COUNTIFS(Sesiones!$A$4:$A$903,$A26,Sesiones!$B$4:$B$903,Parámetros!$B$27)/Parámetros!$D$27) -> 0
A27: =DATE(Parámetros!$C$6,Parámetros!$C$7,24) -> 46258 | B27: =SUMIFS('Caja Diaria'!$F$4:$F$403,'Caja Diaria'!$B$4:$B$403,"Ingreso",'Caja Diaria'!$A$4:$A$403,$A27) -> 0 | C27: =SUMIFS('Caja Diaria'!$F$4:$F$403,'Caja Diaria'!$B$4:$B$403,"Egreso",'Caja Diaria'!$A$4:$A$403,$A27) -> 0 | D27: =B27-C27 -> 0 | E27: =E26+D27 -> 5761500 | F27: =F26+SUMIFS('Caja Diaria'!$F$4:$F$403,'Caja Diaria'!$B$4:$B$403,"Ingreso",'Caja Diaria'!$E$4:$E$403,"Efectivo",'Caja Diaria'!$A$4:$A$403,$A27)-SUMIFS('Caja Diaria'!$F$4:$F$403,'Caja Diaria'!$B$4:$B$403,"Egreso",'Caja Diaria'!$E$4:$E$403,"Efectivo",'Caja Diaria'!$A$4:$A$403,$A27) -> 468000 | G27: =B27/Parámetros!$C$8 -> 0 | H27: =IF(Parámetros!$D$15=0,0,COUNTIFS(Sesiones!$A$4:$A$903,$A27,Sesiones!$B$4:$B$903,Parámetros!$B$15)/Parámetros!$D$15) -> 0 | I27: =IF(Parámetros!$D$16=0,0,COUNTIFS(Sesiones!$A$4:$A$903,$A27,Sesiones!$B$4:$B$903,Parámetros!$B$16)/Parámetros!$D$16) -> 0 | J27: =IF(Parámetros!$D$17=0,0,COUNTIFS(Sesiones!$A$4:$A$903,$A27,Sesiones!$B$4:$B$903,Parámetros!$B$17)/Parámetros!$D$17) -> 0 | K27: =IF(Parámetros!$D$18=0,0,COUNTIFS(Sesiones!$A$4:$A$903,$A27,Sesiones!$B$4:$B$903,Parámetros!$B$18)/Parámetros!$D$18) -> 0 | L27: =IF(Parámetros!$D$19=0,0,COUNTIFS(Sesiones!$A$4:$A$903,$A27,Sesiones!$B$4:$B$903,Parámetros!$B$19)/Parámetros!$D$19) -> 0 | M27: =IF(Parámetros!$D$20=0,0,COUNTIFS(Sesiones!$A$4:$A$903,$A27,Sesiones!$B$4:$B$903,Parámetros!$B$20)/Parámetros!$D$20) -> 0 | N27: =IF(Parámetros!$D$21=0,0,COUNTIFS(Sesiones!$A$4:$A$903,$A27,Sesiones!$B$4:$B$903,Parámetros!$B$21)/Parámetros!$D$21) -> 0 | O27: =IF(Parámetros!$D$22=0,0,COUNTIFS(Sesiones!$A$4:$A$903,$A27,Sesiones!$B$4:$B$903,Parámetros!$B$22)/Parámetros!$D$22) -> 0 | P27: =IF(Parámetros!$D$23=0,0,COUNTIFS(Sesiones!$A$4:$A$903,$A27,Sesiones!$B$4:$B$903,Parámetros!$B$23)/Parámetros!$D$23) -> 0 | Q27: =IF(Parámetros!$D$24=0,0,COUNTIFS(Sesiones!$A$4:$A$903,$A27,Sesiones!$B$4:$B$903,Parámetros!$B$24)/Parámetros!$D$24) -> 0 | R27: =IF(Parámetros!$D$25=0,0,COUNTIFS(Sesiones!$A$4:$A$903,$A27,Sesiones!$B$4:$B$903,Parámetros!$B$25)/Parámetros!$D$25) -> 0 | S27: =IF(Parámetros!$D$26=0,0,COUNTIFS(Sesiones!$A$4:$A$903,$A27,Sesiones!$B$4:$B$903,Parámetros!$B$26)/Parámetros!$D$26) -> 0 | T27: =IF(Parámetros!$D$27=0,0,COUNTIFS(Sesiones!$A$4:$A$903,$A27,Sesiones!$B$4:$B$903,Parámetros!$B$27)/Parámetros!$D$27) -> 0
A28: =DATE(Parámetros!$C$6,Parámetros!$C$7,25) -> 46259 | B28: =SUMIFS('Caja Diaria'!$F$4:$F$403,'Caja Diaria'!$B$4:$B$403,"Ingreso",'Caja Diaria'!$A$4:$A$403,$A28) -> 0 | C28: =SUMIFS('Caja Diaria'!$F$4:$F$403,'Caja Diaria'!$B$4:$B$403,"Egreso",'Caja Diaria'!$A$4:$A$403,$A28) -> 0 | D28: =B28-C28 -> 0 | E28: =E27+D28 -> 5761500 | F28: =F27+SUMIFS('Caja Diaria'!$F$4:$F$403,'Caja Diaria'!$B$4:$B$403,"Ingreso",'Caja Diaria'!$E$4:$E$403,"Efectivo",'Caja Diaria'!$A$4:$A$403,$A28)-SUMIFS('Caja Diaria'!$F$4:$F$403,'Caja Diaria'!$B$4:$B$403,"Egreso",'Caja Diaria'!$E$4:$E$403,"Efectivo",'Caja Diaria'!$A$4:$A$403,$A28) -> 468000 | G28: =B28/Parámetros!$C$8 -> 0 | H28: =IF(Parámetros!$D$15=0,0,COUNTIFS(Sesiones!$A$4:$A$903,$A28,Sesiones!$B$4:$B$903,Parámetros!$B$15)/Parámetros!$D$15) -> 0 | I28: =IF(Parámetros!$D$16=0,0,COUNTIFS(Sesiones!$A$4:$A$903,$A28,Sesiones!$B$4:$B$903,Parámetros!$B$16)/Parámetros!$D$16) -> 0 | J28: =IF(Parámetros!$D$17=0,0,COUNTIFS(Sesiones!$A$4:$A$903,$A28,Sesiones!$B$4:$B$903,Parámetros!$B$17)/Parámetros!$D$17) -> 0 | K28: =IF(Parámetros!$D$18=0,0,COUNTIFS(Sesiones!$A$4:$A$903,$A28,Sesiones!$B$4:$B$903,Parámetros!$B$18)/Parámetros!$D$18) -> 0 | L28: =IF(Parámetros!$D$19=0,0,COUNTIFS(Sesiones!$A$4:$A$903,$A28,Sesiones!$B$4:$B$903,Parámetros!$B$19)/Parámetros!$D$19) -> 0 | M28: =IF(Parámetros!$D$20=0,0,COUNTIFS(Sesiones!$A$4:$A$903,$A28,Sesiones!$B$4:$B$903,Parámetros!$B$20)/Parámetros!$D$20) -> 0 | N28: =IF(Parámetros!$D$21=0,0,COUNTIFS(Sesiones!$A$4:$A$903,$A28,Sesiones!$B$4:$B$903,Parámetros!$B$21)/Parámetros!$D$21) -> 0 | O28: =IF(Parámetros!$D$22=0,0,COUNTIFS(Sesiones!$A$4:$A$903,$A28,Sesiones!$B$4:$B$903,Parámetros!$B$22)/Parámetros!$D$22) -> 0 | P28: =IF(Parámetros!$D$23=0,0,COUNTIFS(Sesiones!$A$4:$A$903,$A28,Sesiones!$B$4:$B$903,Parámetros!$B$23)/Parámetros!$D$23) -> 0 | Q28: =IF(Parámetros!$D$24=0,0,COUNTIFS(Sesiones!$A$4:$A$903,$A28,Sesiones!$B$4:$B$903,Parámetros!$B$24)/Parámetros!$D$24) -> 0 | R28: =IF(Parámetros!$D$25=0,0,COUNTIFS(Sesiones!$A$4:$A$903,$A28,Sesiones!$B$4:$B$903,Parámetros!$B$25)/Parámetros!$D$25) -> 0 | S28: =IF(Parámetros!$D$26=0,0,COUNTIFS(Sesiones!$A$4:$A$903,$A28,Sesiones!$B$4:$B$903,Parámetros!$B$26)/Parámetros!$D$26) -> 0 | T28: =IF(Parámetros!$D$27=0,0,COUNTIFS(Sesiones!$A$4:$A$903,$A28,Sesiones!$B$4:$B$903,Parámetros!$B$27)/Parámetros!$D$27) -> 0
A29: =DATE(Parámetros!$C$6,Parámetros!$C$7,26) -> 46260 | B29: =SUMIFS('Caja Diaria'!$F$4:$F$403,'Caja Diaria'!$B$4:$B$403,"Ingreso",'Caja Diaria'!$A$4:$A$403,$A29) -> 0 | C29: =SUMIFS('Caja Diaria'!$F$4:$F$403,'Caja Diaria'!$B$4:$B$403,"Egreso",'Caja Diaria'!$A$4:$A$403,$A29) -> 0 | D29: =B29-C29 -> 0 | E29: =E28+D29 -> 5761500 | F29: =F28+SUMIFS('Caja Diaria'!$F$4:$F$403,'Caja Diaria'!$B$4:$B$403,"Ingreso",'Caja Diaria'!$E$4:$E$403,"Efectivo",'Caja Diaria'!$A$4:$A$403,$A29)-SUMIFS('Caja Diaria'!$F$4:$F$403,'Caja Diaria'!$B$4:$B$403,"Egreso",'Caja Diaria'!$E$4:$E$403,"Efectivo",'Caja Diaria'!$A$4:$A$403,$A29) -> 468000 | G29: =B29/Parámetros!$C$8 -> 0 | H29: =IF(Parámetros!$D$15=0,0,COUNTIFS(Sesiones!$A$4:$A$903,$A29,Sesiones!$B$4:$B$903,Parámetros!$B$15)/Parámetros!$D$15) -> 0 | I29: =IF(Parámetros!$D$16=0,0,COUNTIFS(Sesiones!$A$4:$A$903,$A29,Sesiones!$B$4:$B$903,Parámetros!$B$16)/Parámetros!$D$16) -> 0 | J29: =IF(Parámetros!$D$17=0,0,COUNTIFS(Sesiones!$A$4:$A$903,$A29,Sesiones!$B$4:$B$903,Parámetros!$B$17)/Parámetros!$D$17) -> 0 | K29: =IF(Parámetros!$D$18=0,0,COUNTIFS(Sesiones!$A$4:$A$903,$A29,Sesiones!$B$4:$B$903,Parámetros!$B$18)/Parámetros!$D$18) -> 0 | L29: =IF(Parámetros!$D$19=0,0,COUNTIFS(Sesiones!$A$4:$A$903,$A29,Sesiones!$B$4:$B$903,Parámetros!$B$19)/Parámetros!$D$19) -> 0 | M29: =IF(Parámetros!$D$20=0,0,COUNTIFS(Sesiones!$A$4:$A$903,$A29,Sesiones!$B$4:$B$903,Parámetros!$B$20)/Parámetros!$D$20) -> 0 | N29: =IF(Parámetros!$D$21=0,0,COUNTIFS(Sesiones!$A$4:$A$903,$A29,Sesiones!$B$4:$B$903,Parámetros!$B$21)/Parámetros!$D$21) -> 0 | O29: =IF(Parámetros!$D$22=0,0,COUNTIFS(Sesiones!$A$4:$A$903,$A29,Sesiones!$B$4:$B$903,Parámetros!$B$22)/Parámetros!$D$22) -> 0 | P29: =IF(Parámetros!$D$23=0,0,COUNTIFS(Sesiones!$A$4:$A$903,$A29,Sesiones!$B$4:$B$903,Parámetros!$B$23)/Parámetros!$D$23) -> 0 | Q29: =IF(Parámetros!$D$24=0,0,COUNTIFS(Sesiones!$A$4:$A$903,$A29,Sesiones!$B$4:$B$903,Parámetros!$B$24)/Parámetros!$D$24) -> 0 | R29: =IF(Parámetros!$D$25=0,0,COUNTIFS(Sesiones!$A$4:$A$903,$A29,Sesiones!$B$4:$B$903,Parámetros!$B$25)/Parámetros!$D$25) -> 0 | S29: =IF(Parámetros!$D$26=0,0,COUNTIFS(Sesiones!$A$4:$A$903,$A29,Sesiones!$B$4:$B$903,Parámetros!$B$26)/Parámetros!$D$26) -> 0 | T29: =IF(Parámetros!$D$27=0,0,COUNTIFS(Sesiones!$A$4:$A$903,$A29,Sesiones!$B$4:$B$903,Parámetros!$B$27)/Parámetros!$D$27) -> 0
A30: =DATE(Parámetros!$C$6,Parámetros!$C$7,27) -> 46261 | B30: =SUMIFS('Caja Diaria'!$F$4:$F$403,'Caja Diaria'!$B$4:$B$403,"Ingreso",'Caja Diaria'!$A$4:$A$403,$A30) -> 0 | C30: =SUMIFS('Caja Diaria'!$F$4:$F$403,'Caja Diaria'!$B$4:$B$403,"Egreso",'Caja Diaria'!$A$4:$A$403,$A30) -> 0 | D30: =B30-C30 -> 0 | E30: =E29+D30 -> 5761500 | F30: =F29+SUMIFS('Caja Diaria'!$F$4:$F$403,'Caja Diaria'!$B$4:$B$403,"Ingreso",'Caja Diaria'!$E$4:$E$403,"Efectivo",'Caja Diaria'!$A$4:$A$403,$A30)-SUMIFS('Caja Diaria'!$F$4:$F$403,'Caja Diaria'!$B$4:$B$403,"Egreso",'Caja Diaria'!$E$4:$E$403,"Efectivo",'Caja Diaria'!$A$4:$A$403,$A30) -> 468000 | G30: =B30/Parámetros!$C$8 -> 0 | H30: =IF(Parámetros!$D$15=0,0,COUNTIFS(Sesiones!$A$4:$A$903,$A30,Sesiones!$B$4:$B$903,Parámetros!$B$15)/Parámetros!$D$15) -> 0 | I30: =IF(Parámetros!$D$16=0,0,COUNTIFS(Sesiones!$A$4:$A$903,$A30,Sesiones!$B$4:$B$903,Parámetros!$B$16)/Parámetros!$D$16) -> 0 | J30: =IF(Parámetros!$D$17=0,0,COUNTIFS(Sesiones!$A$4:$A$903,$A30,Sesiones!$B$4:$B$903,Parámetros!$B$17)/Parámetros!$D$17) -> 0 | K30: =IF(Parámetros!$D$18=0,0,COUNTIFS(Sesiones!$A$4:$A$903,$A30,Sesiones!$B$4:$B$903,Parámetros!$B$18)/Parámetros!$D$18) -> 0 | L30: =IF(Parámetros!$D$19=0,0,COUNTIFS(Sesiones!$A$4:$A$903,$A30,Sesiones!$B$4:$B$903,Parámetros!$B$19)/Parámetros!$D$19) -> 0 | M30: =IF(Parámetros!$D$20=0,0,COUNTIFS(Sesiones!$A$4:$A$903,$A30,Sesiones!$B$4:$B$903,Parámetros!$B$20)/Parámetros!$D$20) -> 0 | N30: =IF(Parámetros!$D$21=0,0,COUNTIFS(Sesiones!$A$4:$A$903,$A30,Sesiones!$B$4:$B$903,Parámetros!$B$21)/Parámetros!$D$21) -> 0 | O30: =IF(Parámetros!$D$22=0,0,COUNTIFS(Sesiones!$A$4:$A$903,$A30,Sesiones!$B$4:$B$903,Parámetros!$B$22)/Parámetros!$D$22) -> 0 | P30: =IF(Parámetros!$D$23=0,0,COUNTIFS(Sesiones!$A$4:$A$903,$A30,Sesiones!$B$4:$B$903,Parámetros!$B$23)/Parámetros!$D$23) -> 0 | Q30: =IF(Parámetros!$D$24=0,0,COUNTIFS(Sesiones!$A$4:$A$903,$A30,Sesiones!$B$4:$B$903,Parámetros!$B$24)/Parámetros!$D$24) -> 0 | R30: =IF(Parámetros!$D$25=0,0,COUNTIFS(Sesiones!$A$4:$A$903,$A30,Sesiones!$B$4:$B$903,Parámetros!$B$25)/Parámetros!$D$25) -> 0 | S30: =IF(Parámetros!$D$26=0,0,COUNTIFS(Sesiones!$A$4:$A$903,$A30,Sesiones!$B$4:$B$903,Parámetros!$B$26)/Parámetros!$D$26) -> 0 | T30: =IF(Parámetros!$D$27=0,0,COUNTIFS(Sesiones!$A$4:$A$903,$A30,Sesiones!$B$4:$B$903,Parámetros!$B$27)/Parámetros!$D$27) -> 0
A31: =DATE(Parámetros!$C$6,Parámetros!$C$7,28) -> 46262 | B31: =SUMIFS('Caja Diaria'!$F$4:$F$403,'Caja Diaria'!$B$4:$B$403,"Ingreso",'Caja Diaria'!$A$4:$A$403,$A31) -> 0 | C31: =SUMIFS('Caja Diaria'!$F$4:$F$403,'Caja Diaria'!$B$4:$B$403,"Egreso",'Caja Diaria'!$A$4:$A$403,$A31) -> 0 | D31: =B31-C31 -> 0 | E31: =E30+D31 -> 5761500 | F31: =F30+SUMIFS('Caja Diaria'!$F$4:$F$403,'Caja Diaria'!$B$4:$B$403,"Ingreso",'Caja Diaria'!$E$4:$E$403,"Efectivo",'Caja Diaria'!$A$4:$A$403,$A31)-SUMIFS('Caja Diaria'!$F$4:$F$403,'Caja Diaria'!$B$4:$B$403,"Egreso",'Caja Diaria'!$E$4:$E$403,"Efectivo",'Caja Diaria'!$A$4:$A$403,$A31) -> 468000 | G31: =B31/Parámetros!$C$8 -> 0 | H31: =IF(Parámetros!$D$15=0,0,COUNTIFS(Sesiones!$A$4:$A$903,$A31,Sesiones!$B$4:$B$903,Parámetros!$B$15)/Parámetros!$D$15) -> 0 | I31: =IF(Parámetros!$D$16=0,0,COUNTIFS(Sesiones!$A$4:$A$903,$A31,Sesiones!$B$4:$B$903,Parámetros!$B$16)/Parámetros!$D$16) -> 0 | J31: =IF(Parámetros!$D$17=0,0,COUNTIFS(Sesiones!$A$4:$A$903,$A31,Sesiones!$B$4:$B$903,Parámetros!$B$17)/Parámetros!$D$17) -> 0 | K31: =IF(Parámetros!$D$18=0,0,COUNTIFS(Sesiones!$A$4:$A$903,$A31,Sesiones!$B$4:$B$903,Parámetros!$B$18)/Parámetros!$D$18) -> 0 | L31: =IF(Parámetros!$D$19=0,0,COUNTIFS(Sesiones!$A$4:$A$903,$A31,Sesiones!$B$4:$B$903,Parámetros!$B$19)/Parámetros!$D$19) -> 0 | M31: =IF(Parámetros!$D$20=0,0,COUNTIFS(Sesiones!$A$4:$A$903,$A31,Sesiones!$B$4:$B$903,Parámetros!$B$20)/Parámetros!$D$20) -> 0 | N31: =IF(Parámetros!$D$21=0,0,COUNTIFS(Sesiones!$A$4:$A$903,$A31,Sesiones!$B$4:$B$903,Parámetros!$B$21)/Parámetros!$D$21) -> 0 | O31: =IF(Parámetros!$D$22=0,0,COUNTIFS(Sesiones!$A$4:$A$903,$A31,Sesiones!$B$4:$B$903,Parámetros!$B$22)/Parámetros!$D$22) -> 0 | P31: =IF(Parámetros!$D$23=0,0,COUNTIFS(Sesiones!$A$4:$A$903,$A31,Sesiones!$B$4:$B$903,Parámetros!$B$23)/Parámetros!$D$23) -> 0 | Q31: =IF(Parámetros!$D$24=0,0,COUNTIFS(Sesiones!$A$4:$A$903,$A31,Sesiones!$B$4:$B$903,Parámetros!$B$24)/Parámetros!$D$24) -> 0 | R31: =IF(Parámetros!$D$25=0,0,COUNTIFS(Sesiones!$A$4:$A$903,$A31,Sesiones!$B$4:$B$903,Parámetros!$B$25)/Parámetros!$D$25) -> 0 | S31: =IF(Parámetros!$D$26=0,0,COUNTIFS(Sesiones!$A$4:$A$903,$A31,Sesiones!$B$4:$B$903,Parámetros!$B$26)/Parámetros!$D$26) -> 0 | T31: =IF(Parámetros!$D$27=0,0,COUNTIFS(Sesiones!$A$4:$A$903,$A31,Sesiones!$B$4:$B$903,Parámetros!$B$27)/Parámetros!$D$27) -> 0
A32: =DATE(Parámetros!$C$6,Parámetros!$C$7,29) -> 46263 | B32: =SUMIFS('Caja Diaria'!$F$4:$F$403,'Caja Diaria'!$B$4:$B$403,"Ingreso",'Caja Diaria'!$A$4:$A$403,$A32) -> 0 | C32: =SUMIFS('Caja Diaria'!$F$4:$F$403,'Caja Diaria'!$B$4:$B$403,"Egreso",'Caja Diaria'!$A$4:$A$403,$A32) -> 0 | D32: =B32-C32 -> 0 | E32: =E31+D32 -> 5761500 | F32: =F31+SUMIFS('Caja Diaria'!$F$4:$F$403,'Caja Diaria'!$B$4:$B$403,"Ingreso",'Caja Diaria'!$E$4:$E$403,"Efectivo",'Caja Diaria'!$A$4:$A$403,$A32)-SUMIFS('Caja Diaria'!$F$4:$F$403,'Caja Diaria'!$B$4:$B$403,"Egreso",'Caja Diaria'!$E$4:$E$403,"Efectivo",'Caja Diaria'!$A$4:$A$403,$A32) -> 468000 | G32: =B32/Parámetros!$C$8 -> 0 | H32: =IF(Parámetros!$D$15=0,0,COUNTIFS(Sesiones!$A$4:$A$903,$A32,Sesiones!$B$4:$B$903,Parámetros!$B$15)/Parámetros!$D$15) -> 0 | I32: =IF(Parámetros!$D$16=0,0,COUNTIFS(Sesiones!$A$4:$A$903,$A32,Sesiones!$B$4:$B$903,Parámetros!$B$16)/Parámetros!$D$16) -> 0 | J32: =IF(Parámetros!$D$17=0,0,COUNTIFS(Sesiones!$A$4:$A$903,$A32,Sesiones!$B$4:$B$903,Parámetros!$B$17)/Parámetros!$D$17) -> 0 | K32: =IF(Parámetros!$D$18=0,0,COUNTIFS(Sesiones!$A$4:$A$903,$A32,Sesiones!$B$4:$B$903,Parámetros!$B$18)/Parámetros!$D$18) -> 0 | L32: =IF(Parámetros!$D$19=0,0,COUNTIFS(Sesiones!$A$4:$A$903,$A32,Sesiones!$B$4:$B$903,Parámetros!$B$19)/Parámetros!$D$19) -> 0 | M32: =IF(Parámetros!$D$20=0,0,COUNTIFS(Sesiones!$A$4:$A$903,$A32,Sesiones!$B$4:$B$903,Parámetros!$B$20)/Parámetros!$D$20) -> 0 | N32: =IF(Parámetros!$D$21=0,0,COUNTIFS(Sesiones!$A$4:$A$903,$A32,Sesiones!$B$4:$B$903,Parámetros!$B$21)/Parámetros!$D$21) -> 0 | O32: =IF(Parámetros!$D$22=0,0,COUNTIFS(Sesiones!$A$4:$A$903,$A32,Sesiones!$B$4:$B$903,Parámetros!$B$22)/Parámetros!$D$22) -> 0 | P32: =IF(Parámetros!$D$23=0,0,COUNTIFS(Sesiones!$A$4:$A$903,$A32,Sesiones!$B$4:$B$903,Parámetros!$B$23)/Parámetros!$D$23) -> 0 | Q32: =IF(Parámetros!$D$24=0,0,COUNTIFS(Sesiones!$A$4:$A$903,$A32,Sesiones!$B$4:$B$903,Parámetros!$B$24)/Parámetros!$D$24) -> 0 | R32: =IF(Parámetros!$D$25=0,0,COUNTIFS(Sesiones!$A$4:$A$903,$A32,Sesiones!$B$4:$B$903,Parámetros!$B$25)/Parámetros!$D$25) -> 0 | S32: =IF(Parámetros!$D$26=0,0,COUNTIFS(Sesiones!$A$4:$A$903,$A32,Sesiones!$B$4:$B$903,Parámetros!$B$26)/Parámetros!$D$26) -> 0 | T32: =IF(Parámetros!$D$27=0,0,COUNTIFS(Sesiones!$A$4:$A$903,$A32,Sesiones!$B$4:$B$903,Parámetros!$B$27)/Parámetros!$D$27) -> 0
A33: =DATE(Parámetros!$C$6,Parámetros!$C$7,30) -> 46264 | B33: =SUMIFS('Caja Diaria'!$F$4:$F$403,'Caja Diaria'!$B$4:$B$403,"Ingreso",'Caja Diaria'!$A$4:$A$403,$A33) -> 0 | C33: =SUMIFS('Caja Diaria'!$F$4:$F$403,'Caja Diaria'!$B$4:$B$403,"Egreso",'Caja Diaria'!$A$4:$A$403,$A33) -> 0 | D33: =B33-C33 -> 0 | E33: =E32+D33 -> 5761500 | F33: =F32+SUMIFS('Caja Diaria'!$F$4:$F$403,'Caja Diaria'!$B$4:$B$403,"Ingreso",'Caja Diaria'!$E$4:$E$403,"Efectivo",'Caja Diaria'!$A$4:$A$403,$A33)-SUMIFS('Caja Diaria'!$F$4:$F$403,'Caja Diaria'!$B$4:$B$403,"Egreso",'Caja Diaria'!$E$4:$E$403,"Efectivo",'Caja Diaria'!$A$4:$A$403,$A33) -> 468000 | G33: =B33/Parámetros!$C$8 -> 0 | H33: =IF(Parámetros!$D$15=0,0,COUNTIFS(Sesiones!$A$4:$A$903,$A33,Sesiones!$B$4:$B$903,Parámetros!$B$15)/Parámetros!$D$15) -> 0 | I33: =IF(Parámetros!$D$16=0,0,COUNTIFS(Sesiones!$A$4:$A$903,$A33,Sesiones!$B$4:$B$903,Parámetros!$B$16)/Parámetros!$D$16) -> 0 | J33: =IF(Parámetros!$D$17=0,0,COUNTIFS(Sesiones!$A$4:$A$903,$A33,Sesiones!$B$4:$B$903,Parámetros!$B$17)/Parámetros!$D$17) -> 0 | K33: =IF(Parámetros!$D$18=0,0,COUNTIFS(Sesiones!$A$4:$A$903,$A33,Sesiones!$B$4:$B$903,Parámetros!$B$18)/Parámetros!$D$18) -> 0 | L33: =IF(Parámetros!$D$19=0,0,COUNTIFS(Sesiones!$A$4:$A$903,$A33,Sesiones!$B$4:$B$903,Parámetros!$B$19)/Parámetros!$D$19) -> 0 | M33: =IF(Parámetros!$D$20=0,0,COUNTIFS(Sesiones!$A$4:$A$903,$A33,Sesiones!$B$4:$B$903,Parámetros!$B$20)/Parámetros!$D$20) -> 0 | N33: =IF(Parámetros!$D$21=0,0,COUNTIFS(Sesiones!$A$4:$A$903,$A33,Sesiones!$B$4:$B$903,Parámetros!$B$21)/Parámetros!$D$21) -> 0 | O33: =IF(Parámetros!$D$22=0,0,COUNTIFS(Sesiones!$A$4:$A$903,$A33,Sesiones!$B$4:$B$903,Parámetros!$B$22)/Parámetros!$D$22) -> 0 | P33: =IF(Parámetros!$D$23=0,0,COUNTIFS(Sesiones!$A$4:$A$903,$A33,Sesiones!$B$4:$B$903,Parámetros!$B$23)/Parámetros!$D$23) -> 0 | Q33: =IF(Parámetros!$D$24=0,0,COUNTIFS(Sesiones!$A$4:$A$903,$A33,Sesiones!$B$4:$B$903,Parámetros!$B$24)/Parámetros!$D$24) -> 0 | R33: =IF(Parámetros!$D$25=0,0,COUNTIFS(Sesiones!$A$4:$A$903,$A33,Sesiones!$B$4:$B$903,Parámetros!$B$25)/Parámetros!$D$25) -> 0 | S33: =IF(Parámetros!$D$26=0,0,COUNTIFS(Sesiones!$A$4:$A$903,$A33,Sesiones!$B$4:$B$903,Parámetros!$B$26)/Parámetros!$D$26) -> 0 | T33: =IF(Parámetros!$D$27=0,0,COUNTIFS(Sesiones!$A$4:$A$903,$A33,Sesiones!$B$4:$B$903,Parámetros!$B$27)/Parámetros!$D$27) -> 0
A34: =DATE(Parámetros!$C$6,Parámetros!$C$7,31) -> 46265 | B34: =SUMIFS('Caja Diaria'!$F$4:$F$403,'Caja Diaria'!$B$4:$B$403,"Ingreso",'Caja Diaria'!$A$4:$A$403,$A34) -> 0 | C34: =SUMIFS('Caja Diaria'!$F$4:$F$403,'Caja Diaria'!$B$4:$B$403,"Egreso",'Caja Diaria'!$A$4:$A$403,$A34) -> 0 | D34: =B34-C34 -> 0 | E34: =E33+D34 -> 5761500 | F34: =F33+SUMIFS('Caja Diaria'!$F$4:$F$403,'Caja Diaria'!$B$4:$B$403,"Ingreso",'Caja Diaria'!$E$4:$E$403,"Efectivo",'Caja Diaria'!$A$4:$A$403,$A34)-SUMIFS('Caja Diaria'!$F$4:$F$403,'Caja Diaria'!$B$4:$B$403,"Egreso",'Caja Diaria'!$E$4:$E$403,"Efectivo",'Caja Diaria'!$A$4:$A$403,$A34) -> 468000 | G34: =B34/Parámetros!$C$8 -> 0 | H34: =IF(Parámetros!$D$15=0,0,COUNTIFS(Sesiones!$A$4:$A$903,$A34,Sesiones!$B$4:$B$903,Parámetros!$B$15)/Parámetros!$D$15) -> 0 | I34: =IF(Parámetros!$D$16=0,0,COUNTIFS(Sesiones!$A$4:$A$903,$A34,Sesiones!$B$4:$B$903,Parámetros!$B$16)/Parámetros!$D$16) -> 0 | J34: =IF(Parámetros!$D$17=0,0,COUNTIFS(Sesiones!$A$4:$A$903,$A34,Sesiones!$B$4:$B$903,Parámetros!$B$17)/Parámetros!$D$17) -> 0 | K34: =IF(Parámetros!$D$18=0,0,COUNTIFS(Sesiones!$A$4:$A$903,$A34,Sesiones!$B$4:$B$903,Parámetros!$B$18)/Parámetros!$D$18) -> 0 | L34: =IF(Parámetros!$D$19=0,0,COUNTIFS(Sesiones!$A$4:$A$903,$A34,Sesiones!$B$4:$B$903,Parámetros!$B$19)/Parámetros!$D$19) -> 0 | M34: =IF(Parámetros!$D$20=0,0,COUNTIFS(Sesiones!$A$4:$A$903,$A34,Sesiones!$B$4:$B$903,Parámetros!$B$20)/Parámetros!$D$20) -> 0 | N34: =IF(Parámetros!$D$21=0,0,COUNTIFS(Sesiones!$A$4:$A$903,$A34,Sesiones!$B$4:$B$903,Parámetros!$B$21)/Parámetros!$D$21) -> 0 | O34: =IF(Parámetros!$D$22=0,0,COUNTIFS(Sesiones!$A$4:$A$903,$A34,Sesiones!$B$4:$B$903,Parámetros!$B$22)/Parámetros!$D$22) -> 0 | P34: =IF(Parámetros!$D$23=0,0,COUNTIFS(Sesiones!$A$4:$A$903,$A34,Sesiones!$B$4:$B$903,Parámetros!$B$23)/Parámetros!$D$23) -> 0 | Q34: =IF(Parámetros!$D$24=0,0,COUNTIFS(Sesiones!$A$4:$A$903,$A34,Sesiones!$B$4:$B$903,Parámetros!$B$24)/Parámetros!$D$24) -> 0 | R34: =IF(Parámetros!$D$25=0,0,COUNTIFS(Sesiones!$A$4:$A$903,$A34,Sesiones!$B$4:$B$903,Parámetros!$B$25)/Parámetros!$D$25) -> 0 | S34: =IF(Parámetros!$D$26=0,0,COUNTIFS(Sesiones!$A$4:$A$903,$A34,Sesiones!$B$4:$B$903,Parámetros!$B$26)/Parámetros!$D$26) -> 0 | T34: =IF(Parámetros!$D$27=0,0,COUNTIFS(Sesiones!$A$4:$A$903,$A34,Sesiones!$B$4:$B$903,Parámetros!$B$27)/Parámetros!$D$27) -> 0
A35: TOTAL / Prom. | B35: =SUM(B4:B34) -> 5836500 | C35: =SUM(C4:C34) -> 75000 | D35: =SUM(D4:D34) -> 5761500 | E35: =E34 -> 5761500 | F35: =F34 -> 468000 | G35: =SUM(G4:G34) -> 3891 | H35: =AVERAGE(H4:H34) -> 0.0053763441 | I35: =AVERAGE(I4:I34) -> 0 | J35: =AVERAGE(J4:J34) -> 0.002688172 | K35: =AVERAGE(K4:K34) -> 0.001344086 | L35: =AVERAGE(L4:L34) -> 0.001344086 | M35: =AVERAGE(M4:M34) -> 0.002688172 | N35: =AVERAGE(N4:N34) -> 0 | O35: =AVERAGE(O4:O34) -> 0.001344086 | ... T35: =AVERAGE(T4:T34) -> 0.002688172

Sheet Membresías & Combos
B1: Membresías activas, MRR y Combos
B2: Cargá socios activos por plan (azul). MRR = plata fija mensual de membresías. Combos vendidos: cargá la cantidad.
B4: Membresías
B5: Plan | C5: Socios activos | D5: Precio USD/mes | E5: MRR USD
B6: FOCUS Standard | C6: 5 | D6: 718 | E6: =C6*D6 -> 3590
B7: FOCUS Intensivo | C7: 0 | D7: 1008 | E7: =C7*D7 -> 0
B8: PRIME Std Individual | C8: 3 | D8: 1752 | E8: =C8*D8 -> 5256
B9: PRIME Int Individual | C9: 0 | D9: 2453 | E9: =C9*D9 -> 0
B10: PRIME Std Pareja | C10: 0 | D10: 1920 | E10: =C10*D10 -> 0
B11: PRIME Int Pareja | C11: 0 | D11: 2688 | E11: =C11*D11 -> 0
B12: HEALTHSPAN Std Individual | C12: 2 | D12: 2184 | E12: =C12*D12 -> 4368
B13: HEALTHSPAN Int Individual | C13: 0 | D13: 3058 | E13: =C13*D13 -> 0
B14: HEALTHSPAN Std Pareja | C14: 0 | D14: 2784 | E14: =C14*D14 -> 0
B15: HEALTHSPAN Int Pareja | C15: 0 | D15: 3898 | E15: =C15*D15 -> 0
B16: TOTAL / MRR | C16: =SUM(C6:C15) -> 10 | E16: =SUM(E6:E15) -> 13214
B17: MRR en ARS | E17: =E16*Parámetros!$C$8 -> 19821000
B19: Combos vendidos en el mes
B20: Combo | C20: Vendidos | D20: Precio USD | E20: Ingreso USD
B21: BIO ENERGY | C21: 8 | D21: 112 | E21: =C21*D21 -> 896
B22: BIO COMPRESS | C22: 0 | D22: 88 | E22: =C22*D22 -> 0
B23: BIO CRYO | C23: 0 | D23: 120 | E23: =C23*D23 -> 0
B24: BIO RECOVERY Ind | C24: 5 | D24: 292 | E24: =C24*D24 -> 1460
B25: BIO LONGEVITY Ind | C25: 3 | D25: 364 | E25: =C25*D25 -> 1092
B26: TOTAL combos | C26: =SUM(C21:C25) -> 16 | E26: =SUM(E21:E25) -> 3448
B28: Nota: 'Combos vendidos' se carga a mano por ahora; el sistema definitivo lo cuenta solo.

Sheet Gastos del Mes
B1: Gastos Operativos del Mes
B2: Gastos del mes en ARS (azul). No incluye la caja chica diaria ni el Bar.
B3: Concepto | C3: Monto ARS | D3: Monto USD | E3: Nota
B4: Sueldos + cargas sociales (27%) | C4: =Empleados!$E$19 -> 0 | D4: =IF(C4=0,0,C4/Parámetros!$C$8) -> 0 | E4: ← desde hoja Empleados
B5: Honorario Dr. Conrado (fijo) | C5: 0 | D5: =IF(C5=0,0,C5/Parámetros!$C$8) -> 0
B6: Honorarios médicos prescriptores (15% IV+TB) | C6: =$F$6*SUMIFS('Caja Diaria'!$F$4:$F$403,'Caja Diaria'!$B$4:$B$403,"Ingreso",'Caja Diaria'!$C$4:$C$403,"IV + Terapias Biológicas") -> 56250 | D6: =IF(C6=0,0,C6/Parámetros!$C$8) -> 37.5 | E6: Auto desde IV+TB en el sistema | F6: 0.15 | G6: % s/ IV+TB cobrado (editable) — VALIDAR base
B7: Costo insumos Regenerar (IV+TB) | C7: =$F$7*SUMIFS('Caja Diaria'!$F$4:$F$403,'Caja Diaria'!$B$4:$B$403,"Ingreso",'Caja Diaria'!$C$4:$C$403,"IV + Terapias Biológicas") -> 112500 | D7: =IF(C7=0,0,C7/Parámetros!$C$8) -> 75 | E7: Variable s/ sesiones TB | F7: 0.3 | G7: % costo insumos s/ IV+TB (editable) — VALIDAR
B8: Alquiler local | C8: 7500000 | D8: =IF(C8=0,0,C8/Parámetros!$C$8) -> 5000 | E8: Desde Año 2
B9: Estacionamiento | C9: 1200000 | D9: =IF(C9=0,0,C9/Parámetros!$C$8) -> 800
B10: Electricidad / Gas | C10: 2000000 | D10: =IF(C10=0,0,C10/Parámetros!$C$8) -> 1333.3333
B11: Internet / Software | C11: 30000 | D11: =IF(C11=0,0,C11/Parámetros!$C$8) -> 20
B12: Seguros | C12: 300000 | D12: =IF(C12=0,0,C12/Parámetros!$C$8) -> 200
B13: Mantenimiento | C13: 0 | D13: =IF(C13=0,0,C13/Parámetros!$C$8) -> 0
B14: Marketing | C14: 700000 | D14: =IF(C14=0,0,C14/Parámetros!$C$8) -> 466.66667
B15: Insumos médicos (stock) | C15: 0 | D15: =IF(C15=0,0,C15/Parámetros!$C$8) -> 0
B16: Contaduría / Legal | C16: 500000 | D16: =IF(C16=0,0,C16/Parámetros!$C$8) -> 333.33333
B17: Comisiones MercadoPago / POS | C17: 0 | D17: =IF(C17=0,0,C17/Parámetros!$C$8) -> 0 | E17: ~1,5% ingresos digitales
B18: IIBB (3%) | C18: 0 | D18: =IF(C18=0,0,C18/Parámetros!$C$8) -> 0 | E18: Sobre ingresos netos
B19: Lavandería | C19: 0 | D19: =IF(C19=0,0,C19/Parámetros!$C$8) -> 0
B20: Gastos varios | C20: ='Gastos Varios'!$D$45 -> 0 | D20: =IF(C20=0,0,C20/Parámetros!$C$8) -> 0 | E20: ← desde hoja Gastos Varios
B21: TOTAL GASTOS OPERATIVOS | C21: =SUM(C4:C20) -> 12398750 | D21: =SUM(D4:D20) -> 8265.8333

Sheet Formas de Pago
B1: Formas de Pago de los clientes
B2: Se llena solo desde Caja Diaria. Muestra cuánto y qué % cobrás por cada medio.
B4: Resumen del mes
B5: Método | C5: Monto ARS | D5: Monto USD | E5: % del total
B6: Efectivo | C6: =SUMIFS('Caja Diaria'!$F$4:$F$403,'Caja Diaria'!$B$4:$B$403,"Ingreso",'Caja Diaria'!$E$4:$E$403,"Efectivo") -> 543000 | D6: =C6/Parámetros!$C$8 -> 362 | E6: =IF($C$11=0,0,C6/$C$11) -> 0.093035209
B7: Tarjeta débito | C7: =SUMIFS('Caja Diaria'!$F$4:$F$403,'Caja Diaria'!$B$4:$B$403,"Ingreso",'Caja Diaria'!$E$4:$E$403,"Tarjeta débito") -> 0 | D7: =C7/Parámetros!$C$8 -> 0 | E7: =IF($C$11=0,0,C7/$C$11) -> 0
B8: Tarjeta crédito | C8: =SUMIFS('Caja Diaria'!$F$4:$F$403,'Caja Diaria'!$B$4:$B$403,"Ingreso",'Caja Diaria'!$E$4:$E$403,"Tarjeta crédito") -> 2665500 | D8: =C8/Parámetros!$C$8 -> 1777 | E8: =IF($C$11=0,0,C8/$C$11) -> 0.45669494
B9: Transferencia | C9: =SUMIFS('Caja Diaria'!$F$4:$F$403,'Caja Diaria'!$B$4:$B$403,"Ingreso",'Caja Diaria'!$E$4:$E$403,"Transferencia") -> 0 | D9: =C9/Parámetros!$C$8 -> 0 | E9: =IF($C$11=0,0,C9/$C$11) -> 0
B10: MercadoPago | C10: =SUMIFS('Caja Diaria'!$F$4:$F$403,'Caja Diaria'!$B$4:$B$403,"Ingreso",'Caja Diaria'!$E$4:$E$403,"MercadoPago") -> 2628000 | D10: =C10/Parámetros!$C$8 -> 1752 | E10: =IF($C$11=0,0,C10/$C$11) -> 0.45026985
B11: TOTAL | C11: =SUM(C6:C10) -> 5836500 | D11: =SUM(D6:D10) -> 3891 | E11: =SUM(E6:E10) -> 1
B14: Detalle diario (montos por método, ARS)
B15: Día | C15: Efectivo | D15: Tarjeta débito | E15: Tarjeta crédito | F15: Transferencia | G15: MercadoPago | H15: Total día | I15: % Efectivo
B16: ='Resumen Diario'!$A$4 -> 46235 | C16: =SUMIFS('Caja Diaria'!$F$4:$F$403,'Caja Diaria'!$B$4:$B$403,"Ingreso",'Caja Diaria'!$E$4:$E$403,"Efectivo",'Caja Diaria'!$A$4:$A$403,'Resumen Diario'!$A$4) -> 0 | D16: =SUMIFS('Caja Diaria'!$F$4:$F$403,'Caja Diaria'!$B$4:$B$403,"Ingreso",'Caja Diaria'!$E$4:$E$403,"Tarjeta débito",'Caja Diaria'!$A$4:$A$403,'Resumen Diario'!$A$4) -> 0 | E16: =SUMIFS('Caja Diaria'!$F$4:$F$403,'Caja Diaria'!$B$4:$B$403,"Ingreso",'Caja Diaria'!$E$4:$E$403,"Tarjeta crédito",'Caja Diaria'!$A$4:$A$403,'Resumen Diario'!$A$4) -> 0 | F16: =SUMIFS('Caja Diaria'!$F$4:$F$403,'Caja Diaria'!$B$4:$B$403,"Ingreso",'Caja Diaria'!$E$4:$E$403,"Transferencia",'Caja Diaria'!$A$4:$A$403,'Resumen Diario'!$A$4) -> 0 | G16: =SUMIFS('Caja Diaria'!$F$4:$F$403,'Caja Diaria'!$B$4:$B$403,"Ingreso",'Caja Diaria'!$E$4:$E$403,"MercadoPago",'Caja Diaria'!$A$4:$A$403,'Resumen Diario'!$A$4) -> 0 | H16: =SUM(C16:G16) -> 0 | I16: =IF(H16=0,0,C16/H16) -> 0
B17: ='Resumen Diario'!$A$5 -> 46236 | C17: =SUMIFS('Caja Diaria'!$F$4:$F$403,'Caja Diaria'!$B$4:$B$403,"Ingreso",'Caja Diaria'!$E$4:$E$403,"Efectivo",'Caja Diaria'!$A$4:$A$403,'Resumen Diario'!$A$5) -> 0 | D17: =SUMIFS('Caja Diaria'!$F$4:$F$403,'Caja Diaria'!$B$4:$B$403,"Ingreso",'Caja Diaria'!$E$4:$E$403,"Tarjeta débito",'Caja Diaria'!$A$4:$A$403,'Resumen Diario'!$A$5) -> 0 | E17: =SUMIFS('Caja Diaria'!$F$4:$F$403,'Caja Diaria'!$B$4:$B$403,"Ingreso",'Caja Diaria'!$E$4:$E$403,"Tarjeta crédito",'Caja Diaria'!$A$4:$A$403,'Resumen Diario'!$A$5) -> 0 | F17: =SUMIFS('Caja Diaria'!$F$4:$F$403,'Caja Diaria'!$B$4:$B$403,"Ingreso",'Caja Diaria'!$E$4:$E$403,"Transferencia",'Caja Diaria'!$A$4:$A$403,'Resumen Diario'!$A$5) -> 0 | G17: =SUMIFS('Caja Diaria'!$F$4:$F$403,'Caja Diaria'!$B$4:$B$403,"Ingreso",'Caja Diaria'!$E$4:$E$403,"MercadoPago",'Caja Diaria'!$A$4:$A$403,'Resumen Diario'!$A$5) -> 0 | H17: =SUM(C17:G17) -> 0 | I17: =IF(H17=0,0,C17/H17) -> 0
B18: ='Resumen Diario'!$A$6 -> 46237 | C18: =SUMIFS('Caja Diaria'!$F$4:$F$403,'Caja Diaria'!$B$4:$B$403,"Ingreso",'Caja Diaria'!$E$4:$E$403,"Efectivo",'Caja Diaria'!$A$4:$A$403,'Resumen Diario'!$A$6) -> 375000 | D18: =SUMIFS('Caja Diaria'!$F$4:$F$403,'Caja Diaria'!$B$4:$B$403,"Ingreso",'Caja Diaria'!$E$4:$E$403,"Tarjeta débito",'Caja Diaria'!$A$4:$A$403,'Resumen Diario'!$A$6) -> 0 | E18: =SUMIFS('Caja Diaria'!$F$4:$F$403,'Caja Diaria'!$B$4:$B$403,"Ingreso",'Caja Diaria'!$E$4:$E$403,"Tarjeta crédito",'Caja Diaria'!$A$4:$A$403,'Resumen Diario'!$A$6) -> 438000 | F18: =SUMIFS('Caja Diaria'!$F$4:$F$403,'Caja Diaria'!$B$4:$B$403,"Ingreso",'Caja Diaria'!$E$4:$E$403,"Transferencia",'Caja Diaria'!$A$4:$A$403,'Resumen Diario'!$A$6) -> 0 | G18: =SUMIFS('Caja Diaria'!$F$4:$F$403,'Caja Diaria'!$B$4:$B$403,"Ingreso",'Caja Diaria'!$E$4:$E$403,"MercadoPago",'Caja Diaria'!$A$4:$A$403,'Resumen Diario'!$A$6) -> 2628000 | H18: =SUM(C18:G18) -> 3441000 | I18: =IF(H18=0,0,C18/H18) -> 0.10897995
B19: ='Resumen Diario'!$A$7 -> 46238 | C19: =SUMIFS('Caja Diaria'!$F$4:$F$403,'Caja Diaria'!$B$4:$B$403,"Ingreso",'Caja Diaria'!$E$4:$E$403,"Efectivo",'Caja Diaria'!$A$4:$A$403,'Resumen Diario'!$A$7) -> 168000 | D19: =SUMIFS('Caja Diaria'!$F$4:$F$403,'Caja Diaria'!$B$4:$B$403,"Ingreso",'Caja Diaria'!$E$4:$E$403,"Tarjeta débito",'Caja Diaria'!$A$4:$A$403,'Resumen Diario'!$A$7) -> 0 | E19: =SUMIFS('Caja Diaria'!$F$4:$F$403,'Caja Diaria'!$B$4:$B$403,"Ingreso",'Caja Diaria'!$E$4:$E$403,"Tarjeta crédito",'Caja Diaria'!$A$4:$A$403,'Resumen Diario'!$A$7) -> 2227500 | F19: =SUMIFS('Caja Diaria'!$F$4:$F$403,'Caja Diaria'!$B$4:$B$403,"Ingreso",'Caja Diaria'!$E$4:$E$403,"Transferencia",'Caja Diaria'!$A$4:$A$403,'Resumen Diario'!$A$7) -> 0 | G19: =SUMIFS('Caja Diaria'!$F$4:$F$403,'Caja Diaria'!$B$4:$B$403,"Ingreso",'Caja Diaria'!$E$4:$E$403,"MercadoPago",'Caja Diaria'!$A$4:$A$403,'Resumen Diario'!$A$7) -> 0 | H19: =SUM(C19:G19) -> 2395500 | I19: =IF(H19=0,0,C19/H19) -> 0.070131497
B20: ='Resumen Diario'!$A$8 -> 46239 | C20: =SUMIFS('Caja Diaria'!$F$4:$F$403,'Caja Diaria'!$B$4:$B$403,"Ingreso",'Caja Diaria'!$E$4:$E$403,"Efectivo",'Caja Diaria'!$A$4:$A$403,'Resumen Diario'!$A$8) -> 0 | D20: =SUMIFS('Caja Diaria'!$F$4:$F$403,'Caja Diaria'!$B$4:$B$403,"Ingreso",'Caja Diaria'!$E$4:$E$403,"Tarjeta débito",'Caja Diaria'!$A$4:$A$403,'Resumen Diario'!$A$8) -> 0 | E20: =SUMIFS('Caja Diaria'!$F$4:$F$403,'Caja Diaria'!$B$4:$B$403,"Ingreso",'Caja Diaria'!$E$4:$E$403,"Tarjeta crédito",'Caja Diaria'!$A$4:$A$403,'Resumen Diario'!$A$8) -> 0 | F20: =SUMIFS('Caja Diaria'!$F$4:$F$403,'Caja Diaria'!$B$4:$B$403,"Ingreso",'Caja Diaria'!$E$4:$E$403,"Transferencia",'Caja Diaria'!$A$4:$A$403,'Resumen Diario'!$A$8) -> 0 | G20: =SUMIFS('Caja Diaria'!$F$4:$F$403,'Caja Diaria'!$B$4:$B$403,"Ingreso",'Caja Diaria'!$E$4:$E$403,"MercadoPago",'Caja Diaria'!$A$4:$A$403,'Resumen Diario'!$A$8) -> 0 | H20: =SUM(C20:G20) -> 0 | I20: =IF(H20=0,0,C20/H20) -> 0
B21: ='Resumen Diario'!$A$9 -> 46240 | C21: =SUMIFS('Caja Diaria'!$F$4:$F$403,'Caja Diaria'!$B$4:$B$403,"Ingreso",'Caja Diaria'!$E$4:$E$403,"Efectivo",'Caja Diaria'!$A$4:$A$403,'Resumen Diario'!$A$9) -> 0 | D21: =SUMIFS('Caja Diaria'!$F$4:$F$403,'Caja Diaria'!$B$4:$B$403,"Ingreso",'Caja Diaria'!$E$4:$E$403,"Tarjeta débito",'Caja Diaria'!$A$4:$A$403,'Resumen Diario'!$A$9) -> 0 | E21: =SUMIFS('Caja Diaria'!$F$4:$F$403,'Caja Diaria'!$B$4:$B$403,"Ingreso",'Caja Diaria'!$E$4:$E$403,"Tarjeta crédito",'Caja Diaria'!$A$4:$A$403,'Resumen Diario'!$A$9) -> 0 | F21: =SUMIFS('Caja Diaria'!$F$4:$F$403,'Caja Diaria'!$B$4:$B$403,"Ingreso",'Caja Diaria'!$E$4:$E$403,"Transferencia",'Caja Diaria'!$A$4:$A$403,'Resumen Diario'!$A$9) -> 0 | G21: =SUMIFS('Caja Diaria'!$F$4:$F$403,'Caja Diaria'!$B$4:$B$403,"Ingreso",'Caja Diaria'!$E$4:$E$403,"MercadoPago",'Caja Diaria'!$A$4:$A$403,'Resumen Diario'!$A$9) -> 0 | H21: =SUM(C21:G21) -> 0 | I21: =IF(H21=0,0,C21/H21) -> 0
B22: ='Resumen Diario'!$A$10 -> 46241 | C22: =SUMIFS('Caja Diaria'!$F$4:$F$403,'Caja Diaria'!$B$4:$B$403,"Ingreso",'Caja Diaria'!$E$4:$E$403,"Efectivo",'Caja Diaria'!$A$4:$A$403,'Resumen Diario'!$A$10) -> 0 | D22: =SUMIFS('Caja Diaria'!$F$4:$F$403,'Caja Diaria'!$B$4:$B$403,"Ingreso",'Caja Diaria'!$E$4:$E$403,"Tarjeta débito",'Caja Diaria'!$A$4:$A$403,'Resumen Diario'!$A$10) -> 0 | E22: =SUMIFS('Caja Diaria'!$F$4:$F$403,'Caja Diaria'!$B$4:$B$403,"Ingreso",'Caja Diaria'!$E$4:$E$403,"Tarjeta crédito",'Caja Diaria'!$A$4:$A$403,'Resumen Diario'!$A$10) -> 0 | F22: =SUMIFS('Caja Diaria'!$F$4:$F$403,'Caja Diaria'!$B$4:$B$403,"Ingreso",'Caja Diaria'!$E$4:$E$403,"Transferencia",'Caja Diaria'!$A$4:$A$403,'Resumen Diario'!$A$10) -> 0 | G22: =SUMIFS('Caja Diaria'!$F$4:$F$403,'Caja Diaria'!$B$4:$B$403,"Ingreso",'Caja Diaria'!$E$4:$E$403,"MercadoPago",'Caja Diaria'!$A$4:$A$403,'Resumen Diario'!$A$10) -> 0 | H22: =SUM(C22:G22) -> 0 | I22: =IF(H22=0,0,C22/H22) -> 0
B23: ='Resumen Diario'!$A$11 -> 46242 | C23: =SUMIFS('Caja Diaria'!$F$4:$F$403,'Caja Diaria'!$B$4:$B$403,"Ingreso",'Caja Diaria'!$E$4:$E$403,"Efectivo",'Caja Diaria'!$A$4:$A$403,'Resumen Diario'!$A$11) -> 0 | D23: =SUMIFS('Caja Diaria'!$F$4:$F$403,'Caja Diaria'!$B$4:$B$403,"Ingreso",'Caja Diaria'!$E$4:$E$403,"Tarjeta débito",'Caja Diaria'!$A$4:$A$403,'Resumen Diario'!$A$11) -> 0 | E23: =SUMIFS('Caja Diaria'!$F$4:$F$403,'Caja Diaria'!$B$4:$B$403,"Ingreso",'Caja Diaria'!$E$4:$E$403,"Tarjeta crédito",'Caja Diaria'!$A$4:$A$403,'Resumen Diario'!$A$11) -> 0 | F23: =SUMIFS('Caja Diaria'!$F$4:$F$403,'Caja Diaria'!$B$4:$B$403,"Ingreso",'Caja Diaria'!$E$4:$E$403,"Transferencia",'Caja Diaria'!$A$4:$A$403,'Resumen Diario'!$A$11) -> 0 | G23: =SUMIFS('Caja Diaria'!$F$4:$F$403,'Caja Diaria'!$B$4:$B$403,"Ingreso",'Caja Diaria'!$E$4:$E$403,"MercadoPago",'Caja Diaria'!$A$4:$A$403,'Resumen Diario'!$A$11) -> 0 | H23: =SUM(C23:G23) -> 0 | I23: =IF(H23=0,0,C23/H23) -> 0
B24: ='Resumen Diario'!$A$12 -> 46243 | C24: =SUMIFS('Caja Diaria'!$F$4:$F$403,'Caja Diaria'!$B$4:$B$403,"Ingreso",'Caja Diaria'!$E$4:$E$403,"Efectivo",'Caja Diaria'!$A$4:$A$403,'Resumen Diario'!$A$12) -> 0 | D24: =SUMIFS('Caja Diaria'!$F$4:$F$403,'Caja Diaria'!$B$4:$B$403,"Ingreso",'Caja Diaria'!$E$4:$E$403,"Tarjeta débito",'Caja Diaria'!$A$4:$A$403,'Resumen Diario'!$A$12) -> 0 | E24: =SUMIFS('Caja Diaria'!$F$4:$F$403,'Caja Diaria'!$B$4:$B$403,"Ingreso",'Caja Diaria'!$E$4:$E$403,"Tarjeta crédito",'Caja Diaria'!$A$4:$A$403,'Resumen Diario'!$A$12) -> 0 | F24: =SUMIFS('Caja Diaria'!$F$4:$F$403,'Caja Diaria'!$B$4:$B$403,"Ingreso",'Caja Diaria'!$E$4:$E$403,"Transferencia",'Caja Diaria'!$A$4:$A$403,'Resumen Diario'!$A$12) -> 0 | G24: =SUMIFS('Caja Diaria'!$F$4:$F$403,'Caja Diaria'!$B$4:$B$403,"Ingreso",'Caja Diaria'!$E$4:$E$403,"MercadoPago",'Caja Diaria'!$A$4:$A$403,'Resumen Diario'!$A$12) -> 0 | H24: =SUM(C24:G24) -> 0 | I24: =IF(H24=0,0,C24/H24) -> 0
B25: ='Resumen Diario'!$A$13 -> 46244 | C25: =SUMIFS('Caja Diaria'!$F$4:$F$403,'Caja Diaria'!$B$4:$B$403,"Ingreso",'Caja Diaria'!$E$4:$E$403,"Efectivo",'Caja Diaria'!$A$4:$A$403,'Resumen Diario'!$A$13) -> 0 | D25: =SUMIFS('Caja Diaria'!$F$4:$F$403,'Caja Diaria'!$B$4:$B$403,"Ingreso",'Caja Diaria'!$E$4:$E$403,"Tarjeta débito",'Caja Diaria'!$A$4:$A$403,'Resumen Diario'!$A$13) -> 0 | E25: =SUMIFS('Caja Diaria'!$F$4:$F$403,'Caja Diaria'!$B$4:$B$403,"Ingreso",'Caja Diaria'!$E$4:$E$403,"Tarjeta crédito",'Caja Diaria'!$A$4:$A$403,'Resumen Diario'!$A$13) -> 0 | F25: =SUMIFS('Caja Diaria'!$F$4:$F$403,'Caja Diaria'!$B$4:$B$403,"Ingreso",'Caja Diaria'!$E$4:$E$403,"Transferencia",'Caja Diaria'!$A$4:$A$403,'Resumen Diario'!$A$13) -> 0 | G25: =SUMIFS('Caja Diaria'!$F$4:$F$403,'Caja Diaria'!$B$4:$B$403,"Ingreso",'Caja Diaria'!$E$4:$E$403,"MercadoPago",'Caja Diaria'!$A$4:$A$403,'Resumen Diario'!$A$13) -> 0 | H25: =SUM(C25:G25) -> 0 | I25: =IF(H25=0,0,C25/H25) -> 0
B26: ='Resumen Diario'!$A$14 -> 46245 | C26: =SUMIFS('Caja Diaria'!$F$4:$F$403,'Caja Diaria'!$B$4:$B$403,"Ingreso",'Caja Diaria'!$E$4:$E$403,"Efectivo",'Caja Diaria'!$A$4:$A$403,'Resumen Diario'!$A$14) -> 0 | D26: =SUMIFS('Caja Diaria'!$F$4:$F$403,'Caja Diaria'!$B$4:$B$403,"Ingreso",'Caja Diaria'!$E$4:$E$403,"Tarjeta débito",'Caja Diaria'!$A$4:$A$403,'Resumen Diario'!$A$14) -> 0 | E26: =SUMIFS('Caja Diaria'!$F$4:$F$403,'Caja Diaria'!$B$4:$B$403,"Ingreso",'Caja Diaria'!$E$4:$E$403,"Tarjeta crédito",'Caja Diaria'!$A$4:$A$403,'Resumen Diario'!$A$14) -> 0 | F26: =SUMIFS('Caja Diaria'!$F$4:$F$403,'Caja Diaria'!$B$4:$B$403,"Ingreso",'Caja Diaria'!$E$4:$E$403,"Transferencia",'Caja Diaria'!$A$4:$A$403,'Resumen Diario'!$A$14) -> 0 | G26: =SUMIFS('Caja Diaria'!$F$4:$F$403,'Caja Diaria'!$B$4:$B$403,"Ingreso",'Caja Diaria'!$E$4:$E$403,"MercadoPago",'Caja Diaria'!$A$4:$A$403,'Resumen Diario'!$A$14) -> 0 | H26: =SUM(C26:G26) -> 0 | I26: =IF(H26=0,0,C26/H26) -> 0
B27: ='Resumen Diario'!$A$15 -> 46246 | C27: =SUMIFS('Caja Diaria'!$F$4:$F$403,'Caja Diaria'!$B$4:$B$403,"Ingreso",'Caja Diaria'!$E$4:$E$403,"Efectivo",'Caja Diaria'!$A$4:$A$403,'Resumen Diario'!$A$15) -> 0 | D27: =SUMIFS('Caja Diaria'!$F$4:$F$403,'Caja Diaria'!$B$4:$B$403,"Ingreso",'Caja Diaria'!$E$4:$E$403,"Tarjeta débito",'Caja Diaria'!$A$4:$A$403,'Resumen Diario'!$A$15) -> 0 | E27: =SUMIFS('Caja Diaria'!$F$4:$F$403,'Caja Diaria'!$B$4:$B$403,"Ingreso",'Caja Diaria'!$E$4:$E$403,"Tarjeta crédito",'Caja Diaria'!$A$4:$A$403,'Resumen Diario'!$A$15) -> 0 | F27: =SUMIFS('Caja Diaria'!$F$4:$F$403,'Caja Diaria'!$B$4:$B$403,"Ingreso",'Caja Diaria'!$E$4:$E$403,"Transferencia",'Caja Diaria'!$A$4:$A$403,'Resumen Diario'!$A$15) -> 0 | G27: =SUMIFS('Caja Diaria'!$F$4:$F$403,'Caja Diaria'!$B$4:$B$403,"Ingreso",'Caja Diaria'!$E$4:$E$403,"MercadoPago",'Caja Diaria'!$A$4:$A$403,'Resumen Diario'!$A$15) -> 0 | H27: =SUM(C27:G27) -> 0 | I27: =IF(H27=0,0,C27/H27) -> 0
B28: ='Resumen Diario'!$A$16 -> 46247 | C28: =SUMIFS('Caja Diaria'!$F$4:$F$403,'Caja Diaria'!$B$4:$B$403,"Ingreso",'Caja Diaria'!$E$4:$E$403,"Efectivo",'Caja Diaria'!$A$4:$A$403,'Resumen Diario'!$A$16) -> 0 | D28: =SUMIFS('Caja Diaria'!$F$4:$F$403,'Caja Diaria'!$B$4:$B$403,"Ingreso",'Caja Diaria'!$E$4:$E$403,"Tarjeta débito",'Caja Diaria'!$A$4:$A$403,'Resumen Diario'!$A$16) -> 0 | E28: =SUMIFS('Caja Diaria'!$F$4:$F$403,'Caja Diaria'!$B$4:$B$403,"Ingreso",'Caja Diaria'!$E$4:$E$403,"Tarjeta crédito",'Caja Diaria'!$A$4:$A$403,'Resumen Diario'!$A$16) -> 0 | F28: =SUMIFS('Caja Diaria'!$F$4:$F$403,'Caja Diaria'!$B$4:$B$403,"Ingreso",'Caja Diaria'!$E$4:$E$403,"Transferencia",'Caja Diaria'!$A$4:$A$403,'Resumen Diario'!$A$16) -> 0 | G28: =SUMIFS('Caja Diaria'!$F$4:$F$403,'Caja Diaria'!$B$4:$B$403,"Ingreso",'Caja Diaria'!$E$4:$E$403,"MercadoPago",'Caja Diaria'!$A$4:$A$403,'Resumen Diario'!$A$16) -> 0 | H28: =SUM(C28:G28) -> 0 | I28: =IF(H28=0,0,C28/H28) -> 0
B29: ='Resumen Diario'!$A$17 -> 46248 | C29: =SUMIFS('Caja Diaria'!$F$4:$F$403,'Caja Diaria'!$B$4:$B$403,"Ingreso",'Caja Diaria'!$E$4:$E$403,"Efectivo",'Caja Diaria'!$A$4:$A$403,'Resumen Diario'!$A$17) -> 0 | D29: =SUMIFS('Caja Diaria'!$F$4:$F$403,'Caja Diaria'!$B$4:$B$403,"Ingreso",'Caja Diaria'!$E$4:$E$403,"Tarjeta débito",'Caja Diaria'!$A$4:$A$403,'Resumen Diario'!$A$17) -> 0 | E29: =SUMIFS('Caja Diaria'!$F$4:$F$403,'Caja Diaria'!$B$4:$B$403,"Ingreso",'Caja Diaria'!$E$4:$E$403,"Tarjeta crédito",'Caja Diaria'!$A$4:$A$403,'Resumen Diario'!$A$17) -> 0 | F29: =SUMIFS('Caja Diaria'!$F$4:$F$403,'Caja Diaria'!$B$4:$B$403,"Ingreso",'Caja Diaria'!$E$4:$E$403,"Transferencia",'Caja Diaria'!$A$4:$A$403,'Resumen Diario'!$A$17) -> 0 | G29: =SUMIFS('Caja Diaria'!$F$4:$F$403,'Caja Diaria'!$B$4:$B$403,"Ingreso",'Caja Diaria'!$E$4:$E$403,"MercadoPago",'Caja Diaria'!$A$4:$A$403,'Resumen Diario'!$A$17) -> 0 | H29: =SUM(C29:G29) -> 0 | I29: =IF(H29=0,0,C29/H29) -> 0
B30: ='Resumen Diario'!$A$18 -> 46249 | C30: =SUMIFS('Caja Diaria'!$F$4:$F$403,'Caja Diaria'!$B$4:$B$403,"Ingreso",'Caja Diaria'!$E$4:$E$403,"Efectivo",'Caja Diaria'!$A$4:$A$403,'Resumen Diario'!$A$18) -> 0 | D30: =SUMIFS('Caja Diaria'!$F$4:$F$403,'Caja Diaria'!$B$4:$B$403,"Ingreso",'Caja Diaria'!$E$4:$E$403,"Tarjeta débito",'Caja Diaria'!$A$4:$A$403,'Resumen Diario'!$A$18) -> 0 | E30: =SUMIFS('Caja Diaria'!$F$4:$F$403,'Caja Diaria'!$B$4:$B$403,"Ingreso",'Caja Diaria'!$E$4:$E$403,"Tarjeta crédito",'Caja Diaria'!$A$4:$A$403,'Resumen Diario'!$A$18) -> 0 | F30: =SUMIFS('Caja Diaria'!$F$4:$F$403,'Caja Diaria'!$B$4:$B$403,"Ingreso",'Caja Diaria'!$E$4:$E$403,"Transferencia",'Caja Diaria'!$A$4:$A$403,'Resumen Diario'!$A$18) -> 0 | G30: =SUMIFS('Caja Diaria'!$F$4:$F$403,'Caja Diaria'!$B$4:$B$403,"Ingreso",'Caja Diaria'!$E$4:$E$403,"MercadoPago",'Caja Diaria'!$A$4:$A$403,'Resumen Diario'!$A$18) -> 0 | H30: =SUM(C30:G30) -> 0 | I30: =IF(H30=0,0,C30/H30) -> 0
B31: ='Resumen Diario'!$A$19 -> 46250 | C31: =SUMIFS('Caja Diaria'!$F$4:$F$403,'Caja Diaria'!$B$4:$B$403,"Ingreso",'Caja Diaria'!$E$4:$E$403,"Efectivo",'Caja Diaria'!$A$4:$A$403,'Resumen Diario'!$A$19) -> 0 | D31: =SUMIFS('Caja Diaria'!$F$4:$F$403,'Caja Diaria'!$B$4:$B$403,"Ingreso",'Caja Diaria'!$E$4:$E$403,"Tarjeta débito",'Caja Diaria'!$A$4:$A$403,'Resumen Diario'!$A$19) -> 0 | E31: =SUMIFS('Caja Diaria'!$F$4:$F$403,'Caja Diaria'!$B$4:$B$403,"Ingreso",'Caja Diaria'!$E$4:$E$403,"Tarjeta crédito",'Caja Diaria'!$A$4:$A$403,'Resumen Diario'!$A$19) -> 0 | F31: =SUMIFS('Caja Diaria'!$F$4:$F$403,'Caja Diaria'!$B$4:$B$403,"Ingreso",'Caja Diaria'!$E$4:$E$403,"Transferencia",'Caja Diaria'!$A$4:$A$403,'Resumen Diario'!$A$19) -> 0 | G31: =SUMIFS('Caja Diaria'!$F$4:$F$403,'Caja Diaria'!$B$4:$B$403,"Ingreso",'Caja Diaria'!$E$4:$E$403,"MercadoPago",'Caja Diaria'!$A$4:$A$403,'Resumen Diario'!$A$19) -> 0 | H31: =SUM(C31:G31) -> 0 | I31: =IF(H31=0,0,C31/H31) -> 0
B32: ='Resumen Diario'!$A$20 -> 46251 | C32: =SUMIFS('Caja Diaria'!$F$4:$F$403,'Caja Diaria'!$B$4:$B$403,"Ingreso",'Caja Diaria'!$E$4:$E$403,"Efectivo",'Caja Diaria'!$A$4:$A$403,'Resumen Diario'!$A$20) -> 0 | D32: =SUMIFS('Caja Diaria'!$F$4:$F$403,'Caja Diaria'!$B$4:$B$403,"Ingreso",'Caja Diaria'!$E$4:$E$403,"Tarjeta débito",'Caja Diaria'!$A$4:$A$403,'Resumen Diario'!$A$20) -> 0 | E32: =SUMIFS('Caja Diaria'!$F$4:$F$403,'Caja Diaria'!$B$4:$B$403,"Ingreso",'Caja Diaria'!$E$4:$E$403,"Tarjeta crédito",'Caja Diaria'!$A$4:$A$403,'Resumen Diario'!$A$20) -> 0 | F32: =SUMIFS('Caja Diaria'!$F$4:$F$403,'Caja Diaria'!$B$4:$B$403,"Ingreso",'Caja Diaria'!$E$4:$E$403,"Transferencia",'Caja Diaria'!$A$4:$A$403,'Resumen Diario'!$A$20) -> 0 | G32: =SUMIFS('Caja Diaria'!$F$4:$F$403,'Caja Diaria'!$B$4:$B$403,"Ingreso",'Caja Diaria'!$E$4:$E$403,"MercadoPago",'Caja Diaria'!$A$4:$A$403,'Resumen Diario'!$A$20) -> 0 | H32: =SUM(C32:G32) -> 0 | I32: =IF(H32=0,0,C32/H32) -> 0
B33: ='Resumen Diario'!$A$21 -> 46252 | C33: =SUMIFS('Caja Diaria'!$F$4:$F$403,'Caja Diaria'!$B$4:$B$403,"Ingreso",'Caja Diaria'!$E$4:$E$403,"Efectivo",'Caja Diaria'!$A$4:$A$403,'Resumen Diario'!$A$21) -> 0 | D33: =SUMIFS('Caja Diaria'!$F$4:$F$403,'Caja Diaria'!$B$4:$B$403,"Ingreso",'Caja Diaria'!$E$4:$E$403,"Tarjeta débito",'Caja Diaria'!$A$4:$A$403,'Resumen Diario'!$A$21) -> 0 | E33: =SUMIFS('Caja Diaria'!$F$4:$F$403,'Caja Diaria'!$B$4:$B$403,"Ingreso",'Caja Diaria'!$E$4:$E$403,"Tarjeta crédito",'Caja Diaria'!$A$4:$A$403,'Resumen Diario'!$A$21) -> 0 | F33: =SUMIFS('Caja Diaria'!$F$4:$F$403,'Caja Diaria'!$B$4:$B$403,"Ingreso",'Caja Diaria'!$E$4:$E$403,"Transferencia",'Caja Diaria'!$A$4:$A$403,'Resumen Diario'!$A$21) -> 0 | G33: =SUMIFS('Caja Diaria'!$F$4:$F$403,'Caja Diaria'!$B$4:$B$403,"Ingreso",'Caja Diaria'!$E$4:$E$403,"MercadoPago",'Caja Diaria'!$A$4:$A$403,'Resumen Diario'!$A$21) -> 0 | H33: =SUM(C33:G33) -> 0 | I33: =IF(H33=0,0,C33/H33) -> 0
B34: ='Resumen Diario'!$A$22 -> 46253 | C34: =SUMIFS('Caja Diaria'!$F$4:$F$403,'Caja Diaria'!$B$4:$B$403,"Ingreso",'Caja Diaria'!$E$4:$E$403,"Efectivo",'Caja Diaria'!$A$4:$A$403,'Resumen Diario'!$A$22) -> 0 | D34: =SUMIFS('Caja Diaria'!$F$4:$F$403,'Caja Diaria'!$B$4:$B$403,"Ingreso",'Caja Diaria'!$E$4:$E$403,"Tarjeta débito",'Caja Diaria'!$A$4:$A$403,'Resumen Diario'!$A$22) -> 0 | E34: =SUMIFS('Caja Diaria'!$F$4:$F$403,'Caja Diaria'!$B$4:$B$403,"Ingreso",'Caja Diaria'!$E$4:$E$403,"Tarjeta crédito",'Caja Diaria'!$A$4:$A$403,'Resumen Diario'!$A$22) -> 0 | F34: =SUMIFS('Caja Diaria'!$F$4:$F$403,'Caja Diaria'!$B$4:$B$403,"Ingreso",'Caja Diaria'!$E$4:$E$403,"Transferencia",'Caja Diaria'!$A$4:$A$403,'Resumen Diario'!$A$22) -> 0 | G34: =SUMIFS('Caja Diaria'!$F$4:$F$403,'Caja Diaria'!$B$4:$B$403,"Ingreso",'Caja Diaria'!$E$4:$E$403,"MercadoPago",'Caja Diaria'!$A$4:$A$403,'Resumen Diario'!$A$22) -> 0 | H34: =SUM(C34:G34) -> 0 | I34: =IF(H34=0,0,C34/H34) -> 0
B35: ='Resumen Diario'!$A$23 -> 46254 | C35: =SUMIFS('Caja Diaria'!$F$4:$F$403,'Caja Diaria'!$B$4:$B$403,"Ingreso",'Caja Diaria'!$E$4:$E$403,"Efectivo",'Caja Diaria'!$A$4:$A$403,'Resumen Diario'!$A$23) -> 0 | D35: =SUMIFS('Caja Diaria'!$F$4:$F$403,'Caja Diaria'!$B$4:$B$403,"Ingreso",'Caja Diaria'!$E$4:$E$403,"Tarjeta débito",'Caja Diaria'!$A$4:$A$403,'Resumen Diario'!$A$23) -> 0 | E35: =SUMIFS('Caja Diaria'!$F$4:$F$403,'Caja Diaria'!$B$4:$B$403,"Ingreso",'Caja Diaria'!$E$4:$E$403,"Tarjeta crédito",'Caja Diaria'!$A$4:$A$403,'Resumen Diario'!$A$23) -> 0 | F35: =SUMIFS('Caja Diaria'!$F$4:$F$403,'Caja Diaria'!$B$4:$B$403,"Ingreso",'Caja Diaria'!$E$4:$E$403,"Transferencia",'Caja Diaria'!$A$4:$A$403,'Resumen Diario'!$A$23) -> 0 | G35: =SUMIFS('Caja Diaria'!$F$4:$F$403,'Caja Diaria'!$B$4:$B$403,"Ingreso",'Caja Diaria'!$E$4:$E$403,"MercadoPago",'Caja Diaria'!$A$4:$A$403,'Resumen Diario'!$A$23) -> 0 | H35: =SUM(C35:G35) -> 0 | I35: =IF(H35=0,0,C35/H35) -> 0
B36: ='Resumen Diario'!$A$24 -> 46255 | C36: =SUMIFS('Caja Diaria'!$F$4:$F$403,'Caja Diaria'!$B$4:$B$403,"Ingreso",'Caja Diaria'!$E$4:$E$403,"Efectivo",'Caja Diaria'!$A$4:$A$403,'Resumen Diario'!$A$24) -> 0 | D36: =SUMIFS('Caja Diaria'!$F$4:$F$403,'Caja Diaria'!$B$4:$B$403,"Ingreso",'Caja Diaria'!$E$4:$E$403,"Tarjeta débito",'Caja Diaria'!$A$4:$A$403,'Resumen Diario'!$A$24) -> 0 | E36: =SUMIFS('Caja Diaria'!$F$4:$F$403,'Caja Diaria'!$B$4:$B$403,"Ingreso",'Caja Diaria'!$E$4:$E$403,"Tarjeta crédito",'Caja Diaria'!$A$4:$A$403,'Resumen Diario'!$A$24) -> 0 | F36: =SUMIFS('Caja Diaria'!$F$4:$F$403,'Caja Diaria'!$B$4:$B$403,"Ingreso",'Caja Diaria'!$E$4:$E$403,"Transferencia",'Caja Diaria'!$A$4:$A$403,'Resumen Diario'!$A$24) -> 0 | G36: =SUMIFS('Caja Diaria'!$F$4:$F$403,'Caja Diaria'!$B$4:$B$403,"Ingreso",'Caja Diaria'!$E$4:$E$403,"MercadoPago",'Caja Diaria'!$A$4:$A$403,'Resumen Diario'!$A$24) -> 0 | H36: =SUM(C36:G36) -> 0 | I36: =IF(H36=0,0,C36/H36) -> 0
B37: ='Resumen Diario'!$A$25 -> 46256 | C37: =SUMIFS('Caja Diaria'!$F$4:$F$403,'Caja Diaria'!$B$4:$B$403,"Ingreso",'Caja Diaria'!$E$4:$E$403,"Efectivo",'Caja Diaria'!$A$4:$A$403,'Resumen Diario'!$A$25) -> 0 | D37: =SUMIFS('Caja Diaria'!$F$4:$F$403,'Caja Diaria'!$B$4:$B$403,"Ingreso",'Caja Diaria'!$E$4:$E$403,"Tarjeta débito",'Caja Diaria'!$A$4:$A$403,'Resumen Diario'!$A$25) -> 0 | E37: =SUMIFS('Caja Diaria'!$F$4:$F$403,'Caja Diaria'!$B$4:$B$403,"Ingreso",'Caja Diaria'!$E$4:$E$403,"Tarjeta crédito",'Caja Diaria'!$A$4:$A$403,'Resumen Diario'!$A$25) -> 0 | F37: =SUMIFS('Caja Diaria'!$F$4:$F$403,'Caja Diaria'!$B$4:$B$403,"Ingreso",'Caja Diaria'!$E$4:$E$403,"Transferencia",'Caja Diaria'!$A$4:$A$403,'Resumen Diario'!$A$25) -> 0 | G37: =SUMIFS('Caja Diaria'!$F$4:$F$403,'Caja Diaria'!$B$4:$B$403,"Ingreso",'Caja Diaria'!$E$4:$E$403,"MercadoPago",'Caja Diaria'!$A$4:$A$403,'Resumen Diario'!$A$25) -> 0 | H37: =SUM(C37:G37) -> 0 | I37: =IF(H37=0,0,C37/H37) -> 0
B38: ='Resumen Diario'!$A$26 -> 46257 | C38: =SUMIFS('Caja Diaria'!$F$4:$F$403,'Caja Diaria'!$B$4:$B$403,"Ingreso",'Caja Diaria'!$E$4:$E$403,"Efectivo",'Caja Diaria'!$A$4:$A$403,'Resumen Diario'!$A$26) -> 0 | D38: =SUMIFS('Caja Diaria'!$F$4:$F$403,'Caja Diaria'!$B$4:$B$403,"Ingreso",'Caja Diaria'!$E$4:$E$403,"Tarjeta débito",'Caja Diaria'!$A$4:$A$403,'Resumen Diario'!$A$26) -> 0 | E38: =SUMIFS('Caja Diaria'!$F$4:$F$403,'Caja Diaria'!$B$4:$B$403,"Ingreso",'Caja Diaria'!$E$4:$E$403,"Tarjeta crédito",'Caja Diaria'!$A$4:$A$403,'Resumen Diario'!$A$26) -> 0 | F38: =SUMIFS('Caja Diaria'!$F$4:$F$403,'Caja Diaria'!$B$4:$B$403,"Ingreso",'Caja Diaria'!$E$4:$E$403,"Transferencia",'Caja Diaria'!$A$4:$A$403,'Resumen Diario'!$A$26) -> 0 | G38: =SUMIFS('Caja Diaria'!$F$4:$F$403,'Caja Diaria'!$B$4:$B$403,"Ingreso",'Caja Diaria'!$E$4:$E$403,"MercadoPago",'Caja Diaria'!$A$4:$A$403,'Resumen Diario'!$A$26) -> 0 | H38: =SUM(C38:G38) -> 0 | I38: =IF(H38=0,0,C38/H38) -> 0
B39: ='Resumen Diario'!$A$27 -> 46258 | C39: =SUMIFS('Caja Diaria'!$F$4:$F$403,'Caja Diaria'!$B$4:$B$403,"Ingreso",'Caja Diaria'!$E$4:$E$403,"Efectivo",'Caja Diaria'!$A$4:$A$403,'Resumen Diario'!$A$27) -> 0 | D39: =SUMIFS('Caja Diaria'!$F$4:$F$403,'Caja Diaria'!$B$4:$B$403,"Ingreso",'Caja Diaria'!$E$4:$E$403,"Tarjeta débito",'Caja Diaria'!$A$4:$A$403,'Resumen Diario'!$A$27) -> 0 | E39: =SUMIFS('Caja Diaria'!$F$4:$F$403,'Caja Diaria'!$B$4:$B$403,"Ingreso",'Caja Diaria'!$E$4:$E$403,"Tarjeta crédito",'Caja Diaria'!$A$4:$A$403,'Resumen Diario'!$A$27) -> 0 | F39: =SUMIFS('Caja Diaria'!$F$4:$F$403,'Caja Diaria'!$B$4:$B$403,"Ingreso",'Caja Diaria'!$E$4:$E$403,"Transferencia",'Caja Diaria'!$A$4:$A$403,'Resumen Diario'!$A$27) -> 0 | G39: =SUMIFS('Caja Diaria'!$F$4:$F$403,'Caja Diaria'!$B$4:$B$403,"Ingreso",'Caja Diaria'!$E$4:$E$403,"MercadoPago",'Caja Diaria'!$A$4:$A$403,'Resumen Diario'!$A$27) -> 0 | H39: =SUM(C39:G39) -> 0 | I39: =IF(H39=0,0,C39/H39) -> 0
B40: ='Resumen Diario'!$A$28 -> 46259 | C40: =SUMIFS('Caja Diaria'!$F$4:$F$403,'Caja Diaria'!$B$4:$B$403,"Ingreso",'Caja Diaria'!$E$4:$E$403,"Efectivo",'Caja Diaria'!$A$4:$A$403,'Resumen Diario'!$A$28) -> 0 | D40: =SUMIFS('Caja Diaria'!$F$4:$F$403,'Caja Diaria'!$B$4:$B$403,"Ingreso",'Caja Diaria'!$E$4:$E$403,"Tarjeta débito",'Caja Diaria'!$A$4:$A$403,'Resumen Diario'!$A$28) -> 0 | E40: =SUMIFS('Caja Diaria'!$F$4:$F$403,'Caja Diaria'!$B$4:$B$403,"Ingreso",'Caja Diaria'!$E$4:$E$403,"Tarjeta crédito",'Caja Diaria'!$A$4:$A$403,'Resumen Diario'!$A$28) -> 0 | F40: =SUMIFS('Caja Diaria'!$F$4:$F$403,'Caja Diaria'!$B$4:$B$403,"Ingreso",'Caja Diaria'!$E$4:$E$403,"Transferencia",'Caja Diaria'!$A$4:$A$403,'Resumen Diario'!$A$28) -> 0 | G40: =SUMIFS('Caja Diaria'!$F$4:$F$403,'Caja Diaria'!$B$4:$B$403,"Ingreso",'Caja Diaria'!$E$4:$E$403,"MercadoPago",'Caja Diaria'!$A$4:$A$403,'Resumen Diario'!$A$28) -> 0 | H40: =SUM(C40:G40) -> 0 | I40: =IF(H40=0,0,C40/H40) -> 0
B41: ='Resumen Diario'!$A$29 -> 46260 | C41: =SUMIFS('Caja Diaria'!$F$4:$F$403,'Caja Diaria'!$B$4:$B$403,"Ingreso",'Caja Diaria'!$E$4:$E$403,"Efectivo",'Caja Diaria'!$A$4:$A$403,'Resumen Diario'!$A$29) -> 0 | D41: =SUMIFS('Caja Diaria'!$F$4:$F$403,'Caja Diaria'!$B$4:$B$403,"Ingreso",'Caja Diaria'!$E$4:$E$403,"Tarjeta débito",'Caja Diaria'!$A$4:$A$403,'Resumen Diario'!$A$29) -> 0 | E41: =SUMIFS('Caja Diaria'!$F$4:$F$403,'Caja Diaria'!$B$4:$B$403,"Ingreso",'Caja Diaria'!$E$4:$E$403,"Tarjeta crédito",'Caja Diaria'!$A$4:$A$403,'Resumen Diario'!$A$29) -> 0 | F41: =SUMIFS('Caja Diaria'!$F$4:$F$403,'Caja Diaria'!$B$4:$B$403,"Ingreso",'Caja Diaria'!$E$4:$E$403,"Transferencia",'Caja Diaria'!$A$4:$A$403,'Resumen Diario'!$A$29) -> 0 | G41: =SUMIFS('Caja Diaria'!$F$4:$F$403,'Caja Diaria'!$B$4:$B$403,"Ingreso",'Caja Diaria'!$E$4:$E$403,"MercadoPago",'Caja Diaria'!$A$4:$A$403,'Resumen Diario'!$A$29) -> 0 | H41: =SUM(C41:G41) -> 0 | I41: =IF(H41=0,0,C41/H41) -> 0
B42: ='Resumen Diario'!$A$30 -> 46261 | C42: =SUMIFS('Caja Diaria'!$F$4:$F$403,'Caja Diaria'!$B$4:$B$403,"Ingreso",'Caja Diaria'!$E$4:$E$403,"Efectivo",'Caja Diaria'!$A$4:$A$403,'Resumen Diario'!$A$30) -> 0 | D42: =SUMIFS('Caja Diaria'!$F$4:$F$403,'Caja Diaria'!$B$4:$B$403,"Ingreso",'Caja Diaria'!$E$4:$E$403,"Tarjeta débito",'Caja Diaria'!$A$4:$A$403,'Resumen Diario'!$A$30) -> 0 | E42: =SUMIFS('Caja Diaria'!$F$4:$F$403,'Caja Diaria'!$B$4:$B$403,"Ingreso",'Caja Diaria'!$E$4:$E$403,"Tarjeta crédito",'Caja Diaria'!$A$4:$A$403,'Resumen Diario'!$A$30) -> 0 | F42: =SUMIFS('Caja Diaria'!$F$4:$F$403,'Caja Diaria'!$B$4:$B$403,"Ingreso",'Caja Diaria'!$E$4:$E$403,"Transferencia",'Caja Diaria'!$A$4:$A$403,'Resumen Diario'!$A$30) -> 0 | G42: =SUMIFS('Caja Diaria'!$F$4:$F$403,'Caja Diaria'!$B$4:$B$403,"Ingreso",'Caja Diaria'!$E$4:$E$403,"MercadoPago",'Caja Diaria'!$A$4:$A$403,'Resumen Diario'!$A$30) -> 0 | H42: =SUM(C42:G42) -> 0 | I42: =IF(H42=0,0,C42/H42) -> 0
B43: ='Resumen Diario'!$A$31 -> 46262 | C43: =SUMIFS('Caja Diaria'!$F$4:$F$403,'Caja Diaria'!$B$4:$B$403,"Ingreso",'Caja Diaria'!$E$4:$E$403,"Efectivo",'Caja Diaria'!$A$4:$A$403,'Resumen Diario'!$A$31) -> 0 | D43: =SUMIFS('Caja Diaria'!$F$4:$F$403,'Caja Diaria'!$B$4:$B$403,"Ingreso",'Caja Diaria'!$E$4:$E$403,"Tarjeta débito",'Caja Diaria'!$A$4:$A$403,'Resumen Diario'!$A$31) -> 0 | E43: =SUMIFS('Caja Diaria'!$F$4:$F$403,'Caja Diaria'!$B$4:$B$403,"Ingreso",'Caja Diaria'!$E$4:$E$403,"Tarjeta crédito",'Caja Diaria'!$A$4:$A$403,'Resumen Diario'!$A$31) -> 0 | F43: =SUMIFS('Caja Diaria'!$F$4:$F$403,'Caja Diaria'!$B$4:$B$403,"Ingreso",'Caja Diaria'!$E$4:$E$403,"Transferencia",'Caja Diaria'!$A$4:$A$403,'Resumen Diario'!$A$31) -> 0 | G43: =SUMIFS('Caja Diaria'!$F$4:$F$403,'Caja Diaria'!$B$4:$B$403,"Ingreso",'Caja Diaria'!$E$4:$E$403,"MercadoPago",'Caja Diaria'!$A$4:$A$403,'Resumen Diario'!$A$31) -> 0 | H43: =SUM(C43:G43) -> 0 | I43: =IF(H43=0,0,C43/H43) -> 0
B44: ='Resumen Diario'!$A$32 -> 46263 | C44: =SUMIFS('Caja Diaria'!$F$4:$F$403,'Caja Diaria'!$B$4:$B$403,"Ingreso",'Caja Diaria'!$E$4:$E$403,"Efectivo",'Caja Diaria'!$A$4:$A$403,'Resumen Diario'!$A$32) -> 0 | D44: =SUMIFS('Caja Diaria'!$F$4:$F$403,'Caja Diaria'!$B$4:$B$403,"Ingreso",'Caja Diaria'!$E$4:$E$403,"Tarjeta débito",'Caja Diaria'!$A$4:$A$403,'Resumen Diario'!$A$32) -> 0 | E44: =SUMIFS('Caja Diaria'!$F$4:$F$403,'Caja Diaria'!$B$4:$B$403,"Ingreso",'Caja Diaria'!$E$4:$E$403,"Tarjeta crédito",'Caja Diaria'!$A$4:$A$403,'Resumen Diario'!$A$32) -> 0 | F44: =SUMIFS('Caja Diaria'!$F$4:$F$403,'Caja Diaria'!$B$4:$B$403,"Ingreso",'Caja Diaria'!$E$4:$E$403,"Transferencia",'Caja Diaria'!$A$4:$A$403,'Resumen Diario'!$A$32) -> 0 | G44: =SUMIFS('Caja Diaria'!$F$4:$F$403,'Caja Diaria'!$B$4:$B$403,"Ingreso",'Caja Diaria'!$E$4:$E$403,"MercadoPago",'Caja Diaria'!$A$4:$A$403,'Resumen Diario'!$A$32) -> 0 | H44: =SUM(C44:G44) -> 0 | I44: =IF(H44=0,0,C44/H44) -> 0
B45: ='Resumen Diario'!$A$33 -> 46264 | C45: =SUMIFS('Caja Diaria'!$F$4:$F$403,'Caja Diaria'!$B$4:$B$403,"Ingreso",'Caja Diaria'!$E$4:$E$403,"Efectivo",'Caja Diaria'!$A$4:$A$403,'Resumen Diario'!$A$33) -> 0 | D45: =SUMIFS('Caja Diaria'!$F$4:$F$403,'Caja Diaria'!$B$4:$B$403,"Ingreso",'Caja Diaria'!$E$4:$E$403,"Tarjeta débito",'Caja Diaria'!$A$4:$A$403,'Resumen Diario'!$A$33) -> 0 | E45: =SUMIFS('Caja Diaria'!$F$4:$F$403,'Caja Diaria'!$B$4:$B$403,"Ingreso",'Caja Diaria'!$E$4:$E$403,"Tarjeta crédito",'Caja Diaria'!$A$4:$A$403,'Resumen Diario'!$A$33) -> 0 | F45: =SUMIFS('Caja Diaria'!$F$4:$F$403,'Caja Diaria'!$B$4:$B$403,"Ingreso",'Caja Diaria'!$E$4:$E$403,"Transferencia",'Caja Diaria'!$A$4:$A$403,'Resumen Diario'!$A$33) -> 0 | G45: =SUMIFS('Caja Diaria'!$F$4:$F$403,'Caja Diaria'!$B$4:$B$403,"Ingreso",'Caja Diaria'!$E$4:$E$403,"MercadoPago",'Caja Diaria'!$A$4:$A$403,'Resumen Diario'!$A$33) -> 0 | H45: =SUM(C45:G45) -> 0 | I45: =IF(H45=0,0,C45/H45) -> 0
B46: ='Resumen Diario'!$A$34 -> 46265 | C46: =SUMIFS('Caja Diaria'!$F$4:$F$403,'Caja Diaria'!$B$4:$B$403,"Ingreso",'Caja Diaria'!$E$4:$E$403,"Efectivo",'Caja Diaria'!$A$4:$A$403,'Resumen Diario'!$A$34) -> 0 | D46: =SUMIFS('Caja Diaria'!$F$4:$F$403,'Caja Diaria'!$B$4:$B$403,"Ingreso",'Caja Diaria'!$E$4:$E$403,"Tarjeta débito",'Caja Diaria'!$A$4:$A$403,'Resumen Diario'!$A$34) -> 0 | E46: =SUMIFS('Caja Diaria'!$F$4:$F$403,'Caja Diaria'!$B$4:$B$403,"Ingreso",'Caja Diaria'!$E$4:$E$403,"Tarjeta crédito",'Caja Diaria'!$A$4:$A$403,'Resumen Diario'!$A$34) -> 0 | F46: =SUMIFS('Caja Diaria'!$F$4:$F$403,'Caja Diaria'!$B$4:$B$403,"Ingreso",'Caja Diaria'!$E$4:$E$403,"Transferencia",'Caja Diaria'!$A$4:$A$403,'Resumen Diario'!$A$34) -> 0 | G46: =SUMIFS('Caja Diaria'!$F$4:$F$403,'Caja Diaria'!$B$4:$B$403,"Ingreso",'Caja Diaria'!$E$4:$E$403,"MercadoPago",'Caja Diaria'!$A$4:$A$403,'Resumen Diario'!$A$34) -> 0 | H46: =SUM(C46:G46) -> 0 | I46: =IF(H46=0,0,C46/H46) -> 0
B47: TOTAL | C47: =SUM(C16:C46) -> 543000 | D47: =SUM(D16:D46) -> 0 | E47: =SUM(E16:E46) -> 2665500 | F47: =SUM(F16:F46) -> 0 | G47: =SUM(G16:G46) -> 2628000 | H47: =SUM(H16:H46) -> 5836500 | I47: =IF(H47=0,0,C47/H47) -> 0.093035209

Sheet Empleados
B1: Empleados — sueldos y cargas sociales
B2: Cargá el sueldo bruto de cada uno (azul). Las cargas y el total se calculan. El TOTAL alimenta 'Gastos del Mes'.
B4: % Cargas sociales | C4: 0.27 | D4: Editable (default 27%)
B6: Empleado | C6: Sueldo bruto ARS | D6: Cargas sociales | E6: Total ARS
B7: Recepción 1 | C7: 0 | D7: =C7*$C$4 -> 0 | E7: =C7+D7 -> 0
B8: Recepción 2 | C8: 0 | D8: =C8*$C$4 -> 0 | E8: =C8+D8 -> 0
B9: Enfermero/a | C9: 0 | D9: =C9*$C$4 -> 0 | E9: =C9+D9 -> 0
B10: Técnico/a 1 | C10: 0 | D10: =C10*$C$4 -> 0 | E10: =C10+D10 -> 0
B11: Técnico/a 2 | C11: 0 | D11: =C11*$C$4 -> 0 | E11: =C11+D11 -> 0
B12: Coordinador/a operativo/a | C12: 0 | D12: =C12*$C$4 -> 0 | E12: =C12+D12 -> 0
B13: Limpieza | C13: 0 | D13: =C13*$C$4 -> 0 | E13: =C13+D13 -> 0
B14: Mantenimiento | C14: 0 | D14: =C14*$C$4 -> 0 | E14: =C14+D14 -> 0
B15: Marketing in-house | C15: 0 | D15: =C15*$C$4 -> 0 | E15: =C15+D15 -> 0
B16: (libre) | C16: 0 | D16: =C16*$C$4 -> 0 | E16: =C16+D16 -> 0
B17: (libre) | C17: 0 | D17: =C17*$C$4 -> 0 | E17: =C17+D17 -> 0
B18: (libre) | C18: 0 | D18: =C18*$C$4 -> 0 | E18: =C18+D18 -> 0
B19: TOTAL (sueldos + cargas) | C19: =SUM(C7:C18) -> 0 | D19: =SUM(D7:D18) -> 0 | E19: =SUM(E7:E18) -> 0
B21: Nota: el personal del Bar NO va acá (el Bar es unidad aparte, se carga su neto en el Dashboard).

Sheet Gastos Varios
B1: Gastos Varios — detalle
B2: Volcá acá cada gasto vario. El TOTAL alimenta 'Gastos del Mes'.
B4: Fecha | C4: Concepto | D4: Monto ARS
C45: TOTAL GASTOS VARIOS | D45: =SUM(D5:D44) -> 0

Sheet Consultas (Split)
B1: Consultas médicas y nutrición — split de ingresos
B2: Cargá cantidad y precio (azul). Calcula el reparto. El neto BW es lo que le queda a Biowellness.
B4: Consultas médicas — split 70% médico / 30% BW
C5: Cantidad | D5: Precio ARS | E5: Ingreso bruto | F5: Médicos (70%) | G5: BW (30%)
B6: Consultas médicas | C6: 0 | D6: 0 | E6: =C6*D6 -> 0 | F6: =E6*0.7 -> 0 | G6: =E6*0.3 -> 0
B9: Consultas nutrición — 50% nutri / 20% Diego Sívori / 30% BW
C10: Cantidad | D10: Precio ARS | E10: Ingreso bruto | F10: Nutri (50%) | G10: Sívori (20%) | H10: BW (30%)
B11: Consultas nutrición | C11: 0 | D11: 0 | E11: =C11*D11 -> 0 | F11: =E11*0.5 -> 0 | G11: =E11*0.2 -> 0 | H11: =E11*0.3 -> 0
B14: Resumen
B15: Neto BW total consultas | C15: =G6+H11 -> 0
B16: Payout médicos | C16: =F6 -> 0
B17: Payout nutricionista | C17: =F11 -> 0
B18: Payout Diego Sívori | C18: =G11 -> 0
B20: PENDIENTE (definir con Andrés): en qué línea del estado de resultados impacta el 'Neto BW de consultas'. Por ahora esta hoja calcula los splits pero NO está conectada al Dashboard. Avisame y lo enchufo (línea propia o dentro de 'Otros').
