Workbook

Sheet Dashboard Anual
B1: BIOWELLNESS — Dashboard Anual 2026
B2: Se actualiza solo desde Resumen Anual
B4: INGRESOS AÑO (ARS) | E4: RESULTADO TOTAL AÑO | H4: MARGEN ANUAL | K4: MEJOR MES
B5: ='Resumen Anual'!O9 -> 0 | E5: ='Resumen Anual'!O14 -> 0 | H5: ='Resumen Anual'!O15 -> 0 | K5: =INDEX('Resumen Anual'!C$3:N$3,MATCH(MAX('Resumen Anual'!C14:N14),'Resumen Anual'!C14:N14,0)) -> Ene
B9: Evolución mensual (ARS)
B10: Mes | C10: Ingresos | D10: Resultado total
B11: Ene | C11: ='Resumen Anual'!C9 -> 0 | D11: ='Resumen Anual'!C14 -> 0
B12: Feb | C12: ='Resumen Anual'!D9 -> 0 | D12: ='Resumen Anual'!D14 -> 0
B13: Mar | C13: ='Resumen Anual'!E9 -> 0 | D13: ='Resumen Anual'!E14 -> 0
B14: Abr | C14: ='Resumen Anual'!F9 -> 0 | D14: ='Resumen Anual'!F14 -> 0
B15: May | C15: ='Resumen Anual'!G9 -> 0 | D15: ='Resumen Anual'!G14 -> 0
B16: Jun | C16: ='Resumen Anual'!H9 -> 0 | D16: ='Resumen Anual'!H14 -> 0
B17: Jul | C17: ='Resumen Anual'!I9 -> 0 | D17: ='Resumen Anual'!I14 -> 0
B18: Ago | C18: ='Resumen Anual'!J9 -> 0 | D18: ='Resumen Anual'!J14 -> 0
B19: Sep | C19: ='Resumen Anual'!K9 -> 0 | D19: ='Resumen Anual'!K14 -> 0
B20: Oct | C20: ='Resumen Anual'!L9 -> 0 | D20: ='Resumen Anual'!L14 -> 0
B21: Nov | C21: ='Resumen Anual'!M9 -> 0 | D21: ='Resumen Anual'!M14 -> 0
B22: Dic | C22: ='Resumen Anual'!N9 -> 0 | D22: ='Resumen Anual'!N14 -> 0
B25: Mix de ingresos del año
B26: Línea | C26: ARS
B27: Membresías | C27: ='Resumen Anual'!O4 -> 0
B28: Sueltas & Combos | C28: ='Resumen Anual'!O5 -> 0
B29: Paquetes | C29: ='Resumen Anual'!O6 -> 0
B30: IV + Terapias Biológicas | C30: ='Resumen Anual'!O7 -> 0
B31: Otros | C31: ='Resumen Anual'!O8 -> 0

Sheet Resumen Anual
B1: BIOWELLNESS — Consolidado Anual 2026
B2: Pegá cada mes los totales del Dashboard Mensual en las celdas AZULES. Verde = se calcula solo. La operación arranca en Agosto.
B3: Concepto (ARS) | C3: Ene | D3: Feb | E3: Mar | F3: Abr | G3: May | H3: Jun | I3: Jul | J3: Ago | K3: Sep | L3: Oct | M3: Nov | N3: Dic | O3: Total / Prom.
B4: Membresías | C4: 0 | D4: 0 | E4: 0 | F4: 0 | G4: 0 | H4: 0 | I4: 0 | J4: 0 | K4: 0 | L4: 0 | M4: 0 | N4: 0 | O4: =SUM(C4:N4) -> 0
B5: Sueltas & Combos | C5: 0 | D5: 0 | E5: 0 | F5: 0 | G5: 0 | H5: 0 | I5: 0 | J5: 0 | K5: 0 | L5: 0 | M5: 0 | N5: 0 | O5: =SUM(C5:N5) -> 0
B6: Paquetes | C6: 0 | D6: 0 | E6: 0 | F6: 0 | G6: 0 | H6: 0 | I6: 0 | J6: 0 | K6: 0 | L6: 0 | M6: 0 | N6: 0 | O6: =SUM(C6:N6) -> 0
B7: IV + Terapias Biológicas | C7: 0 | D7: 0 | E7: 0 | F7: 0 | G7: 0 | H7: 0 | I7: 0 | J7: 0 | K7: 0 | L7: 0 | M7: 0 | N7: 0 | O7: =SUM(C7:N7) -> 0
B8: Otros | C8: 0 | D8: 0 | E8: 0 | F8: 0 | G8: 0 | H8: 0 | I8: 0 | J8: 0 | K8: 0 | L8: 0 | M8: 0 | N8: 0 | O8: =SUM(C8:N8) -> 0
B9: INGRESOS WELLNESS | C9: =SUM(C4:C8) -> 0 | D9: =SUM(D4:D8) -> 0 | E9: =SUM(E4:E8) -> 0 | F9: =SUM(F4:F8) -> 0 | G9: =SUM(G4:G8) -> 0 | H9: =SUM(H4:H8) -> 0 | I9: =SUM(I4:I8) -> 0 | J9: =SUM(J4:J8) -> 0 | ... N9: =SUM(N4:N8) -> 0 | O9: =SUM(C9:N9) -> 0
B10: (–) Gastos operativos | C10: 0 | D10: 0 | E10: 0 | F10: 0 | G10: 0 | H10: 0 | I10: 0 | J10: 0 | K10: 0 | L10: 0 | M10: 0 | N10: 0 | O10: =SUM(C10:N10) -> 0
B11: (–) Egresos de caja chica | C11: 0 | D11: 0 | E11: 0 | F11: 0 | G11: 0 | H11: 0 | I11: 0 | J11: 0 | K11: 0 | L11: 0 | M11: 0 | N11: 0 | O11: =SUM(C11:N11) -> 0
B12: RESULTADO WELLNESS | C12: =C9-C10-C11 -> 0 | D12: =D9-D10-D11 -> 0 | E12: =E9-E10-E11 -> 0 | F12: =F9-F10-F11 -> 0 | G12: =G9-G10-G11 -> 0 | H12: =H9-H10-H11 -> 0 | I12: =I9-I10-I11 -> 0 | J12: =J9-J10-J11 -> 0 | ... N12: =N9-N10-N11 -> 0 | O12: =SUM(C12:N12) -> 0
B13: (+) Bar — resultado neto | C13: 0 | D13: 0 | E13: 0 | F13: 0 | G13: 0 | H13: 0 | I13: 0 | J13: 0 | K13: 0 | L13: 0 | M13: 0 | N13: 0 | O13: =SUM(C13:N13) -> 0
B14: RESULTADO TOTAL | C14: =C12+C13 -> 0 | D14: =D12+D13 -> 0 | E14: =E12+E13 -> 0 | F14: =F12+F13 -> 0 | G14: =G12+G13 -> 0 | H14: =H12+H13 -> 0 | I14: =I12+I13 -> 0 | J14: =J12+J13 -> 0 | ... N14: =N12+N13 -> 0 | O14: =SUM(C14:N14) -> 0
B15: Margen operativo (wellness) | C15: =IF(C9=0,0,C12/C9) -> 0 | D15: =IF(D9=0,0,D12/D9) -> 0 | E15: =IF(E9=0,0,E12/E9) -> 0 | F15: =IF(F9=0,0,F12/F9) -> 0 | G15: =IF(G9=0,0,G12/G9) -> 0 | H15: =IF(H9=0,0,H12/H9) -> 0 | I15: =IF(I9=0,0,I12/I9) -> 0 | J15: =IF(J9=0,0,J12/J9) -> 0 | ... O15: =IF(O9=0,0,O12/O9) -> 0
B17: Distribución del resultado por socio (referencia bruta)
B18: Socio | C18: Ene | D18: Feb | E18: Mar | F18: Abr | G18: May | H18: Jun | I18: Jul | J18: Ago | K18: Sep | L18: Oct | M18: Nov | N18: Dic | O18: Total | Q18: %
B19: Andrés Aizenberg | C19: =$Q19*C14 -> 0 | D19: =$Q19*D14 -> 0 | E19: =$Q19*E14 -> 0 | F19: =$Q19*F14 -> 0 | G19: =$Q19*G14 -> 0 | H19: =$Q19*H14 -> 0 | I19: =$Q19*I14 -> 0 | J19: =$Q19*J14 -> 0 | ... N19: =$Q19*N14 -> 0 | O19: =SUM(C19:N19) -> 0 | Q19: 0.53
B20: Diego | C20: =$Q20*C14 -> 0 | D20: =$Q20*D14 -> 0 | E20: =$Q20*E14 -> 0 | F20: =$Q20*F14 -> 0 | G20: =$Q20*G14 -> 0 | H20: =$Q20*H14 -> 0 | I20: =$Q20*I14 -> 0 | J20: =$Q20*J14 -> 0 | ... N20: =$Q20*N14 -> 0 | O20: =SUM(C20:N20) -> 0 | Q20: 0.24
B21: Daniel Tognetti | C21: =$Q21*C14 -> 0 | D21: =$Q21*D14 -> 0 | E21: =$Q21*E14 -> 0 | F21: =$Q21*F14 -> 0 | G21: =$Q21*G14 -> 0 | H21: =$Q21*H14 -> 0 | I21: =$Q21*I14 -> 0 | J21: =$Q21*J14 -> 0 | ... N21: =$Q21*N14 -> 0 | O21: =SUM(C21:N21) -> 0 | Q21: 0.09
B22: Evangelina Varela | C22: =$Q22*C14 -> 0 | D22: =$Q22*D14 -> 0 | E22: =$Q22*E14 -> 0 | F22: =$Q22*F14 -> 0 | G22: =$Q22*G14 -> 0 | H22: =$Q22*H14 -> 0 | I22: =$Q22*I14 -> 0 | J22: =$Q22*J14 -> 0 | ... N22: =$Q22*N14 -> 0 | O22: =SUM(C22:N22) -> 0 | Q22: 0.06
B23: Julián Massetti | C23: =$Q23*C14 -> 0 | D23: =$Q23*D14 -> 0 | E23: =$Q23*E14 -> 0 | F23: =$Q23*F14 -> 0 | G23: =$Q23*G14 -> 0 | H23: =$Q23*H14 -> 0 | I23: =$Q23*I14 -> 0 | J23: =$Q23*J14 -> 0 | ... N23: =$Q23*N14 -> 0 | O23: =SUM(C23:N23) -> 0 | Q23: 0.05
B24: Fernando Aldazabal | C24: =$Q24*C14 -> 0 | D24: =$Q24*D14 -> 0 | E24: =$Q24*E14 -> 0 | F24: =$Q24*F14 -> 0 | G24: =$Q24*G14 -> 0 | H24: =$Q24*H14 -> 0 | I24: =$Q24*I14 -> 0 | J24: =$Q24*J14 -> 0 | ... N24: =$Q24*N14 -> 0 | O24: =SUM(C24:N24) -> 0 | Q24: 0.02
B25: Diego Sívori | C25: =$Q25*C14 -> 0 | D25: =$Q25*D14 -> 0 | E25: =$Q25*E14 -> 0 | F25: =$Q25*F14 -> 0 | G25: =$Q25*G14 -> 0 | H25: =$Q25*H14 -> 0 | I25: =$Q25*I14 -> 0 | J25: =$Q25*J14 -> 0 | ... N25: =$Q25*N14 -> 0 | O25: =SUM(C25:N25) -> 0 | Q25: 0.01
B26: TOTAL distribuido | C26: =SUM(C19:C25) -> 0 | D26: =SUM(D19:D25) -> 0 | E26: =SUM(E19:E25) -> 0 | F26: =SUM(F19:F25) -> 0 | G26: =SUM(G19:G25) -> 0 | H26: =SUM(H19:H25) -> 0 | I26: =SUM(I19:I25) -> 0 | J26: =SUM(J19:J25) -> 0 | ... O26: =SUM(O19:O25) -> 0 | Q26: =SUM(Q19:Q25) -> 1
B28: Los % (columna Q, azul) son editables. Reparto bruto del resultado total; no descuenta reservas ni CAPEX. Validar con Andrés.
B29: Formas de pago (montos del mes, ARS) — pegá de la pestaña Formas de Pago
B30: Método | C30: Ene | D30: Feb | E30: Mar | F30: Abr | G30: May | H30: Jun | I30: Jul | J30: Ago | K30: Sep | L30: Oct | M30: Nov | N30: Dic | O30: Total | Q30: %
B31: Efectivo | C31: 0 | D31: 0 | E31: 0 | F31: 0 | G31: 0 | H31: 0 | I31: 0 | J31: 0 | K31: 0 | L31: 0 | M31: 0 | N31: 0 | O31: =SUM(C31:N31) -> 0 | Q31: =IF($O$36=0,0,O31/$O$36) -> 0
B32: Tarjeta débito | C32: 0 | D32: 0 | E32: 0 | F32: 0 | G32: 0 | H32: 0 | I32: 0 | J32: 0 | K32: 0 | L32: 0 | M32: 0 | N32: 0 | O32: =SUM(C32:N32) -> 0 | Q32: =IF($O$36=0,0,O32/$O$36) -> 0
B33: Tarjeta crédito | C33: 0 | D33: 0 | E33: 0 | F33: 0 | G33: 0 | H33: 0 | I33: 0 | J33: 0 | K33: 0 | L33: 0 | M33: 0 | N33: 0 | O33: =SUM(C33:N33) -> 0 | Q33: =IF($O$36=0,0,O33/$O$36) -> 0
B34: Transferencia | C34: 0 | D34: 0 | E34: 0 | F34: 0 | G34: 0 | H34: 0 | I34: 0 | J34: 0 | K34: 0 | L34: 0 | M34: 0 | N34: 0 | O34: =SUM(C34:N34) -> 0 | Q34: =IF($O$36=0,0,O34/$O$36) -> 0
B35: MercadoPago | C35: 0 | D35: 0 | E35: 0 | F35: 0 | G35: 0 | H35: 0 | I35: 0 | J35: 0 | K35: 0 | L35: 0 | M35: 0 | N35: 0 | O35: =SUM(C35:N35) -> 0 | Q35: =IF($O$36=0,0,O35/$O$36) -> 0
B36: TOTAL | C36: =SUM(C31:C35) -> 0 | D36: =SUM(D31:D35) -> 0 | E36: =SUM(E31:E35) -> 0 | F36: =SUM(F31:F35) -> 0 | G36: =SUM(G31:G35) -> 0 | H36: =SUM(H31:H35) -> 0 | I36: =SUM(I31:I35) -> 0 | J36: =SUM(J31:J35) -> 0 | ... N36: =SUM(N31:N35) -> 0 | O36: =SUM(C36:N36) -> 0 | Q36: =SUM(Q31:Q35) -> 0
B38: Cargá los montos por método de cada mes (azul). El % es sobre el total cobrado del año.
